
## Javap

Fully javap results.

```javascript
Classfile /Users/saito.masaya/work/io/findify/s3mock/S3Mock.class
  Last modified 2017/06/19; size 16833 bytes
  MD5 checksum 36ba222bfbf5871334a819f5be622889
  Compiled from "S3Mock.scala"
public class io.findify.s3mock.S3Mock implements com.typesafe.scalalogging.LazyLogging
  minor version: 0
  major version: 52
  flags: ACC_PUBLIC, ACC_SUPER
Constant pool:
    #1 = Utf8               io/findify/s3mock/S3Mock
    #2 = Class              #1            // io/findify/s3mock/S3Mock
    #3 = Utf8               java/lang/Object
    #4 = Class              #3            // java/lang/Object
    #5 = Utf8               com/typesafe/scalalogging/LazyLogging
    #6 = Class              #5            // com/typesafe/scalalogging/LazyLogging
    #7 = Utf8               S3Mock.scala
    #8 = Utf8               Lscala/reflect/ScalaSignature;
    #9 = Utf8               bytes
   #10 = Utf8               %dB%aaUN_\'BA8'\8dW*QABM&tG-4z9AA5p2!\tYa\"D\ri!B:dC2BA\r\te.*fMBG%)1F\rgG.7pOLgn+Y\t^=qKNg-/1m\7\ne\"a'bufdunZ4j]DbIHa>H;%a:$BAxN^5eKJ\"A\t\rR!\t\n#)s_ZLG-:\t!!Q!\naa]=tilCA/Q#BA-\t7\r^8siB1lWL!aGo:TsN$X-c!\tAMy%t M:5mAQA!9q\rIA\"B1a\"1\tb%aOaV\t>I!IaBbAI!\t\tLgZB!I\"kb]2bY$72\nA;ua&\nRR$/L\ni1+:wKJN3j]T!!#\t9!a\ny2j]|F%Z9ACAR\tFBV]&$b+N\r!Qq\nB,A&)AcS:$CY)AtiHC[1,ti>X#)u0\rMTj\2l!\t)tLB!m`!)gCER\taCe?Q-AbaBd5M\")1da9!)AmCQRA'6\tm9\t-<7L'ni:aN\t_2ic\"\ta:p_RtBA:\r&/3fM&QO'RN\4Md\"=`\tIAB2sK$X\r5u\")1da9!)pCyRA' @\tmY\t-\7\rqAAU/7eKJ\"a \t\rEzHAA)\t\tIE}la\ny!C#\t1Z3gCVdGU8siV\tAC}\r\"yA-4bk2$k:u?*FQ3AVA\n\r;y)1!WMZ1vYRvN;!!\t\tc a\nYa3fM,H)s_ZLG-:\tr1A\na3fM,H)s_ZLG-:`IHc)*!AA+a\tC.}B!,g-Y;miBxN^5eKJbBA1G\to&$U8siR!BAYqa9!9H@aE<ji\"Le.T3n_JL()Y2lK:$bBAqHo&$NR5mK\n7m[3oIR!BA!\t%aA1A]1uQ\"9qI@%!2vS2$G#\t5s,%A=amKNN\5uIX-;fe\"WMZ1vYR$3Rq\rQM3FAA+!\t9&!e#BA.;\n\"8dQ7.3}C\"b]:|G/;j_:LA!aZ\t\tRO\2iK\W\r,be&gnY3\t\rm\tY11\naC
   #11 = Utf8               akka/http/scaladsl/Http$ServerBinding
   #12 = Class              #11           // akka/http/scaladsl/Http$ServerBinding
   #13 = Utf8               akka/http/scaladsl/Http
   #14 = Class              #13           // akka/http/scaladsl/Http
   #15 = Utf8               ServerBinding
   #16 = Utf8               akka/http/scaladsl/model/StatusCodes$ServerError
   #17 = Class              #16           // akka/http/scaladsl/model/StatusCodes$ServerError
   #18 = Utf8               akka/http/scaladsl/model/StatusCodes
   #19 = Class              #18           // akka/http/scaladsl/model/StatusCodes
   #20 = Utf8               ServerError
   #21 = Utf8               akka/http/scaladsl/model/Uri$Path
   #22 = Class              #21           // akka/http/scaladsl/model/Uri$Path
   #23 = Utf8               akka/http/scaladsl/model/Uri
   #24 = Class              #23           // akka/http/scaladsl/model/Uri
   #25 = Utf8               Path
   #26 = Utf8               akka/http/scaladsl/server/PathMatchers$RemainingPath$
   #27 = Class              #26           // akka/http/scaladsl/server/PathMatchers$RemainingPath$
   #28 = Utf8               akka/http/scaladsl/server/PathMatchers
   #29 = Class              #28           // akka/http/scaladsl/server/PathMatchers
   #30 = Utf8               RemainingPath$
   #31 = Utf8               akka/http/scaladsl/server/PathMatchers$Segment$
   #32 = Class              #31           // akka/http/scaladsl/server/PathMatchers$Segment$
   #33 = Utf8               Segment$
   #34 = Utf8               akka/http/scaladsl/server/RouteConcatenation$RouteWithConcatenation
   #35 = Class              #34           // akka/http/scaladsl/server/RouteConcatenation$RouteWithConcatenation
   #36 = Utf8               akka/http/scaladsl/server/RouteConcatenation
   #37 = Class              #36           // akka/http/scaladsl/server/RouteConcatenation
   #38 = Utf8               RouteWithConcatenation
   #39 = Utf8               io/findify/s3mock/S3Mock$Builder
   #40 = Class              #39           // io/findify/s3mock/S3Mock$Builder
   #41 = Utf8               Builder
   #42 = Utf8               java/lang/invoke/MethodHandles$Lookup
   #43 = Class              #42           // java/lang/invoke/MethodHandles$Lookup
   #44 = Utf8               java/lang/invoke/MethodHandles
   #45 = Class              #44           // java/lang/invoke/MethodHandles
   #46 = Utf8               Lookup
   #47 = Utf8               scala/concurrent/duration/Duration$Infinite
   #48 = Class              #47           // scala/concurrent/duration/Duration$Infinite
   #49 = Utf8               scala/concurrent/duration/Duration
   #50 = Class              #49           // scala/concurrent/duration/Duration
   #51 = Utf8               Infinite
   #52 = Utf8               port
   #53 = Utf8               I
   #54 = Utf8               system
   #55 = Utf8               Lakka/actor/ActorSystem;
   #56 = Utf8               p
   #57 = Utf8               Lio/findify/s3mock/provider/Provider;
   #58 = Utf8               bind
   #59 = Utf8               Lakka/http/scaladsl/Http$ServerBinding;
   #60 = Utf8               logger
   #61 = Utf8               Lcom/typesafe/scalalogging/Logger;
   #62 = Utf8               bitmap$0
   #63 = Utf8               Z
   #64 = Utf8               $lessinit$greater$default$3
   #65 = Utf8               (ILio/findify/s3mock/provider/Provider;)Lakka/actor/ActorSystem;
   #66 = Utf8               io/findify/s3mock/S3Mock$
   #67 = Class              #66           // io/findify/s3mock/S3Mock$
   #68 = Utf8               MODULE$
   #69 = Utf8               Lio/findify/s3mock/S3Mock$;
   #70 = NameAndType        #68:#69       // MODULE$:Lio/findify/s3mock/S3Mock$;
   #71 = Fieldref           #67.#70       // io/findify/s3mock/S3Mock$.MODULE$:Lio/findify/s3mock/S3Mock$;
   #72 = NameAndType        #64:#65       // $lessinit$greater$default$3:(ILio/findify/s3mock/provider/Provider;)Lakka/actor/ActorSystem;
   #73 = Methodref          #67.#72       // io/findify/s3mock/S3Mock$.$lessinit$greater$default$3:(ILio/findify/s3mock/provider/Provider;)Lakka/actor/ActorSystem;
   #74 = Utf8               create
   #75 = Utf8               (ILjava/lang/String;)Lio/findify/s3mock/S3Mock;
   #76 = NameAndType        #74:#75       // create:(ILjava/lang/String;)Lio/findify/s3mock/S3Mock;
   #77 = Methodref          #67.#76       // io/findify/s3mock/S3Mock$.create:(ILjava/lang/String;)Lio/findify/s3mock/S3Mock;
   #78 = Utf8               (I)Lio/findify/s3mock/S3Mock;
   #79 = NameAndType        #74:#78       // create:(I)Lio/findify/s3mock/S3Mock;
   #80 = Methodref          #67.#79       // io/findify/s3mock/S3Mock$.create:(I)Lio/findify/s3mock/S3Mock;
   #81 = Utf8               apply
   #82 = NameAndType        #81:#75       // apply:(ILjava/lang/String;)Lio/findify/s3mock/S3Mock;
   #83 = Methodref          #67.#82       // io/findify/s3mock/S3Mock$.apply:(ILjava/lang/String;)Lio/findify/s3mock/S3Mock;
   #84 = NameAndType        #81:#78       // apply:(I)Lio/findify/s3mock/S3Mock;
   #85 = Methodref          #67.#84       // io/findify/s3mock/S3Mock$.apply:(I)Lio/findify/s3mock/S3Mock;
   #86 = Utf8               logger$lzycompute
   #87 = Utf8               ()Lcom/typesafe/scalalogging/Logger;
   #88 = NameAndType        #62:#63       // bitmap$0:Z
   #89 = Fieldref           #2.#88        // io/findify/s3mock/S3Mock.bitmap$0:Z
   #90 = Utf8               logger$
   #91 = Utf8               (Lcom/typesafe/scalalogging/LazyLogging;)Lcom/typesafe/scalalogging/Logger;
   #92 = NameAndType        #90:#91       // logger$:(Lcom/typesafe/scalalogging/LazyLogging;)Lcom/typesafe/scalalogging/Logger;
   #93 = InterfaceMethodref #6.#92        // com/typesafe/scalalogging/LazyLogging.logger$:(Lcom/typesafe/scalalogging/LazyLogging;)Lcom/typesafe/scalalogging/Logger;
   #94 = NameAndType        #60:#61       // logger:Lcom/typesafe/scalalogging/Logger;
   #95 = Fieldref           #2.#94        // io/findify/s3mock/S3Mock.logger:Lcom/typesafe/scalalogging/Logger;
   #96 = Utf8               this
   #97 = Utf8               Lio/findify/s3mock/S3Mock;
   #98 = Utf8               java/lang/Throwable
   #99 = Class              #98           // java/lang/Throwable
  #100 = NameAndType        #86:#87       // logger$lzycompute:()Lcom/typesafe/scalalogging/Logger;
  #101 = Methodref          #2.#100       // io/findify/s3mock/S3Mock.logger$lzycompute:()Lcom/typesafe/scalalogging/Logger;
  #102 = Utf8               com/typesafe/scalalogging/Logger
  #103 = Class              #102          // com/typesafe/scalalogging/Logger
  #104 = Utf8               ()Lio/findify/s3mock/provider/Provider;
  #105 = NameAndType        #56:#57       // p:Lio/findify/s3mock/provider/Provider;
  #106 = Fieldref           #2.#105       // io/findify/s3mock/S3Mock.p:Lio/findify/s3mock/provider/Provider;
  #107 = Utf8               ()Lakka/http/scaladsl/Http$ServerBinding;
  #108 = NameAndType        #58:#59       // bind:Lakka/http/scaladsl/Http$ServerBinding;
  #109 = Fieldref           #2.#108       // io/findify/s3mock/S3Mock.bind:Lakka/http/scaladsl/Http$ServerBinding;
  #110 = Utf8               bind_$eq
  #111 = Utf8               (Lakka/http/scaladsl/Http$ServerBinding;)V
  #112 = Utf8               x$1
  #113 = Utf8               start
  #114 = Utf8               akka/stream/ActorMaterializer$
  #115 = Class              #114          // akka/stream/ActorMaterializer$
  #116 = Utf8               Lakka/stream/ActorMaterializer$;
  #117 = NameAndType        #68:#116      // MODULE$:Lakka/stream/ActorMaterializer$;
  #118 = Fieldref           #115.#117     // akka/stream/ActorMaterializer$.MODULE$:Lakka/stream/ActorMaterializer$;
  #119 = Utf8               apply$default$1
  #120 = Utf8               ()Lscala/Option;
  #121 = NameAndType        #119:#120     // apply$default$1:()Lscala/Option;
  #122 = Methodref          #115.#121     // akka/stream/ActorMaterializer$.apply$default$1:()Lscala/Option;
  #123 = Utf8               apply$default$2
  #124 = NameAndType        #123:#120     // apply$default$2:()Lscala/Option;
  #125 = Methodref          #115.#124     // akka/stream/ActorMaterializer$.apply$default$2:()Lscala/Option;
  #126 = NameAndType        #54:#55       // system:Lakka/actor/ActorSystem;
  #127 = Fieldref           #2.#126       // io/findify/s3mock/S3Mock.system:Lakka/actor/ActorSystem;
  #128 = Utf8               (Lscala/Option;Lscala/Option;Lakka/actor/ActorRefFactory;)Lakka/stream/ActorMaterializer;
  #129 = NameAndType        #81:#128      // apply:(Lscala/Option;Lscala/Option;Lakka/actor/ActorRefFactory;)Lakka/stream/ActorMaterializer;
  #130 = Methodref          #115.#129     // akka/stream/ActorMaterializer$.apply:(Lscala/Option;Lscala/Option;Lakka/actor/ActorRefFactory;)Lakka/stream/ActorMaterializer;
  #131 = Utf8               akka/http/scaladsl/Http$
  #132 = Class              #131          // akka/http/scaladsl/Http$
  #133 = Utf8               Lakka/http/scaladsl/Http$;
  #134 = NameAndType        #68:#133      // MODULE$:Lakka/http/scaladsl/Http$;
  #135 = Fieldref           #132.#134     // akka/http/scaladsl/Http$.MODULE$:Lakka/http/scaladsl/Http$;
  #136 = Utf8               (Lakka/actor/ActorSystem;)Lakka/actor/Extension;
  #137 = NameAndType        #81:#136      // apply:(Lakka/actor/ActorSystem;)Lakka/actor/Extension;
  #138 = Methodref          #132.#137     // akka/http/scaladsl/Http$.apply:(Lakka/actor/ActorSystem;)Lakka/actor/Extension;
  #139 = Utf8               akka/http/scaladsl/HttpExt
  #140 = Class              #139          // akka/http/scaladsl/HttpExt
  #141 = Utf8               akka/http/scaladsl/server/Directives$
  #142 = Class              #141          // akka/http/scaladsl/server/Directives$
  #143 = Utf8               Lakka/http/scaladsl/server/Directives$;
  #144 = NameAndType        #68:#143      // MODULE$:Lakka/http/scaladsl/server/Directives$;
  #145 = Fieldref           #142.#144     // akka/http/scaladsl/server/Directives$.MODULE$:Lakka/http/scaladsl/server/Directives$;
  #146 = Utf8               akka/http/scaladsl/server/Directive$
  #147 = Class              #146          // akka/http/scaladsl/server/Directive$
  #148 = Utf8               Lakka/http/scaladsl/server/Directive$;
  #149 = NameAndType        #68:#148      // MODULE$:Lakka/http/scaladsl/server/Directive$;
  #150 = Fieldref           #147.#149     // akka/http/scaladsl/server/Directive$.MODULE$:Lakka/http/scaladsl/server/Directive$;
  #151 = Utf8               Segment
  #152 = Utf8               ()Lakka/http/scaladsl/server/PathMatchers$Segment$;
  #153 = NameAndType        #151:#152     // Segment:()Lakka/http/scaladsl/server/PathMatchers$Segment$;
  #154 = Methodref          #142.#153     // akka/http/scaladsl/server/Directives$.Segment:()Lakka/http/scaladsl/server/PathMatchers$Segment$;
  #155 = Utf8               pathPrefix
  #156 = Utf8               (Lakka/http/scaladsl/server/PathMatcher;)Lakka/http/scaladsl/server/Directive;
  #157 = NameAndType        #155:#156     // pathPrefix:(Lakka/http/scaladsl/server/PathMatcher;)Lakka/http/scaladsl/server/Directive;
  #158 = Methodref          #142.#157     // akka/http/scaladsl/server/Directives$.pathPrefix:(Lakka/http/scaladsl/server/PathMatcher;)Lakka/http/scaladsl/server/Directive;
  #159 = Utf8               akka/http/scaladsl/server/util/ApplyConverter$
  #160 = Class              #159          // akka/http/scaladsl/server/util/ApplyConverter$
  #161 = Utf8               Lakka/http/scaladsl/server/util/ApplyConverter$;
  #162 = NameAndType        #68:#161      // MODULE$:Lakka/http/scaladsl/server/util/ApplyConverter$;
  #163 = Fieldref           #160.#162     // akka/http/scaladsl/server/util/ApplyConverter$.MODULE$:Lakka/http/scaladsl/server/util/ApplyConverter$;
  #164 = Utf8               hac1
  #165 = Utf8               ()Lakka/http/scaladsl/server/util/ApplyConverter;
  #166 = NameAndType        #164:#165     // hac1:()Lakka/http/scaladsl/server/util/ApplyConverter;
  #167 = Methodref          #160.#166     // akka/http/scaladsl/server/util/ApplyConverter$.hac1:()Lakka/http/scaladsl/server/util/ApplyConverter;
  #168 = Utf8               addDirectiveApply
  #169 = Utf8               (Lakka/http/scaladsl/server/Directive;Lakka/http/scaladsl/server/util/ApplyConverter;)Lscala/Function1;
  #170 = NameAndType        #168:#169     // addDirectiveApply:(Lakka/http/scaladsl/server/Directive;Lakka/http/scaladsl/server/util/ApplyConverter;)Lscala/Function1;
  #171 = Methodref          #147.#170     // akka/http/scaladsl/server/Directive$.addDirectiveApply:(Lakka/http/scaladsl/server/Directive;Lakka/http/scaladsl/server/util/ApplyConverter;)Lscala/Function1;
  #172 = Utf8               java/lang/invoke/LambdaMetafactory
  #173 = Class              #172          // java/lang/invoke/LambdaMetafactory
  #174 = Utf8               altMetafactory
  #175 = Utf8               (Ljava/lang/invoke/MethodHandles$Lookup;Ljava/lang/String;Ljava/lang/invoke/MethodType;[Ljava/lang/Object;)Ljava/lang/invoke/CallSite;
  #176 = NameAndType        #174:#175     // altMetafactory:(Ljava/lang/invoke/MethodHandles$Lookup;Ljava/lang/String;Ljava/lang/invoke/MethodType;[Ljava/lang/Object;)Ljava/lang/invoke/CallSite;
  #177 = Methodref          #173.#176     // java/lang/invoke/LambdaMetafactory.altMetafactory:(Ljava/lang/invoke/MethodHandles$Lookup;Ljava/lang/String;Ljava/lang/invoke/MethodType;[Ljava/lang/Object;)Ljava/lang/invoke/CallSite;
  #178 = MethodHandle       #6:#177       // invokestatic java/lang/invoke/LambdaMetafactory.altMetafactory:(Ljava/lang/invoke/MethodHandles$Lookup;Ljava/lang/String;Ljava/lang/invoke/MethodType;[Ljava/lang/Object;)Ljava/lang/invoke/CallSite;
  #179 = Utf8               (Ljava/lang/Object;)Ljava/lang/Object;
  #180 = MethodType         #179          //  (Ljava/lang/Object;)Ljava/lang/Object;
  #181 = Utf8               $anonfun$start$1
  #182 = Utf8               (Lio/findify/s3mock/S3Mock;Lakka/stream/ActorMaterializer;Ljava/lang/String;)Lscala/Function1;
  #183 = NameAndType        #181:#182     // $anonfun$start$1:(Lio/findify/s3mock/S3Mock;Lakka/stream/ActorMaterializer;Ljava/lang/String;)Lscala/Function1;
  #184 = Methodref          #2.#183       // io/findify/s3mock/S3Mock.$anonfun$start$1:(Lio/findify/s3mock/S3Mock;Lakka/stream/ActorMaterializer;Ljava/lang/String;)Lscala/Function1;
  #185 = MethodHandle       #6:#184       // invokestatic io/findify/s3mock/S3Mock.$anonfun$start$1:(Lio/findify/s3mock/S3Mock;Lakka/stream/ActorMaterializer;Ljava/lang/String;)Lscala/Function1;
  #186 = Utf8               (Ljava/lang/String;)Lscala/Function1;
  #187 = MethodType         #186          //  (Ljava/lang/String;)Lscala/Function1;
  #188 = Integer            3
  #189 = Integer            1
  #190 = Utf8               scala/Serializable
  #191 = Class              #190          // scala/Serializable
  #192 = Utf8               (Lio/findify/s3mock/S3Mock;Lakka/stream/ActorMaterializer;)Lscala/Function1;
  #193 = NameAndType        #81:#192      // apply:(Lio/findify/s3mock/S3Mock;Lakka/stream/ActorMaterializer;)Lscala/Function1;
  #194 = InvokeDynamic      #0:#193       // #0:apply:(Lio/findify/s3mock/S3Mock;Lakka/stream/ActorMaterializer;)Lscala/Function1;
  #195 = Utf8               scala/Function1
  #196 = Class              #195          // scala/Function1
  #197 = NameAndType        #81:#179      // apply:(Ljava/lang/Object;)Ljava/lang/Object;
  #198 = InterfaceMethodref #196.#197     // scala/Function1.apply:(Ljava/lang/Object;)Ljava/lang/Object;
  #199 = Utf8               _enhanceRouteWithConcatenation
  #200 = Utf8               (Lscala/Function1;)Lakka/http/scaladsl/server/RouteConcatenation$RouteWithConcatenation;
  #201 = NameAndType        #199:#200     // _enhanceRouteWithConcatenation:(Lscala/Function1;)Lakka/http/scaladsl/server/RouteConcatenation$RouteWithConcatenation;
  #202 = Methodref          #142.#201     // akka/http/scaladsl/server/Directives$._enhanceRouteWithConcatenation:(Lscala/Function1;)Lakka/http/scaladsl/server/RouteConcatenation$RouteWithConcatenation;
  #203 = Utf8               io/findify/s3mock/route/ListBuckets
  #204 = Class              #203          // io/findify/s3mock/route/ListBuckets
  #205 = NameAndType        #56:#104      // p:()Lio/findify/s3mock/provider/Provider;
  #206 = Methodref          #2.#205       // io/findify/s3mock/S3Mock.p:()Lio/findify/s3mock/provider/Provider;
  #207 = Utf8               <init>
  #208 = Utf8               (Lio/findify/s3mock/provider/Provider;)V
  #209 = NameAndType        #207:#208     // "<init>":(Lio/findify/s3mock/provider/Provider;)V
  #210 = Methodref          #204.#209     // io/findify/s3mock/route/ListBuckets."<init>":(Lio/findify/s3mock/provider/Provider;)V
  #211 = Utf8               route
  #212 = Utf8               ()Lscala/Function1;
  #213 = NameAndType        #211:#212     // route:()Lscala/Function1;
  #214 = Methodref          #204.#213     // io/findify/s3mock/route/ListBuckets.route:()Lscala/Function1;
  #215 = Utf8               $tilde
  #216 = Utf8               (Lscala/Function1;)Lscala/Function1;
  #217 = NameAndType        #215:#216     // $tilde:(Lscala/Function1;)Lscala/Function1;
  #218 = Methodref          #35.#217      // akka/http/scaladsl/server/RouteConcatenation$RouteWithConcatenation.$tilde:(Lscala/Function1;)Lscala/Function1;
  #219 = Utf8               extractRequest
  #220 = Utf8               ()Lakka/http/scaladsl/server/Directive;
  #221 = NameAndType        #219:#220     // extractRequest:()Lakka/http/scaladsl/server/Directive;
  #222 = Methodref          #142.#221     // akka/http/scaladsl/server/Directives$.extractRequest:()Lakka/http/scaladsl/server/Directive;
  #223 = Utf8               $anonfun$start$6
  #224 = Utf8               (Lio/findify/s3mock/S3Mock;Lakka/http/scaladsl/model/HttpRequest;)Lakka/http/scaladsl/server/StandardRoute;
  #225 = NameAndType        #223:#224     // $anonfun$start$6:(Lio/findify/s3mock/S3Mock;Lakka/http/scaladsl/model/HttpRequest;)Lakka/http/scaladsl/server/StandardRoute;
  #226 = Methodref          #2.#225       // io/findify/s3mock/S3Mock.$anonfun$start$6:(Lio/findify/s3mock/S3Mock;Lakka/http/scaladsl/model/HttpRequest;)Lakka/http/scaladsl/server/StandardRoute;
  #227 = MethodHandle       #6:#226       // invokestatic io/findify/s3mock/S3Mock.$anonfun$start$6:(Lio/findify/s3mock/S3Mock;Lakka/http/scaladsl/model/HttpRequest;)Lakka/http/scaladsl/server/StandardRoute;
  #228 = Utf8               (Lakka/http/scaladsl/model/HttpRequest;)Lakka/http/scaladsl/server/StandardRoute;
  #229 = MethodType         #228          //  (Lakka/http/scaladsl/model/HttpRequest;)Lakka/http/scaladsl/server/StandardRoute;
  #230 = Utf8               (Lio/findify/s3mock/S3Mock;)Lscala/Function1;
  #231 = NameAndType        #81:#230      // apply:(Lio/findify/s3mock/S3Mock;)Lscala/Function1;
  #232 = InvokeDynamic      #1:#231       // #1:apply:(Lio/findify/s3mock/S3Mock;)Lscala/Function1;
  #233 = Utf8               scala/concurrent/Await$
  #234 = Class              #233          // scala/concurrent/Await$
  #235 = Utf8               Lscala/concurrent/Await$;
  #236 = NameAndType        #68:#235      // MODULE$:Lscala/concurrent/Await$;
  #237 = Fieldref           #234.#236     // scala/concurrent/Await$.MODULE$:Lscala/concurrent/Await$;
  #238 = Utf8               akka/http/scaladsl/settings/RoutingSettings$
  #239 = Class              #238          // akka/http/scaladsl/settings/RoutingSettings$
  #240 = Utf8               Lakka/http/scaladsl/settings/RoutingSettings$;
  #241 = NameAndType        #68:#240      // MODULE$:Lakka/http/scaladsl/settings/RoutingSettings$;
  #242 = Fieldref           #239.#241     // akka/http/scaladsl/settings/RoutingSettings$.MODULE$:Lakka/http/scaladsl/settings/RoutingSettings$;
  #243 = Utf8               default
  #244 = Utf8               (Lakka/actor/ActorRefFactory;)Ljava/lang/Object;
  #245 = NameAndType        #243:#244     // default:(Lakka/actor/ActorRefFactory;)Ljava/lang/Object;
  #246 = Methodref          #239.#245     // akka/http/scaladsl/settings/RoutingSettings$.default:(Lakka/actor/ActorRefFactory;)Ljava/lang/Object;
  #247 = Utf8               akka/http/scaladsl/settings/RoutingSettings
  #248 = Class              #247          // akka/http/scaladsl/settings/RoutingSettings
  #249 = Utf8               akka/http/scaladsl/settings/ParserSettings$
  #250 = Class              #249          // akka/http/scaladsl/settings/ParserSettings$
  #251 = Utf8               Lakka/http/scaladsl/settings/ParserSettings$;
  #252 = NameAndType        #68:#251      // MODULE$:Lakka/http/scaladsl/settings/ParserSettings$;
  #253 = Fieldref           #250.#252     // akka/http/scaladsl/settings/ParserSettings$.MODULE$:Lakka/http/scaladsl/settings/ParserSettings$;
  #254 = Methodref          #250.#245     // akka/http/scaladsl/settings/ParserSettings$.default:(Lakka/actor/ActorRefFactory;)Ljava/lang/Object;
  #255 = Utf8               akka/http/scaladsl/settings/ParserSettings
  #256 = Class              #255          // akka/http/scaladsl/settings/ParserSettings
  #257 = Utf8               akka/http/scaladsl/server/RoutingLog$
  #258 = Class              #257          // akka/http/scaladsl/server/RoutingLog$
  #259 = Utf8               Lakka/http/scaladsl/server/RoutingLog$;
  #260 = NameAndType        #68:#259      // MODULE$:Lakka/http/scaladsl/server/RoutingLog$;
  #261 = Fieldref           #258.#260     // akka/http/scaladsl/server/RoutingLog$.MODULE$:Lakka/http/scaladsl/server/RoutingLog$;
  #262 = Utf8               fromActorSystem
  #263 = Utf8               (Lakka/actor/ActorSystem;)Lakka/http/scaladsl/server/RoutingLog;
  #264 = NameAndType        #262:#263     // fromActorSystem:(Lakka/actor/ActorSystem;)Lakka/http/scaladsl/server/RoutingLog;
  #265 = Methodref          #258.#264     // akka/http/scaladsl/server/RoutingLog$.fromActorSystem:(Lakka/actor/ActorSystem;)Lakka/http/scaladsl/server/RoutingLog;
  #266 = Utf8               akka/http/scaladsl/server/RouteResult$
  #267 = Class              #266          // akka/http/scaladsl/server/RouteResult$
  #268 = Utf8               Lakka/http/scaladsl/server/RouteResult$;
  #269 = NameAndType        #68:#268      // MODULE$:Lakka/http/scaladsl/server/RouteResult$;
  #270 = Fieldref           #267.#269     // akka/http/scaladsl/server/RouteResult$.MODULE$:Lakka/http/scaladsl/server/RouteResult$;
  #271 = Utf8               route2HandlerFlow$default$6
  #272 = Utf8               (Lscala/Function1;)Lscala/concurrent/ExecutionContext;
  #273 = NameAndType        #271:#272     // route2HandlerFlow$default$6:(Lscala/Function1;)Lscala/concurrent/ExecutionContext;
  #274 = Methodref          #267.#273     // akka/http/scaladsl/server/RouteResult$.route2HandlerFlow$default$6:(Lscala/Function1;)Lscala/concurrent/ExecutionContext;
  #275 = Utf8               route2HandlerFlow$default$7
  #276 = Utf8               (Lscala/Function1;)Lakka/http/scaladsl/server/RejectionHandler;
  #277 = NameAndType        #275:#276     // route2HandlerFlow$default$7:(Lscala/Function1;)Lakka/http/scaladsl/server/RejectionHandler;
  #278 = Methodref          #267.#277     // akka/http/scaladsl/server/RouteResult$.route2HandlerFlow$default$7:(Lscala/Function1;)Lakka/http/scaladsl/server/RejectionHandler;
  #279 = Utf8               route2HandlerFlow$default$8
  #280 = Utf8               (Lscala/Function1;)Lakka/http/scaladsl/server/ExceptionHandler;
  #281 = NameAndType        #279:#280     // route2HandlerFlow$default$8:(Lscala/Function1;)Lakka/http/scaladsl/server/ExceptionHandler;
  #282 = Methodref          #267.#281     // akka/http/scaladsl/server/RouteResult$.route2HandlerFlow$default$8:(Lscala/Function1;)Lakka/http/scaladsl/server/ExceptionHandler;
  #283 = Utf8               route2HandlerFlow
  #284 = Utf8               (Lscala/Function1;Lakka/http/scaladsl/settings/RoutingSettings;Lakka/http/scaladsl/settings/ParserSettings;Lakka/stream/Materializer;Lakka/http/scaladsl/server/RoutingLog;Lscala/concurrent/ExecutionContext;Lakka/http/scaladsl/server/RejectionHandler;Lakka/http/scaladsl/server/ExceptionHandler;)Lakka/stream/scaladsl/Flow;
  #285 = NameAndType        #283:#284     // route2HandlerFlow:(Lscala/Function1;Lakka/http/scaladsl/settings/RoutingSettings;Lakka/http/scaladsl/settings/ParserSettings;Lakka/stream/Materializer;Lakka/http/scaladsl/server/RoutingLog;Lscala/concurrent/ExecutionContext;Lakka/http/scaladsl/server/RejectionHandler;Lakka/http/scaladsl/server/ExceptionHandler;)Lakka/stream/scaladsl/Flow;
  #286 = Methodref          #267.#285     // akka/http/scaladsl/server/RouteResult$.route2HandlerFlow:(Lscala/Function1;Lakka/http/scaladsl/settings/RoutingSettings;Lakka/http/scaladsl/settings/ParserSettings;Lakka/stream/Materializer;Lakka/http/scaladsl/server/RoutingLog;Lscala/concurrent/ExecutionContext;Lakka/http/scaladsl/server/RejectionHandler;Lakka/http/scaladsl/server/ExceptionHandler;)Lakka/stream/scaladsl/Flow;
  #287 = Utf8               localhost
  #288 = String             #287          // localhost
  #289 = NameAndType        #52:#53       // port:I
  #290 = Fieldref           #2.#289       // io/findify/s3mock/S3Mock.port:I
  #291 = Utf8               bindAndHandle$default$4
  #292 = Utf8               ()Lakka/http/scaladsl/ConnectionContext;
  #293 = NameAndType        #291:#292     // bindAndHandle$default$4:()Lakka/http/scaladsl/ConnectionContext;
  #294 = Methodref          #140.#293     // akka/http/scaladsl/HttpExt.bindAndHandle$default$4:()Lakka/http/scaladsl/ConnectionContext;
  #295 = Utf8               bindAndHandle$default$5
  #296 = Utf8               ()Lakka/http/scaladsl/settings/ServerSettings;
  #297 = NameAndType        #295:#296     // bindAndHandle$default$5:()Lakka/http/scaladsl/settings/ServerSettings;
  #298 = Methodref          #140.#297     // akka/http/scaladsl/HttpExt.bindAndHandle$default$5:()Lakka/http/scaladsl/settings/ServerSettings;
  #299 = Utf8               bindAndHandle$default$6
  #300 = Utf8               ()Lakka/event/LoggingAdapter;
  #301 = NameAndType        #299:#300     // bindAndHandle$default$6:()Lakka/event/LoggingAdapter;
  #302 = Methodref          #140.#301     // akka/http/scaladsl/HttpExt.bindAndHandle$default$6:()Lakka/event/LoggingAdapter;
  #303 = Utf8               bindAndHandle
  #304 = Utf8               (Lakka/stream/scaladsl/Flow;Ljava/lang/String;ILakka/http/scaladsl/ConnectionContext;Lakka/http/scaladsl/settings/ServerSettings;Lakka/event/LoggingAdapter;Lakka/stream/Materializer;)Lscala/concurrent/Future;
  #305 = NameAndType        #303:#304     // bindAndHandle:(Lakka/stream/scaladsl/Flow;Ljava/lang/String;ILakka/http/scaladsl/ConnectionContext;Lakka/http/scaladsl/settings/ServerSettings;Lakka/event/LoggingAdapter;Lakka/stream/Materializer;)Lscala/concurrent/Future;
  #306 = Methodref          #140.#305     // akka/http/scaladsl/HttpExt.bindAndHandle:(Lakka/stream/scaladsl/Flow;Ljava/lang/String;ILakka/http/scaladsl/ConnectionContext;Lakka/http/scaladsl/settings/ServerSettings;Lakka/event/LoggingAdapter;Lakka/stream/Materializer;)Lscala/concurrent/Future;
  #307 = Utf8               scala/concurrent/duration/Duration$
  #308 = Class              #307          // scala/concurrent/duration/Duration$
  #309 = Utf8               Lscala/concurrent/duration/Duration$;
  #310 = NameAndType        #68:#309      // MODULE$:Lscala/concurrent/duration/Duration$;
  #311 = Fieldref           #308.#310     // scala/concurrent/duration/Duration$.MODULE$:Lscala/concurrent/duration/Duration$;
  #312 = Utf8               Inf
  #313 = Utf8               ()Lscala/concurrent/duration/Duration$Infinite;
  #314 = NameAndType        #312:#313     // Inf:()Lscala/concurrent/duration/Duration$Infinite;
  #315 = Methodref          #308.#314     // scala/concurrent/duration/Duration$.Inf:()Lscala/concurrent/duration/Duration$Infinite;
  #316 = Utf8               result
  #317 = Utf8               (Lscala/concurrent/Awaitable;Lscala/concurrent/duration/Duration;)Ljava/lang/Object;
  #318 = NameAndType        #316:#317     // result:(Lscala/concurrent/Awaitable;Lscala/concurrent/duration/Duration;)Ljava/lang/Object;
  #319 = Methodref          #234.#318     // scala/concurrent/Await$.result:(Lscala/concurrent/Awaitable;Lscala/concurrent/duration/Duration;)Ljava/lang/Object;
  #320 = NameAndType        #110:#111     // bind_$eq:(Lakka/http/scaladsl/Http$ServerBinding;)V
  #321 = Methodref          #2.#320       // io/findify/s3mock/S3Mock.bind_$eq:(Lakka/http/scaladsl/Http$ServerBinding;)V
  #322 = NameAndType        #58:#107      // bind:()Lakka/http/scaladsl/Http$ServerBinding;
  #323 = Methodref          #2.#322       // io/findify/s3mock/S3Mock.bind:()Lakka/http/scaladsl/Http$ServerBinding;
  #324 = Utf8               Lscala/Function1;
  #325 = Utf8               x$2
  #326 = Utf8               Lakka/http/scaladsl/settings/RoutingSettings;
  #327 = Utf8               x$3
  #328 = Utf8               Lakka/http/scaladsl/settings/ParserSettings;
  #329 = Utf8               x$4
  #330 = Utf8               Lakka/stream/ActorMaterializer;
  #331 = Utf8               x$5
  #332 = Utf8               Lakka/http/scaladsl/server/RoutingLog;
  #333 = Utf8               x$6
  #334 = Utf8               Lscala/concurrent/ExecutionContext;
  #335 = Utf8               x$7
  #336 = Utf8               Lakka/http/scaladsl/server/RejectionHandler;
  #337 = Utf8               x$8
  #338 = Utf8               Lakka/http/scaladsl/server/ExceptionHandler;
  #339 = Utf8               mat
  #340 = Utf8               http
  #341 = Utf8               Lakka/http/scaladsl/HttpExt;
  #342 = Utf8               stop
  #343 = Utf8               ()V
  #344 = Utf8               unbind
  #345 = Utf8               ()Lscala/concurrent/Future;
  #346 = NameAndType        #344:#345     // unbind:()Lscala/concurrent/Future;
  #347 = Methodref          #12.#346      // akka/http/scaladsl/Http$ServerBinding.unbind:()Lscala/concurrent/Future;
  #348 = Utf8               $anonfun$start$2
  #349 = Utf8               (Lio/findify/s3mock/S3Mock;Ljava/lang/String;)Lscala/Function1;
  #350 = Utf8               $this
  #351 = Utf8               bucket$1
  #352 = Utf8               scala/Predef$
  #353 = Class              #352          // scala/Predef$
  #354 = Utf8               Lscala/Predef$;
  #355 = NameAndType        #68:#354      // MODULE$:Lscala/Predef$;
  #356 = Fieldref           #353.#355     // scala/Predef$.MODULE$:Lscala/Predef$;
  #357 = Utf8               io/findify/s3mock/route/ListBucket
  #358 = Class              #357          // io/findify/s3mock/route/ListBucket
  #359 = Methodref          #358.#209     // io/findify/s3mock/route/ListBucket."<init>":(Lio/findify/s3mock/provider/Provider;)V
  #360 = NameAndType        #211:#186     // route:(Ljava/lang/String;)Lscala/Function1;
  #361 = Methodref          #358.#360     // io/findify/s3mock/route/ListBucket.route:(Ljava/lang/String;)Lscala/Function1;
  #362 = Utf8               io/findify/s3mock/route/CreateBucket
  #363 = Class              #362          // io/findify/s3mock/route/CreateBucket
  #364 = Methodref          #363.#209     // io/findify/s3mock/route/CreateBucket."<init>":(Lio/findify/s3mock/provider/Provider;)V
  #365 = Methodref          #363.#360     // io/findify/s3mock/route/CreateBucket.route:(Ljava/lang/String;)Lscala/Function1;
  #366 = Utf8               io/findify/s3mock/route/DeleteBucket
  #367 = Class              #366          // io/findify/s3mock/route/DeleteBucket
  #368 = Methodref          #367.#209     // io/findify/s3mock/route/DeleteBucket."<init>":(Lio/findify/s3mock/provider/Provider;)V
  #369 = Methodref          #367.#360     // io/findify/s3mock/route/DeleteBucket.route:(Ljava/lang/String;)Lscala/Function1;
  #370 = Utf8               io/findify/s3mock/route/DeleteObjects
  #371 = Class              #370          // io/findify/s3mock/route/DeleteObjects
  #372 = Methodref          #371.#209     // io/findify/s3mock/route/DeleteObjects."<init>":(Lio/findify/s3mock/provider/Provider;)V
  #373 = Methodref          #371.#360     // io/findify/s3mock/route/DeleteObjects.route:(Ljava/lang/String;)Lscala/Function1;
  #374 = Utf8               [Ljava/lang/Object;
  #375 = Class              #374          // "[Ljava/lang/Object;"
  #376 = Utf8               wrapRefArray
  #377 = Utf8               ([Ljava/lang/Object;)Lscala/collection/mutable/WrappedArray;
  #378 = NameAndType        #376:#377     // wrapRefArray:([Ljava/lang/Object;)Lscala/collection/mutable/WrappedArray;
  #379 = Methodref          #353.#378     // scala/Predef$.wrapRefArray:([Ljava/lang/Object;)Lscala/collection/mutable/WrappedArray;
  #380 = Utf8               concat
  #381 = Utf8               (Lscala/collection/Seq;)Lscala/Function1;
  #382 = NameAndType        #380:#381     // concat:(Lscala/collection/Seq;)Lscala/Function1;
  #383 = Methodref          #142.#382     // akka/http/scaladsl/server/Directives$.concat:(Lscala/collection/Seq;)Lscala/Function1;
  #384 = Utf8               Ljava/lang/String;
  #385 = Utf8               $anonfun$start$3
  #386 = Utf8               $anonfun$start$5
  #387 = Utf8               (Lio/findify/s3mock/S3Mock;Lakka/stream/ActorMaterializer;Ljava/lang/String;Lscala/collection/immutable/Map;Lakka/http/scaladsl/model/Uri$Path;)Lscala/Function1;
  #388 = Utf8               mat$1
  #389 = Utf8               params$1
  #390 = Utf8               key
  #391 = Utf8               io/findify/s3mock/route/GetObject
  #392 = Class              #391          // io/findify/s3mock/route/GetObject
  #393 = Methodref          #392.#209     // io/findify/s3mock/route/GetObject."<init>":(Lio/findify/s3mock/provider/Provider;)V
  #394 = Utf8               toString
  #395 = Utf8               ()Ljava/lang/String;
  #396 = NameAndType        #394:#395     // toString:()Ljava/lang/String;
  #397 = Methodref          #22.#396      // akka/http/scaladsl/model/Uri$Path.toString:()Ljava/lang/String;
  #398 = Utf8               (Ljava/lang/String;Ljava/lang/String;Lscala/collection/immutable/Map;)Lscala/Function1;
  #399 = NameAndType        #211:#398     // route:(Ljava/lang/String;Ljava/lang/String;Lscala/collection/immutable/Map;)Lscala/Function1;
  #400 = Methodref          #392.#399     // io/findify/s3mock/route/GetObject.route:(Ljava/lang/String;Ljava/lang/String;Lscala/collection/immutable/Map;)Lscala/Function1;
  #401 = Utf8               io/findify/s3mock/route/CopyObject
  #402 = Class              #401          // io/findify/s3mock/route/CopyObject
  #403 = Methodref          #402.#209     // io/findify/s3mock/route/CopyObject."<init>":(Lio/findify/s3mock/provider/Provider;)V
  #404 = Utf8               (Ljava/lang/String;Ljava/lang/String;)Lscala/Function1;
  #405 = NameAndType        #211:#404     // route:(Ljava/lang/String;Ljava/lang/String;)Lscala/Function1;
  #406 = Methodref          #402.#405     // io/findify/s3mock/route/CopyObject.route:(Ljava/lang/String;Ljava/lang/String;)Lscala/Function1;
  #407 = Utf8               io/findify/s3mock/route/PutObjectMultipart
  #408 = Class              #407          // io/findify/s3mock/route/PutObjectMultipart
  #409 = Utf8               (Lio/findify/s3mock/provider/Provider;Lakka/stream/Materializer;)V
  #410 = NameAndType        #207:#409     // "<init>":(Lio/findify/s3mock/provider/Provider;Lakka/stream/Materializer;)V
  #411 = Methodref          #408.#410     // io/findify/s3mock/route/PutObjectMultipart."<init>":(Lio/findify/s3mock/provider/Provider;Lakka/stream/Materializer;)V
  #412 = Methodref          #408.#405     // io/findify/s3mock/route/PutObjectMultipart.route:(Ljava/lang/String;Ljava/lang/String;)Lscala/Function1;
  #413 = Utf8               io/findify/s3mock/route/PutObjectMultipartStart
  #414 = Class              #413          // io/findify/s3mock/route/PutObjectMultipartStart
  #415 = Methodref          #414.#209     // io/findify/s3mock/route/PutObjectMultipartStart."<init>":(Lio/findify/s3mock/provider/Provider;)V
  #416 = Methodref          #414.#405     // io/findify/s3mock/route/PutObjectMultipartStart.route:(Ljava/lang/String;Ljava/lang/String;)Lscala/Function1;
  #417 = Utf8               io/findify/s3mock/route/PutObjectMultipartComplete
  #418 = Class              #417          // io/findify/s3mock/route/PutObjectMultipartComplete
  #419 = Methodref          #418.#209     // io/findify/s3mock/route/PutObjectMultipartComplete."<init>":(Lio/findify/s3mock/provider/Provider;)V
  #420 = Methodref          #418.#405     // io/findify/s3mock/route/PutObjectMultipartComplete.route:(Ljava/lang/String;Ljava/lang/String;)Lscala/Function1;
  #421 = Utf8               io/findify/s3mock/route/PutObject
  #422 = Class              #421          // io/findify/s3mock/route/PutObject
  #423 = Methodref          #422.#410     // io/findify/s3mock/route/PutObject."<init>":(Lio/findify/s3mock/provider/Provider;Lakka/stream/Materializer;)V
  #424 = Methodref          #422.#405     // io/findify/s3mock/route/PutObject.route:(Ljava/lang/String;Ljava/lang/String;)Lscala/Function1;
  #425 = Utf8               io/findify/s3mock/route/DeleteObject
  #426 = Class              #425          // io/findify/s3mock/route/DeleteObject
  #427 = Methodref          #426.#209     // io/findify/s3mock/route/DeleteObject."<init>":(Lio/findify/s3mock/provider/Provider;)V
  #428 = Methodref          #426.#405     // io/findify/s3mock/route/DeleteObject.route:(Ljava/lang/String;Ljava/lang/String;)Lscala/Function1;
  #429 = Utf8               Lscala/collection/immutable/Map;
  #430 = Utf8               Lakka/http/scaladsl/model/Uri$Path;
  #431 = Utf8               $anonfun$start$4
  #432 = Utf8               (Lio/findify/s3mock/S3Mock;Lakka/stream/ActorMaterializer;Ljava/lang/String;Lscala/collection/immutable/Map;)Lscala/Function1;
  #433 = Utf8               params
  #434 = Utf8               RemainingPath
  #435 = Utf8               ()Lakka/http/scaladsl/server/PathMatchers$RemainingPath$;
  #436 = NameAndType        #434:#435     // RemainingPath:()Lakka/http/scaladsl/server/PathMatchers$RemainingPath$;
  #437 = Methodref          #142.#436     // akka/http/scaladsl/server/Directives$.RemainingPath:()Lakka/http/scaladsl/server/PathMatchers$RemainingPath$;
  #438 = Utf8               path
  #439 = NameAndType        #438:#156     // path:(Lakka/http/scaladsl/server/PathMatcher;)Lakka/http/scaladsl/server/Directive;
  #440 = Methodref          #142.#439     // akka/http/scaladsl/server/Directives$.path:(Lakka/http/scaladsl/server/PathMatcher;)Lakka/http/scaladsl/server/Directive;
  #441 = NameAndType        #386:#387     // $anonfun$start$5:(Lio/findify/s3mock/S3Mock;Lakka/stream/ActorMaterializer;Ljava/lang/String;Lscala/collection/immutable/Map;Lakka/http/scaladsl/model/Uri$Path;)Lscala/Function1;
  #442 = Methodref          #2.#441       // io/findify/s3mock/S3Mock.$anonfun$start$5:(Lio/findify/s3mock/S3Mock;Lakka/stream/ActorMaterializer;Ljava/lang/String;Lscala/collection/immutable/Map;Lakka/http/scaladsl/model/Uri$Path;)Lscala/Function1;
  #443 = MethodHandle       #6:#442       // invokestatic io/findify/s3mock/S3Mock.$anonfun$start$5:(Lio/findify/s3mock/S3Mock;Lakka/stream/ActorMaterializer;Ljava/lang/String;Lscala/collection/immutable/Map;Lakka/http/scaladsl/model/Uri$Path;)Lscala/Function1;
  #444 = Utf8               (Lakka/http/scaladsl/model/Uri$Path;)Lscala/Function1;
  #445 = MethodType         #444          //  (Lakka/http/scaladsl/model/Uri$Path;)Lscala/Function1;
  #446 = NameAndType        #81:#432      // apply:(Lio/findify/s3mock/S3Mock;Lakka/stream/ActorMaterializer;Ljava/lang/String;Lscala/collection/immutable/Map;)Lscala/Function1;
  #447 = InvokeDynamic      #2:#446       // #2:apply:(Lio/findify/s3mock/S3Mock;Lakka/stream/ActorMaterializer;Ljava/lang/String;Lscala/collection/immutable/Map;)Lscala/Function1;
  #448 = Utf8               bucket
  #449 = Utf8               pathSingleSlash
  #450 = NameAndType        #449:#220     // pathSingleSlash:()Lakka/http/scaladsl/server/Directive;
  #451 = Methodref          #142.#450     // akka/http/scaladsl/server/Directives$.pathSingleSlash:()Lakka/http/scaladsl/server/Directive;
  #452 = Utf8               addByNameNullaryApply
  #453 = Utf8               (Lakka/http/scaladsl/server/Directive;)Lscala/Function1;
  #454 = NameAndType        #452:#453     // addByNameNullaryApply:(Lakka/http/scaladsl/server/Directive;)Lscala/Function1;
  #455 = Methodref          #147.#454     // akka/http/scaladsl/server/Directive$.addByNameNullaryApply:(Lakka/http/scaladsl/server/Directive;)Lscala/Function1;
  #456 = Utf8               ()Ljava/lang/Object;
  #457 = MethodType         #456          //  ()Ljava/lang/Object;
  #458 = NameAndType        #348:#349     // $anonfun$start$2:(Lio/findify/s3mock/S3Mock;Ljava/lang/String;)Lscala/Function1;
  #459 = Methodref          #2.#458       // io/findify/s3mock/S3Mock.$anonfun$start$2:(Lio/findify/s3mock/S3Mock;Ljava/lang/String;)Lscala/Function1;
  #460 = MethodHandle       #6:#459       // invokestatic io/findify/s3mock/S3Mock.$anonfun$start$2:(Lio/findify/s3mock/S3Mock;Ljava/lang/String;)Lscala/Function1;
  #461 = MethodType         #212          //  ()Lscala/Function1;
  #462 = Utf8               (Lio/findify/s3mock/S3Mock;Ljava/lang/String;)Lscala/Function0;
  #463 = NameAndType        #81:#462      // apply:(Lio/findify/s3mock/S3Mock;Ljava/lang/String;)Lscala/Function0;
  #464 = InvokeDynamic      #3:#463       // #3:apply:(Lio/findify/s3mock/S3Mock;Ljava/lang/String;)Lscala/Function0;
  #465 = Utf8               pathEnd
  #466 = NameAndType        #465:#220     // pathEnd:()Lakka/http/scaladsl/server/Directive;
  #467 = Methodref          #142.#466     // akka/http/scaladsl/server/Directives$.pathEnd:()Lakka/http/scaladsl/server/Directive;
  #468 = NameAndType        #385:#349     // $anonfun$start$3:(Lio/findify/s3mock/S3Mock;Ljava/lang/String;)Lscala/Function1;
  #469 = Methodref          #2.#468       // io/findify/s3mock/S3Mock.$anonfun$start$3:(Lio/findify/s3mock/S3Mock;Ljava/lang/String;)Lscala/Function1;
  #470 = MethodHandle       #6:#469       // invokestatic io/findify/s3mock/S3Mock.$anonfun$start$3:(Lio/findify/s3mock/S3Mock;Ljava/lang/String;)Lscala/Function1;
  #471 = InvokeDynamic      #4:#463       // #4:apply:(Lio/findify/s3mock/S3Mock;Ljava/lang/String;)Lscala/Function0;
  #472 = Utf8               parameterMap
  #473 = NameAndType        #472:#220     // parameterMap:()Lakka/http/scaladsl/server/Directive;
  #474 = Methodref          #142.#473     // akka/http/scaladsl/server/Directives$.parameterMap:()Lakka/http/scaladsl/server/Directive;
  #475 = NameAndType        #431:#432     // $anonfun$start$4:(Lio/findify/s3mock/S3Mock;Lakka/stream/ActorMaterializer;Ljava/lang/String;Lscala/collection/immutable/Map;)Lscala/Function1;
  #476 = Methodref          #2.#475       // io/findify/s3mock/S3Mock.$anonfun$start$4:(Lio/findify/s3mock/S3Mock;Lakka/stream/ActorMaterializer;Ljava/lang/String;Lscala/collection/immutable/Map;)Lscala/Function1;
  #477 = MethodHandle       #6:#476       // invokestatic io/findify/s3mock/S3Mock.$anonfun$start$4:(Lio/findify/s3mock/S3Mock;Lakka/stream/ActorMaterializer;Ljava/lang/String;Lscala/collection/immutable/Map;)Lscala/Function1;
  #478 = Utf8               (Lscala/collection/immutable/Map;)Lscala/Function1;
  #479 = MethodType         #478          //  (Lscala/collection/immutable/Map;)Lscala/Function1;
  #480 = NameAndType        #81:#182      // apply:(Lio/findify/s3mock/S3Mock;Lakka/stream/ActorMaterializer;Ljava/lang/String;)Lscala/Function1;
  #481 = InvokeDynamic      #5:#480       // #5:apply:(Lio/findify/s3mock/S3Mock;Lakka/stream/ActorMaterializer;Ljava/lang/String;)Lscala/Function1;
  #482 = Utf8               $anonfun$start$7
  #483 = Utf8               (Lio/findify/s3mock/S3Mock;Lakka/http/scaladsl/model/HttpRequest;)Lakka/http/scaladsl/marshalling/ToResponseMarshallable;
  #484 = Utf8               request$1
  #485 = NameAndType        #60:#87       // logger:()Lcom/typesafe/scalalogging/Logger;
  #486 = Methodref          #2.#485       // io/findify/s3mock/S3Mock.logger:()Lcom/typesafe/scalalogging/Logger;
  #487 = Utf8               underlying
  #488 = Utf8               ()Lorg/slf4j/Logger;
  #489 = NameAndType        #487:#488     // underlying:()Lorg/slf4j/Logger;
  #490 = Methodref          #103.#489     // com/typesafe/scalalogging/Logger.underlying:()Lorg/slf4j/Logger;
  #491 = Utf8               org/slf4j/Logger
  #492 = Class              #491          // org/slf4j/Logger
  #493 = Utf8               isErrorEnabled
  #494 = Utf8               ()Z
  #495 = NameAndType        #493:#494     // isErrorEnabled:()Z
  #496 = InterfaceMethodref #492.#495     // org/slf4j/Logger.isErrorEnabled:()Z
  #497 = Utf8               scala/StringContext
  #498 = Class              #497          // scala/StringContext
  #499 = Utf8               java/lang/String
  #500 = Class              #499          // java/lang/String
  #501 = Utf8               method not implemented:
  #502 = String             #501          // method not implemented:
  #503 = Utf8
  #504 = String             #503          //
  #505 = Utf8
  #506 = String             #505          //
  #507 = Utf8               (Lscala/collection/Seq;)V
  #508 = NameAndType        #207:#507     // "<init>":(Lscala/collection/Seq;)V
  #509 = Methodref          #498.#508     // scala/StringContext."<init>":(Lscala/collection/Seq;)V
  #510 = Utf8               akka/http/scaladsl/model/HttpRequest
  #511 = Class              #510          // akka/http/scaladsl/model/HttpRequest
  #512 = Utf8               method
  #513 = Utf8               ()Lakka/http/scaladsl/model/HttpMethod;
  #514 = NameAndType        #512:#513     // method:()Lakka/http/scaladsl/model/HttpMethod;
  #515 = Methodref          #511.#514     // akka/http/scaladsl/model/HttpRequest.method:()Lakka/http/scaladsl/model/HttpMethod;
  #516 = Utf8               akka/http/scaladsl/model/HttpMethod
  #517 = Class              #516          // akka/http/scaladsl/model/HttpMethod
  #518 = Utf8               value
  #519 = NameAndType        #518:#395     // value:()Ljava/lang/String;
  #520 = Methodref          #517.#519     // akka/http/scaladsl/model/HttpMethod.value:()Ljava/lang/String;
  #521 = Utf8               uri
  #522 = Utf8               ()Lakka/http/scaladsl/model/Uri;
  #523 = NameAndType        #521:#522     // uri:()Lakka/http/scaladsl/model/Uri;
  #524 = Methodref          #511.#523     // akka/http/scaladsl/model/HttpRequest.uri:()Lakka/http/scaladsl/model/Uri;
  #525 = Methodref          #24.#396      // akka/http/scaladsl/model/Uri.toString:()Ljava/lang/String;
  #526 = Utf8               genericWrapArray
  #527 = Utf8               (Ljava/lang/Object;)Lscala/collection/mutable/WrappedArray;
  #528 = NameAndType        #526:#527     // genericWrapArray:(Ljava/lang/Object;)Lscala/collection/mutable/WrappedArray;
  #529 = Methodref          #353.#528     // scala/Predef$.genericWrapArray:(Ljava/lang/Object;)Lscala/collection/mutable/WrappedArray;
  #530 = Utf8               s
  #531 = Utf8               (Lscala/collection/Seq;)Ljava/lang/String;
  #532 = NameAndType        #530:#531     // s:(Lscala/collection/Seq;)Ljava/lang/String;
  #533 = Methodref          #498.#532     // scala/StringContext.s:(Lscala/collection/Seq;)Ljava/lang/String;
  #534 = Utf8               error
  #535 = Utf8               (Ljava/lang/String;)V
  #536 = NameAndType        #534:#535     // error:(Ljava/lang/String;)V
  #537 = InterfaceMethodref #492.#536     // org/slf4j/Logger.error:(Ljava/lang/String;)V
  #538 = Utf8               scala/runtime/BoxedUnit
  #539 = Class              #538          // scala/runtime/BoxedUnit
  #540 = Utf8               UNIT
  #541 = Utf8               Lscala/runtime/BoxedUnit;
  #542 = NameAndType        #540:#541     // UNIT:Lscala/runtime/BoxedUnit;
  #543 = Fieldref           #539.#542     // scala/runtime/BoxedUnit.UNIT:Lscala/runtime/BoxedUnit;
  #544 = Utf8               akka/http/scaladsl/marshalling/ToResponseMarshallable$
  #545 = Class              #544          // akka/http/scaladsl/marshalling/ToResponseMarshallable$
  #546 = Utf8               Lakka/http/scaladsl/marshalling/ToResponseMarshallable$;
  #547 = NameAndType        #68:#546      // MODULE$:Lakka/http/scaladsl/marshalling/ToResponseMarshallable$;
  #548 = Fieldref           #545.#547     // akka/http/scaladsl/marshalling/ToResponseMarshallable$.MODULE$:Lakka/http/scaladsl/marshalling/ToResponseMarshallable$;
  #549 = Utf8               akka/http/scaladsl/model/HttpResponse$
  #550 = Class              #549          // akka/http/scaladsl/model/HttpResponse$
  #551 = Utf8               Lakka/http/scaladsl/model/HttpResponse$;
  #552 = NameAndType        #68:#551      // MODULE$:Lakka/http/scaladsl/model/HttpResponse$;
  #553 = Fieldref           #550.#552     // akka/http/scaladsl/model/HttpResponse$.MODULE$:Lakka/http/scaladsl/model/HttpResponse$;
  #554 = Utf8               akka/http/scaladsl/model/StatusCodes$
  #555 = Class              #554          // akka/http/scaladsl/model/StatusCodes$
  #556 = Utf8               Lakka/http/scaladsl/model/StatusCodes$;
  #557 = NameAndType        #68:#556      // MODULE$:Lakka/http/scaladsl/model/StatusCodes$;
  #558 = Fieldref           #555.#557     // akka/http/scaladsl/model/StatusCodes$.MODULE$:Lakka/http/scaladsl/model/StatusCodes$;
  #559 = Utf8               NotImplemented
  #560 = Utf8               ()Lakka/http/scaladsl/model/StatusCodes$ServerError;
  #561 = NameAndType        #559:#560     // NotImplemented:()Lakka/http/scaladsl/model/StatusCodes$ServerError;
  #562 = Methodref          #555.#561     // akka/http/scaladsl/model/StatusCodes$.NotImplemented:()Lakka/http/scaladsl/model/StatusCodes$ServerError;
  #563 = Utf8               ()Lscala/collection/immutable/Seq;
  #564 = NameAndType        #123:#563     // apply$default$2:()Lscala/collection/immutable/Seq;
  #565 = Methodref          #550.#564     // akka/http/scaladsl/model/HttpResponse$.apply$default$2:()Lscala/collection/immutable/Seq;
  #566 = Utf8               apply$default$3
  #567 = Utf8               ()Lakka/http/scaladsl/model/ResponseEntity;
  #568 = NameAndType        #566:#567     // apply$default$3:()Lakka/http/scaladsl/model/ResponseEntity;
  #569 = Methodref          #550.#568     // akka/http/scaladsl/model/HttpResponse$.apply$default$3:()Lakka/http/scaladsl/model/ResponseEntity;
  #570 = Utf8               apply$default$4
  #571 = Utf8               ()Lakka/http/scaladsl/model/HttpProtocol;
  #572 = NameAndType        #570:#571     // apply$default$4:()Lakka/http/scaladsl/model/HttpProtocol;
  #573 = Methodref          #550.#572     // akka/http/scaladsl/model/HttpResponse$.apply$default$4:()Lakka/http/scaladsl/model/HttpProtocol;
  #574 = Utf8               (Lakka/http/scaladsl/model/StatusCode;Lscala/collection/immutable/Seq;Lakka/http/scaladsl/model/ResponseEntity;Lakka/http/scaladsl/model/HttpProtocol;)Lakka/http/scaladsl/model/HttpResponse;
  #575 = NameAndType        #81:#574      // apply:(Lakka/http/scaladsl/model/StatusCode;Lscala/collection/immutable/Seq;Lakka/http/scaladsl/model/ResponseEntity;Lakka/http/scaladsl/model/HttpProtocol;)Lakka/http/scaladsl/model/HttpResponse;
  #576 = Methodref          #550.#575     // akka/http/scaladsl/model/HttpResponse$.apply:(Lakka/http/scaladsl/model/StatusCode;Lscala/collection/immutable/Seq;Lakka/http/scaladsl/model/ResponseEntity;Lakka/http/scaladsl/model/HttpProtocol;)Lakka/http/scaladsl/model/HttpResponse;
  #577 = Utf8               akka/http/scaladsl/marshalling/Marshaller$
  #578 = Class              #577          // akka/http/scaladsl/marshalling/Marshaller$
  #579 = Utf8               Lakka/http/scaladsl/marshalling/Marshaller$;
  #580 = NameAndType        #68:#579      // MODULE$:Lakka/http/scaladsl/marshalling/Marshaller$;
  #581 = Fieldref           #578.#580     // akka/http/scaladsl/marshalling/Marshaller$.MODULE$:Lakka/http/scaladsl/marshalling/Marshaller$;
  #582 = Utf8               fromResponse
  #583 = Utf8               ()Lakka/http/scaladsl/marshalling/Marshaller;
  #584 = NameAndType        #582:#583     // fromResponse:()Lakka/http/scaladsl/marshalling/Marshaller;
  #585 = Methodref          #578.#584     // akka/http/scaladsl/marshalling/Marshaller$.fromResponse:()Lakka/http/scaladsl/marshalling/Marshaller;
  #586 = Utf8               (Ljava/lang/Object;Lakka/http/scaladsl/marshalling/Marshaller;)Lakka/http/scaladsl/marshalling/ToResponseMarshallable;
  #587 = NameAndType        #81:#586      // apply:(Ljava/lang/Object;Lakka/http/scaladsl/marshalling/Marshaller;)Lakka/http/scaladsl/marshalling/ToResponseMarshallable;
  #588 = Methodref          #545.#587     // akka/http/scaladsl/marshalling/ToResponseMarshallable$.apply:(Ljava/lang/Object;Lakka/http/scaladsl/marshalling/Marshaller;)Lakka/http/scaladsl/marshalling/ToResponseMarshallable;
  #589 = Utf8               Lakka/http/scaladsl/model/HttpRequest;
  #590 = Utf8               request
  #591 = NameAndType        #482:#483     // $anonfun$start$7:(Lio/findify/s3mock/S3Mock;Lakka/http/scaladsl/model/HttpRequest;)Lakka/http/scaladsl/marshalling/ToResponseMarshallable;
  #592 = Methodref          #2.#591       // io/findify/s3mock/S3Mock.$anonfun$start$7:(Lio/findify/s3mock/S3Mock;Lakka/http/scaladsl/model/HttpRequest;)Lakka/http/scaladsl/marshalling/ToResponseMarshallable;
  #593 = MethodHandle       #6:#592       // invokestatic io/findify/s3mock/S3Mock.$anonfun$start$7:(Lio/findify/s3mock/S3Mock;Lakka/http/scaladsl/model/HttpRequest;)Lakka/http/scaladsl/marshalling/ToResponseMarshallable;
  #594 = Utf8               ()Lakka/http/scaladsl/marshalling/ToResponseMarshallable;
  #595 = MethodType         #594          //  ()Lakka/http/scaladsl/marshalling/ToResponseMarshallable;
  #596 = Utf8               (Lio/findify/s3mock/S3Mock;Lakka/http/scaladsl/model/HttpRequest;)Lscala/Function0;
  #597 = NameAndType        #81:#596      // apply:(Lio/findify/s3mock/S3Mock;Lakka/http/scaladsl/model/HttpRequest;)Lscala/Function0;
  #598 = InvokeDynamic      #6:#597       // #6:apply:(Lio/findify/s3mock/S3Mock;Lakka/http/scaladsl/model/HttpRequest;)Lscala/Function0;
  #599 = Utf8               complete
  #600 = Utf8               (Lscala/Function0;)Lakka/http/scaladsl/server/StandardRoute;
  #601 = NameAndType        #599:#600     // complete:(Lscala/Function0;)Lakka/http/scaladsl/server/StandardRoute;
  #602 = Methodref          #142.#601     // akka/http/scaladsl/server/Directives$.complete:(Lscala/Function0;)Lakka/http/scaladsl/server/StandardRoute;
  #603 = Utf8               (ILio/findify/s3mock/provider/Provider;Lakka/actor/ActorSystem;)V
  #604 = Utf8               provider
  #605 = NameAndType        #207:#343     // "<init>":()V
  #606 = Methodref          #4.#605       // java/lang/Object."<init>":()V
  #607 = Utf8               $init$
  #608 = Utf8               (Lcom/typesafe/scalalogging/LazyLogging;)V
  #609 = NameAndType        #607:#608     // $init$:(Lcom/typesafe/scalalogging/LazyLogging;)V
  #610 = InterfaceMethodref #6.#609       // com/typesafe/scalalogging/LazyLogging.$init$:(Lcom/typesafe/scalalogging/LazyLogging;)V
  #611 = Utf8               $deserializeLambda$
  #612 = Utf8               (Ljava/lang/invoke/SerializedLambda;)Ljava/lang/Object;
  #613 = Utf8               scala/runtime/LambdaDeserialize
  #614 = Class              #613          // scala/runtime/LambdaDeserialize
  #615 = Utf8               bootstrap
  #616 = Utf8               (Ljava/lang/invoke/MethodHandles$Lookup;Ljava/lang/String;Ljava/lang/invoke/MethodType;[Ljava/lang/invoke/MethodHandle;)Ljava/lang/invoke/CallSite;
  #617 = NameAndType        #615:#616     // bootstrap:(Ljava/lang/invoke/MethodHandles$Lookup;Ljava/lang/String;Ljava/lang/invoke/MethodType;[Ljava/lang/invoke/MethodHandle;)Ljava/lang/invoke/CallSite;
  #618 = Methodref          #614.#617     // scala/runtime/LambdaDeserialize.bootstrap:(Ljava/lang/invoke/MethodHandles$Lookup;Ljava/lang/String;Ljava/lang/invoke/MethodType;[Ljava/lang/invoke/MethodHandle;)Ljava/lang/invoke/CallSite;
  #619 = MethodHandle       #6:#618       // invokestatic scala/runtime/LambdaDeserialize.bootstrap:(Ljava/lang/invoke/MethodHandles$Lookup;Ljava/lang/String;Ljava/lang/invoke/MethodType;[Ljava/lang/invoke/MethodHandle;)Ljava/lang/invoke/CallSite;
  #620 = Utf8               lambdaDeserialize
  #621 = NameAndType        #620:#612     // lambdaDeserialize:(Ljava/lang/invoke/SerializedLambda;)Ljava/lang/Object;
  #622 = InvokeDynamic      #7:#621       // #7:lambdaDeserialize:(Ljava/lang/invoke/SerializedLambda;)Ljava/lang/Object;
  #623 = Utf8               Code
  #624 = Utf8               LocalVariableTable
  #625 = Utf8               LineNumberTable
  #626 = Utf8               StackMapTable
  #627 = Utf8               MethodParameters
  #628 = Utf8               BootstrapMethods
  #629 = Utf8               SourceFile
  #630 = Utf8               InnerClasses
  #631 = Utf8               RuntimeVisibleAnnotations
  #632 = Utf8               ScalaInlineInfo
  #633 = Utf8               ScalaSig
{
  private final int port;
    descriptor: I
    flags: ACC_PRIVATE, ACC_FINAL

  private final akka.actor.ActorSystem system;
    descriptor: Lakka/actor/ActorSystem;
    flags: ACC_PRIVATE, ACC_FINAL

  private final io.findify.s3mock.provider.Provider p;
    descriptor: Lio/findify/s3mock/provider/Provider;
    flags: ACC_PRIVATE, ACC_FINAL

  private akka.http.scaladsl.Http$ServerBinding bind;
    descriptor: Lakka/http/scaladsl/Http$ServerBinding;
    flags: ACC_PRIVATE

  private volatile com.typesafe.scalalogging.Logger logger;
    descriptor: Lcom/typesafe/scalalogging/Logger;
    flags: ACC_PRIVATE, ACC_VOLATILE

  private volatile boolean bitmap$0;
    descriptor: Z
    flags: ACC_PRIVATE, ACC_VOLATILE

  public static akka.actor.ActorSystem $lessinit$greater$default$3(int, io.findify.s3mock.provider.Provider);
    descriptor: (ILio/findify/s3mock/provider/Provider;)Lakka/actor/ActorSystem;
    flags: ACC_PUBLIC, ACC_STATIC
    Code:
      stack=3, locals=2, args_size=2
         0: getstatic     #71                 // Field io/findify/s3mock/S3Mock$.MODULE$:Lio/findify/s3mock/S3Mock$;
         3: iload_0
         4: aload_1
         5: invokevirtual #73                 // Method io/findify/s3mock/S3Mock$.$lessinit$greater$default$3:(ILio/findify/s3mock/provider/Provider;)Lakka/actor/ActorSystem;
         8: areturn

  public static io.findify.s3mock.S3Mock create(int, java.lang.String);
    descriptor: (ILjava/lang/String;)Lio/findify/s3mock/S3Mock;
    flags: ACC_PUBLIC, ACC_STATIC
    Code:
      stack=3, locals=2, args_size=2
         0: getstatic     #71                 // Field io/findify/s3mock/S3Mock$.MODULE$:Lio/findify/s3mock/S3Mock$;
         3: iload_0
         4: aload_1
         5: invokevirtual #77                 // Method io/findify/s3mock/S3Mock$.create:(ILjava/lang/String;)Lio/findify/s3mock/S3Mock;
         8: areturn

  public static io.findify.s3mock.S3Mock create(int);
    descriptor: (I)Lio/findify/s3mock/S3Mock;
    flags: ACC_PUBLIC, ACC_STATIC
    Code:
      stack=2, locals=1, args_size=1
         0: getstatic     #71                 // Field io/findify/s3mock/S3Mock$.MODULE$:Lio/findify/s3mock/S3Mock$;
         3: iload_0
         4: invokevirtual #80                 // Method io/findify/s3mock/S3Mock$.create:(I)Lio/findify/s3mock/S3Mock;
         7: areturn

  public static io.findify.s3mock.S3Mock apply(int, java.lang.String);
    descriptor: (ILjava/lang/String;)Lio/findify/s3mock/S3Mock;
    flags: ACC_PUBLIC, ACC_STATIC
    Code:
      stack=3, locals=2, args_size=2
         0: getstatic     #71                 // Field io/findify/s3mock/S3Mock$.MODULE$:Lio/findify/s3mock/S3Mock$;
         3: iload_0
         4: aload_1
         5: invokevirtual #83                 // Method io/findify/s3mock/S3Mock$.apply:(ILjava/lang/String;)Lio/findify/s3mock/S3Mock;
         8: areturn

  public static io.findify.s3mock.S3Mock apply(int);
    descriptor: (I)Lio/findify/s3mock/S3Mock;
    flags: ACC_PUBLIC, ACC_STATIC
    Code:
      stack=2, locals=1, args_size=1
         0: getstatic     #71                 // Field io/findify/s3mock/S3Mock$.MODULE$:Lio/findify/s3mock/S3Mock$;
         3: iload_0
         4: invokevirtual #85                 // Method io/findify/s3mock/S3Mock$.apply:(I)Lio/findify/s3mock/S3Mock;
         7: areturn

  private com.typesafe.scalalogging.Logger logger$lzycompute();
    descriptor: ()Lcom/typesafe/scalalogging/Logger;
    flags: ACC_PRIVATE
    Code:
      stack=2, locals=2, args_size=1
         0: aload_0
         1: dup
         2: astore_1
         3: monitorenter
         4: aload_0
         5: getfield      #89                 // Field bitmap$0:Z
         8: ifne          24
        11: aload_0
        12: aload_0
        13: invokestatic  #93                 // InterfaceMethod com/typesafe/scalalogging/LazyLogging.logger$:(Lcom/typesafe/scalalogging/LazyLogging;)Lcom/typesafe/scalalogging/Logger;
        16: putfield      #95                 // Field logger:Lcom/typesafe/scalalogging/Logger;
        19: aload_0
        20: iconst_1
        21: putfield      #89                 // Field bitmap$0:Z
        24: aload_1
        25: monitorexit
        26: goto          32
        29: aload_1
        30: monitorexit
        31: athrow
        32: aload_0
        33: getfield      #95                 // Field logger:Lcom/typesafe/scalalogging/Logger;
        36: areturn
      Exception table:
         from    to  target type
             4    24    29   any
      LocalVariableTable:
        Start  Length  Slot  Name   Signature
            0      37     0  this   Lio/findify/s3mock/S3Mock;
      LineNumberTable:
        line 20: 0
      StackMapTable: number_of_entries = 3
        frame_type = 252 /* append */
          offset_delta = 24
          locals = [ class io/findify/s3mock/S3Mock ]
        frame_type = 68 /* same_locals_1_stack_item */
          stack = [ class java/lang/Throwable ]
        frame_type = 2 /* same */

  public com.typesafe.scalalogging.Logger logger();
    descriptor: ()Lcom/typesafe/scalalogging/Logger;
    flags: ACC_PUBLIC
    Code:
      stack=1, locals=1, args_size=1
         0: aload_0
         1: getfield      #89                 // Field bitmap$0:Z
         4: ifne          14
         7: aload_0
         8: invokespecial #101                // Method logger$lzycompute:()Lcom/typesafe/scalalogging/Logger;
        11: goto          18
        14: aload_0
        15: getfield      #95                 // Field logger:Lcom/typesafe/scalalogging/Logger;
        18: areturn
      LocalVariableTable:
        Start  Length  Slot  Name   Signature
            0      19     0  this   Lio/findify/s3mock/S3Mock;
      LineNumberTable:
        line 20: 0
      StackMapTable: number_of_entries = 2
        frame_type = 14 /* same */
        frame_type = 67 /* same_locals_1_stack_item */
          stack = [ class com/typesafe/scalalogging/Logger ]

  public io.findify.s3mock.provider.Provider p();
    descriptor: ()Lio/findify/s3mock/provider/Provider;
    flags: ACC_PUBLIC
    Code:
      stack=1, locals=1, args_size=1
         0: aload_0
         1: getfield      #106                // Field p:Lio/findify/s3mock/provider/Provider;
         4: areturn
      LocalVariableTable:
        Start  Length  Slot  Name   Signature
            0       5     0  this   Lio/findify/s3mock/S3Mock;
      LineNumberTable:
        line 21: 0

  private akka.http.scaladsl.Http$ServerBinding bind();
    descriptor: ()Lakka/http/scaladsl/Http$ServerBinding;
    flags: ACC_PRIVATE
    Code:
      stack=1, locals=1, args_size=1
         0: aload_0
         1: getfield      #109                // Field bind:Lakka/http/scaladsl/Http$ServerBinding;
         4: areturn
      LocalVariableTable:
        Start  Length  Slot  Name   Signature
            0       5     0  this   Lio/findify/s3mock/S3Mock;
      LineNumberTable:
        line 22: 0

  private void bind_$eq(akka.http.scaladsl.Http$ServerBinding);
    descriptor: (Lakka/http/scaladsl/Http$ServerBinding;)V
    flags: ACC_PRIVATE
    Code:
      stack=2, locals=2, args_size=2
         0: aload_0
         1: aload_1
         2: putfield      #109                // Field bind:Lakka/http/scaladsl/Http$ServerBinding;
         5: return
      LocalVariableTable:
        Start  Length  Slot  Name   Signature
            0       6     0  this   Lio/findify/s3mock/S3Mock;
            0       6     1   x$1   Lakka/http/scaladsl/Http$ServerBinding;
      LineNumberTable:
        line 22: 0
    MethodParameters:
      Name                           Flags
      x$1                            final

  public akka.http.scaladsl.Http$ServerBinding start();
    descriptor: ()Lakka/http/scaladsl/Http$ServerBinding;
    flags: ACC_PUBLIC
    Code:
      stack=12, locals=12, args_size=1
         0: getstatic     #118                // Field akka/stream/ActorMaterializer$.MODULE$:Lakka/stream/ActorMaterializer$;
         3: getstatic     #118                // Field akka/stream/ActorMaterializer$.MODULE$:Lakka/stream/ActorMaterializer$;
         6: invokevirtual #122                // Method akka/stream/ActorMaterializer$.apply$default$1:()Lscala/Option;
         9: getstatic     #118                // Field akka/stream/ActorMaterializer$.MODULE$:Lakka/stream/ActorMaterializer$;
        12: invokevirtual #125                // Method akka/stream/ActorMaterializer$.apply$default$2:()Lscala/Option;
        15: aload_0
        16: getfield      #127                // Field system:Lakka/actor/ActorSystem;
        19: invokevirtual #130                // Method akka/stream/ActorMaterializer$.apply:(Lscala/Option;Lscala/Option;Lakka/actor/ActorRefFactory;)Lakka/stream/ActorMaterializer;
        22: astore_1
        23: getstatic     #135                // Field akka/http/scaladsl/Http$.MODULE$:Lakka/http/scaladsl/Http$;
        26: aload_0
        27: getfield      #127                // Field system:Lakka/actor/ActorSystem;
        30: invokevirtual #138                // Method akka/http/scaladsl/Http$.apply:(Lakka/actor/ActorSystem;)Lakka/actor/Extension;
        33: checkcast     #140                // class akka/http/scaladsl/HttpExt
        36: astore_2
        37: getstatic     #145                // Field akka/http/scaladsl/server/Directives$.MODULE$:Lakka/http/scaladsl/server/Directives$;
        40: getstatic     #145                // Field akka/http/scaladsl/server/Directives$.MODULE$:Lakka/http/scaladsl/server/Directives$;
        43: getstatic     #150                // Field akka/http/scaladsl/server/Directive$.MODULE$:Lakka/http/scaladsl/server/Directive$;
        46: getstatic     #145                // Field akka/http/scaladsl/server/Directives$.MODULE$:Lakka/http/scaladsl/server/Directives$;
        49: getstatic     #145                // Field akka/http/scaladsl/server/Directives$.MODULE$:Lakka/http/scaladsl/server/Directives$;
        52: invokevirtual #154                // Method akka/http/scaladsl/server/Directives$.Segment:()Lakka/http/scaladsl/server/PathMatchers$Segment$;
        55: invokevirtual #158                // Method akka/http/scaladsl/server/Directives$.pathPrefix:(Lakka/http/scaladsl/server/PathMatcher;)Lakka/http/scaladsl/server/Directive;
        58: getstatic     #163                // Field akka/http/scaladsl/server/util/ApplyConverter$.MODULE$:Lakka/http/scaladsl/server/util/ApplyConverter$;
        61: invokevirtual #167                // Method akka/http/scaladsl/server/util/ApplyConverter$.hac1:()Lakka/http/scaladsl/server/util/ApplyConverter;
        64: invokevirtual #171                // Method akka/http/scaladsl/server/Directive$.addDirectiveApply:(Lakka/http/scaladsl/server/Directive;Lakka/http/scaladsl/server/util/ApplyConverter;)Lscala/Function1;
        67: aload_0
        68: aload_1
        69: invokedynamic #194,  0            // InvokeDynamic #0:apply:(Lio/findify/s3mock/S3Mock;Lakka/stream/ActorMaterializer;)Lscala/Function1;
        74: invokeinterface #198,  2          // InterfaceMethod scala/Function1.apply:(Ljava/lang/Object;)Ljava/lang/Object;
        79: checkcast     #196                // class scala/Function1
        82: invokevirtual #202                // Method akka/http/scaladsl/server/Directives$._enhanceRouteWithConcatenation:(Lscala/Function1;)Lakka/http/scaladsl/server/RouteConcatenation$RouteWithConcatenation;
        85: new           #204                // class io/findify/s3mock/route/ListBuckets
        88: dup
        89: aload_0
        90: invokevirtual #206                // Method p:()Lio/findify/s3mock/provider/Provider;
        93: invokespecial #210                // Method io/findify/s3mock/route/ListBuckets."<init>":(Lio/findify/s3mock/provider/Provider;)V
        96: invokevirtual #214                // Method io/findify/s3mock/route/ListBuckets.route:()Lscala/Function1;
        99: invokevirtual #218                // Method akka/http/scaladsl/server/RouteConcatenation$RouteWithConcatenation.$tilde:(Lscala/Function1;)Lscala/Function1;
       102: invokevirtual #202                // Method akka/http/scaladsl/server/Directives$._enhanceRouteWithConcatenation:(Lscala/Function1;)Lakka/http/scaladsl/server/RouteConcatenation$RouteWithConcatenation;
       105: getstatic     #150                // Field akka/http/scaladsl/server/Directive$.MODULE$:Lakka/http/scaladsl/server/Directive$;
       108: getstatic     #145                // Field akka/http/scaladsl/server/Directives$.MODULE$:Lakka/http/scaladsl/server/Directives$;
       111: invokevirtual #222                // Method akka/http/scaladsl/server/Directives$.extractRequest:()Lakka/http/scaladsl/server/Directive;
       114: getstatic     #163                // Field akka/http/scaladsl/server/util/ApplyConverter$.MODULE$:Lakka/http/scaladsl/server/util/ApplyConverter$;
       117: invokevirtual #167                // Method akka/http/scaladsl/server/util/ApplyConverter$.hac1:()Lakka/http/scaladsl/server/util/ApplyConverter;
       120: invokevirtual #171                // Method akka/http/scaladsl/server/Directive$.addDirectiveApply:(Lakka/http/scaladsl/server/Directive;Lakka/http/scaladsl/server/util/ApplyConverter;)Lscala/Function1;
       123: aload_0
       124: invokedynamic #232,  0            // InvokeDynamic #1:apply:(Lio/findify/s3mock/S3Mock;)Lscala/Function1;
       129: invokeinterface #198,  2          // InterfaceMethod scala/Function1.apply:(Ljava/lang/Object;)Ljava/lang/Object;
       134: checkcast     #196                // class scala/Function1
       137: invokevirtual #218                // Method akka/http/scaladsl/server/RouteConcatenation$RouteWithConcatenation.$tilde:(Lscala/Function1;)Lscala/Function1;
       140: astore_3
       141: aload_0
       142: getstatic     #237                // Field scala/concurrent/Await$.MODULE$:Lscala/concurrent/Await$;
       145: aload_2
       146: aload_3
       147: astore        4
       149: getstatic     #242                // Field akka/http/scaladsl/settings/RoutingSettings$.MODULE$:Lakka/http/scaladsl/settings/RoutingSettings$;
       152: aload_0
       153: getfield      #127                // Field system:Lakka/actor/ActorSystem;
       156: invokevirtual #246                // Method akka/http/scaladsl/settings/RoutingSettings$.default:(Lakka/actor/ActorRefFactory;)Ljava/lang/Object;
       159: checkcast     #248                // class akka/http/scaladsl/settings/RoutingSettings
       162: astore        5
       164: getstatic     #253                // Field akka/http/scaladsl/settings/ParserSettings$.MODULE$:Lakka/http/scaladsl/settings/ParserSettings$;
       167: aload_0
       168: getfield      #127                // Field system:Lakka/actor/ActorSystem;
       171: invokevirtual #254                // Method akka/http/scaladsl/settings/ParserSettings$.default:(Lakka/actor/ActorRefFactory;)Ljava/lang/Object;
       174: checkcast     #256                // class akka/http/scaladsl/settings/ParserSettings
       177: astore        6
       179: aload_1
       180: astore        7
       182: getstatic     #261                // Field akka/http/scaladsl/server/RoutingLog$.MODULE$:Lakka/http/scaladsl/server/RoutingLog$;
       185: aload_0
       186: getfield      #127                // Field system:Lakka/actor/ActorSystem;
       189: invokevirtual #265                // Method akka/http/scaladsl/server/RoutingLog$.fromActorSystem:(Lakka/actor/ActorSystem;)Lakka/http/scaladsl/server/RoutingLog;
       192: astore        8
       194: getstatic     #270                // Field akka/http/scaladsl/server/RouteResult$.MODULE$:Lakka/http/scaladsl/server/RouteResult$;
       197: aload         4
       199: invokevirtual #274                // Method akka/http/scaladsl/server/RouteResult$.route2HandlerFlow$default$6:(Lscala/Function1;)Lscala/concurrent/ExecutionContext;
       202: astore        9
       204: getstatic     #270                // Field akka/http/scaladsl/server/RouteResult$.MODULE$:Lakka/http/scaladsl/server/RouteResult$;
       207: aload         4
       209: invokevirtual #278                // Method akka/http/scaladsl/server/RouteResult$.route2HandlerFlow$default$7:(Lscala/Function1;)Lakka/http/scaladsl/server/RejectionHandler;
       212: astore        10
       214: getstatic     #270                // Field akka/http/scaladsl/server/RouteResult$.MODULE$:Lakka/http/scaladsl/server/RouteResult$;
       217: aload         4
       219: invokevirtual #282                // Method akka/http/scaladsl/server/RouteResult$.route2HandlerFlow$default$8:(Lscala/Function1;)Lakka/http/scaladsl/server/ExceptionHandler;
       222: astore        11
       224: getstatic     #270                // Field akka/http/scaladsl/server/RouteResult$.MODULE$:Lakka/http/scaladsl/server/RouteResult$;
       227: aload         4
       229: aload         5
       231: aload         6
       233: aload         7
       235: aload         8
       237: aload         9
       239: aload         10
       241: aload         11
       243: invokevirtual #286                // Method akka/http/scaladsl/server/RouteResult$.route2HandlerFlow:(Lscala/Function1;Lakka/http/scaladsl/settings/RoutingSettings;Lakka/http/scaladsl/settings/ParserSettings;Lakka/stream/Materializer;Lakka/http/scaladsl/server/RoutingLog;Lscala/concurrent/ExecutionContext;Lakka/http/scaladsl/server/RejectionHandler;Lakka/http/scaladsl/server/ExceptionHandler;)Lakka/stream/scaladsl/Flow;
       246: ldc_w         #288                // String localhost
       249: aload_0
       250: getfield      #290                // Field port:I
       253: aload_2
       254: invokevirtual #294                // Method akka/http/scaladsl/HttpExt.bindAndHandle$default$4:()Lakka/http/scaladsl/ConnectionContext;
       257: aload_2
       258: invokevirtual #298                // Method akka/http/scaladsl/HttpExt.bindAndHandle$default$5:()Lakka/http/scaladsl/settings/ServerSettings;
       261: aload_2
       262: invokevirtual #302                // Method akka/http/scaladsl/HttpExt.bindAndHandle$default$6:()Lakka/event/LoggingAdapter;
       265: aload_1
       266: invokevirtual #306                // Method akka/http/scaladsl/HttpExt.bindAndHandle:(Lakka/stream/scaladsl/Flow;Ljava/lang/String;ILakka/http/scaladsl/ConnectionContext;Lakka/http/scaladsl/settings/ServerSettings;Lakka/event/LoggingAdapter;Lakka/stream/Materializer;)Lscala/concurrent/Future;
       269: getstatic     #311                // Field scala/concurrent/duration/Duration$.MODULE$:Lscala/concurrent/duration/Duration$;
       272: invokevirtual #315                // Method scala/concurrent/duration/Duration$.Inf:()Lscala/concurrent/duration/Duration$Infinite;
       275: invokevirtual #319                // Method scala/concurrent/Await$.result:(Lscala/concurrent/Awaitable;Lscala/concurrent/duration/Duration;)Ljava/lang/Object;
       278: checkcast     #12                 // class akka/http/scaladsl/Http$ServerBinding
       281: invokespecial #321                // Method bind_$eq:(Lakka/http/scaladsl/Http$ServerBinding;)V
       284: aload_0
       285: invokespecial #323                // Method bind:()Lakka/http/scaladsl/Http$ServerBinding;
       288: areturn
      LocalVariableTable:
        Start  Length  Slot  Name   Signature
          147      99     4   x$1   Lscala/Function1;
          162      84     5   x$2   Lakka/http/scaladsl/settings/RoutingSettings;
          177      69     6   x$3   Lakka/http/scaladsl/settings/ParserSettings;
          180      66     7   x$4   Lakka/stream/ActorMaterializer;
          192      54     8   x$5   Lakka/http/scaladsl/server/RoutingLog;
          202      44     9   x$6   Lscala/concurrent/ExecutionContext;
          212      34    10   x$7   Lakka/http/scaladsl/server/RejectionHandler;
          222      24    11   x$8   Lakka/http/scaladsl/server/ExceptionHandler;
           22     266     1   mat   Lakka/stream/ActorMaterializer;
           36     252     2  http   Lakka/http/scaladsl/HttpExt;
          140     148     3 route   Lscala/Function1;
            0     289     0  this   Lio/findify/s3mock/S3Mock;
      LineNumberTable:
        line 25: 0
        line 26: 23
        line 55: 37
        line 28: 40
        line 55: 85
        line 62: 141
        line 63: 284

  public void stop();
    descriptor: ()V
    flags: ACC_PUBLIC
    Code:
      stack=3, locals=1, args_size=1
         0: getstatic     #237                // Field scala/concurrent/Await$.MODULE$:Lscala/concurrent/Await$;
         3: aload_0
         4: invokespecial #323                // Method bind:()Lakka/http/scaladsl/Http$ServerBinding;
         7: invokevirtual #347                // Method akka/http/scaladsl/Http$ServerBinding.unbind:()Lscala/concurrent/Future;
        10: getstatic     #311                // Field scala/concurrent/duration/Duration$.MODULE$:Lscala/concurrent/duration/Duration$;
        13: invokevirtual #315                // Method scala/concurrent/duration/Duration$.Inf:()Lscala/concurrent/duration/Duration$Infinite;
        16: invokevirtual #319                // Method scala/concurrent/Await$.result:(Lscala/concurrent/Awaitable;Lscala/concurrent/duration/Duration;)Ljava/lang/Object;
        19: pop
        20: return
      LocalVariableTable:
        Start  Length  Slot  Name   Signature
            0      21     0  this   Lio/findify/s3mock/S3Mock;
      LineNumberTable:
        line 69: 0

  public static final scala.Function1 $anonfun$start$2(io.findify.s3mock.S3Mock, java.lang.String);
    descriptor: (Lio/findify/s3mock/S3Mock;Ljava/lang/String;)Lscala/Function1;
    flags: ACC_PUBLIC, ACC_STATIC, ACC_FINAL, ACC_SYNTHETIC
    Code:
      stack=8, locals=2, args_size=2
         0: getstatic     #145                // Field akka/http/scaladsl/server/Directives$.MODULE$:Lakka/http/scaladsl/server/Directives$;
         3: getstatic     #356                // Field scala/Predef$.MODULE$:Lscala/Predef$;
         6: iconst_4
         7: anewarray     #196                // class scala/Function1
        10: dup
        11: iconst_0
        12: new           #358                // class io/findify/s3mock/route/ListBucket
        15: dup
        16: aload_0
        17: invokevirtual #206                // Method p:()Lio/findify/s3mock/provider/Provider;
        20: invokespecial #359                // Method io/findify/s3mock/route/ListBucket."<init>":(Lio/findify/s3mock/provider/Provider;)V
        23: aload_1
        24: invokevirtual #361                // Method io/findify/s3mock/route/ListBucket.route:(Ljava/lang/String;)Lscala/Function1;
        27: aastore
        28: dup
        29: iconst_1
        30: new           #363                // class io/findify/s3mock/route/CreateBucket
        33: dup
        34: aload_0
        35: invokevirtual #206                // Method p:()Lio/findify/s3mock/provider/Provider;
        38: invokespecial #364                // Method io/findify/s3mock/route/CreateBucket."<init>":(Lio/findify/s3mock/provider/Provider;)V
        41: aload_1
        42: invokevirtual #365                // Method io/findify/s3mock/route/CreateBucket.route:(Ljava/lang/String;)Lscala/Function1;
        45: aastore
        46: dup
        47: iconst_2
        48: new           #367                // class io/findify/s3mock/route/DeleteBucket
        51: dup
        52: aload_0
        53: invokevirtual #206                // Method p:()Lio/findify/s3mock/provider/Provider;
        56: invokespecial #368                // Method io/findify/s3mock/route/DeleteBucket."<init>":(Lio/findify/s3mock/provider/Provider;)V
        59: aload_1
        60: invokevirtual #369                // Method io/findify/s3mock/route/DeleteBucket.route:(Ljava/lang/String;)Lscala/Function1;
        63: aastore
        64: dup
        65: iconst_3
        66: new           #371                // class io/findify/s3mock/route/DeleteObjects
        69: dup
        70: aload_0
        71: invokevirtual #206                // Method p:()Lio/findify/s3mock/provider/Provider;
        74: invokespecial #372                // Method io/findify/s3mock/route/DeleteObjects."<init>":(Lio/findify/s3mock/provider/Provider;)V
        77: aload_1
        78: invokevirtual #373                // Method io/findify/s3mock/route/DeleteObjects.route:(Ljava/lang/String;)Lscala/Function1;
        81: aastore
        82: checkcast     #375                // class "[Ljava/lang/Object;"
        85: invokevirtual #379                // Method scala/Predef$.wrapRefArray:([Ljava/lang/Object;)Lscala/collection/mutable/WrappedArray;
        88: invokevirtual #383                // Method akka/http/scaladsl/server/Directives$.concat:(Lscala/collection/Seq;)Lscala/Function1;
        91: areturn
      LocalVariableTable:
        Start  Length  Slot  Name   Signature
            0      92     0 $this   Lio/findify/s3mock/S3Mock;
            0      92     1 bucket$1   Ljava/lang/String;
      LineNumberTable:
        line 30: 0
        line 31: 12
        line 32: 30
        line 33: 48
        line 34: 66
    MethodParameters:
      Name                           Flags
      $this                          final synthetic
      bucket$1                       final

  public static final scala.Function1 $anonfun$start$3(io.findify.s3mock.S3Mock, java.lang.String);
    descriptor: (Lio/findify/s3mock/S3Mock;Ljava/lang/String;)Lscala/Function1;
    flags: ACC_PUBLIC, ACC_STATIC, ACC_FINAL, ACC_SYNTHETIC
    Code:
      stack=8, locals=2, args_size=2
         0: getstatic     #145                // Field akka/http/scaladsl/server/Directives$.MODULE$:Lakka/http/scaladsl/server/Directives$;
         3: getstatic     #356                // Field scala/Predef$.MODULE$:Lscala/Predef$;
         6: iconst_3
         7: anewarray     #196                // class scala/Function1
        10: dup
        11: iconst_0
        12: new           #358                // class io/findify/s3mock/route/ListBucket
        15: dup
        16: aload_0
        17: invokevirtual #206                // Method p:()Lio/findify/s3mock/provider/Provider;
        20: invokespecial #359                // Method io/findify/s3mock/route/ListBucket."<init>":(Lio/findify/s3mock/provider/Provider;)V
        23: aload_1
        24: invokevirtual #361                // Method io/findify/s3mock/route/ListBucket.route:(Ljava/lang/String;)Lscala/Function1;
        27: aastore
        28: dup
        29: iconst_1
        30: new           #363                // class io/findify/s3mock/route/CreateBucket
        33: dup
        34: aload_0
        35: invokevirtual #206                // Method p:()Lio/findify/s3mock/provider/Provider;
        38: invokespecial #364                // Method io/findify/s3mock/route/CreateBucket."<init>":(Lio/findify/s3mock/provider/Provider;)V
        41: aload_1
        42: invokevirtual #365                // Method io/findify/s3mock/route/CreateBucket.route:(Ljava/lang/String;)Lscala/Function1;
        45: aastore
        46: dup
        47: iconst_2
        48: new           #367                // class io/findify/s3mock/route/DeleteBucket
        51: dup
        52: aload_0
        53: invokevirtual #206                // Method p:()Lio/findify/s3mock/provider/Provider;
        56: invokespecial #368                // Method io/findify/s3mock/route/DeleteBucket."<init>":(Lio/findify/s3mock/provider/Provider;)V
        59: aload_1
        60: invokevirtual #369                // Method io/findify/s3mock/route/DeleteBucket.route:(Ljava/lang/String;)Lscala/Function1;
        63: aastore
        64: checkcast     #375                // class "[Ljava/lang/Object;"
        67: invokevirtual #379                // Method scala/Predef$.wrapRefArray:([Ljava/lang/Object;)Lscala/collection/mutable/WrappedArray;
        70: invokevirtual #383                // Method akka/http/scaladsl/server/Directives$.concat:(Lscala/collection/Seq;)Lscala/Function1;
        73: areturn
      LocalVariableTable:
        Start  Length  Slot  Name   Signature
            0      74     0 $this   Lio/findify/s3mock/S3Mock;
            0      74     1 bucket$1   Ljava/lang/String;
      LineNumberTable:
        line 37: 0
        line 38: 12
        line 39: 30
        line 40: 48
    MethodParameters:
      Name                           Flags
      $this                          final synthetic
      bucket$1                       final

  public static final scala.Function1 $anonfun$start$5(io.findify.s3mock.S3Mock, akka.stream.ActorMaterializer, java.lang.String, scala.collection.immutable.Map, akka.http.scaladsl.model.Uri$Path);
    descriptor: (Lio/findify/s3mock/S3Mock;Lakka/stream/ActorMaterializer;Ljava/lang/String;Lscala/collection/immutable/Map;Lakka/http/scaladsl/model/Uri$Path;)Lscala/Function1;
    flags: ACC_PUBLIC, ACC_STATIC, ACC_FINAL, ACC_SYNTHETIC
    Code:
      stack=9, locals=5, args_size=5
         0: getstatic     #145                // Field akka/http/scaladsl/server/Directives$.MODULE$:Lakka/http/scaladsl/server/Directives$;
         3: getstatic     #356                // Field scala/Predef$.MODULE$:Lscala/Predef$;
         6: bipush        7
         8: anewarray     #196                // class scala/Function1
        11: dup
        12: iconst_0
        13: new           #392                // class io/findify/s3mock/route/GetObject
        16: dup
        17: aload_0
        18: invokevirtual #206                // Method p:()Lio/findify/s3mock/provider/Provider;
        21: invokespecial #393                // Method io/findify/s3mock/route/GetObject."<init>":(Lio/findify/s3mock/provider/Provider;)V
        24: aload_2
        25: aload         4
        27: invokevirtual #397                // Method akka/http/scaladsl/model/Uri$Path.toString:()Ljava/lang/String;
        30: aload_3
        31: invokevirtual #400                // Method io/findify/s3mock/route/GetObject.route:(Ljava/lang/String;Ljava/lang/String;Lscala/collection/immutable/Map;)Lscala/Function1;
        34: aastore
        35: dup
        36: iconst_1
        37: new           #402                // class io/findify/s3mock/route/CopyObject
        40: dup
        41: aload_0
        42: invokevirtual #206                // Method p:()Lio/findify/s3mock/provider/Provider;
        45: invokespecial #403                // Method io/findify/s3mock/route/CopyObject."<init>":(Lio/findify/s3mock/provider/Provider;)V
        48: aload_2
        49: aload         4
        51: invokevirtual #397                // Method akka/http/scaladsl/model/Uri$Path.toString:()Ljava/lang/String;
        54: invokevirtual #406                // Method io/findify/s3mock/route/CopyObject.route:(Ljava/lang/String;Ljava/lang/String;)Lscala/Function1;
        57: aastore
        58: dup
        59: iconst_2
        60: new           #408                // class io/findify/s3mock/route/PutObjectMultipart
        63: dup
        64: aload_0
        65: invokevirtual #206                // Method p:()Lio/findify/s3mock/provider/Provider;
        68: aload_1
        69: invokespecial #411                // Method io/findify/s3mock/route/PutObjectMultipart."<init>":(Lio/findify/s3mock/provider/Provider;Lakka/stream/Materializer;)V
        72: aload_2
        73: aload         4
        75: invokevirtual #397                // Method akka/http/scaladsl/model/Uri$Path.toString:()Ljava/lang/String;
        78: invokevirtual #412                // Method io/findify/s3mock/route/PutObjectMultipart.route:(Ljava/lang/String;Ljava/lang/String;)Lscala/Function1;
        81: aastore
        82: dup
        83: iconst_3
        84: new           #414                // class io/findify/s3mock/route/PutObjectMultipartStart
        87: dup
        88: aload_0
        89: invokevirtual #206                // Method p:()Lio/findify/s3mock/provider/Provider;
        92: invokespecial #415                // Method io/findify/s3mock/route/PutObjectMultipartStart."<init>":(Lio/findify/s3mock/provider/Provider;)V
        95: aload_2
        96: aload         4
        98: invokevirtual #397                // Method akka/http/scaladsl/model/Uri$Path.toString:()Ljava/lang/String;
       101: invokevirtual #416                // Method io/findify/s3mock/route/PutObjectMultipartStart.route:(Ljava/lang/String;Ljava/lang/String;)Lscala/Function1;
       104: aastore
       105: dup
       106: iconst_4
       107: new           #418                // class io/findify/s3mock/route/PutObjectMultipartComplete
       110: dup
       111: aload_0
       112: invokevirtual #206                // Method p:()Lio/findify/s3mock/provider/Provider;
       115: invokespecial #419                // Method io/findify/s3mock/route/PutObjectMultipartComplete."<init>":(Lio/findify/s3mock/provider/Provider;)V
       118: aload_2
       119: aload         4
       121: invokevirtual #397                // Method akka/http/scaladsl/model/Uri$Path.toString:()Ljava/lang/String;
       124: invokevirtual #420                // Method io/findify/s3mock/route/PutObjectMultipartComplete.route:(Ljava/lang/String;Ljava/lang/String;)Lscala/Function1;
       127: aastore
       128: dup
       129: iconst_5
       130: new           #422                // class io/findify/s3mock/route/PutObject
       133: dup
       134: aload_0
       135: invokevirtual #206                // Method p:()Lio/findify/s3mock/provider/Provider;
       138: aload_1
       139: invokespecial #423                // Method io/findify/s3mock/route/PutObject."<init>":(Lio/findify/s3mock/provider/Provider;Lakka/stream/Materializer;)V
       142: aload_2
       143: aload         4
       145: invokevirtual #397                // Method akka/http/scaladsl/model/Uri$Path.toString:()Ljava/lang/String;
       148: invokevirtual #424                // Method io/findify/s3mock/route/PutObject.route:(Ljava/lang/String;Ljava/lang/String;)Lscala/Function1;
       151: aastore
       152: dup
       153: bipush        6
       155: new           #426                // class io/findify/s3mock/route/DeleteObject
       158: dup
       159: aload_0
       160: invokevirtual #206                // Method p:()Lio/findify/s3mock/provider/Provider;
       163: invokespecial #427                // Method io/findify/s3mock/route/DeleteObject."<init>":(Lio/findify/s3mock/provider/Provider;)V
       166: aload_2
       167: aload         4
       169: invokevirtual #397                // Method akka/http/scaladsl/model/Uri$Path.toString:()Ljava/lang/String;
       172: invokevirtual #428                // Method io/findify/s3mock/route/DeleteObject.route:(Ljava/lang/String;Ljava/lang/String;)Lscala/Function1;
       175: aastore
       176: checkcast     #375                // class "[Ljava/lang/Object;"
       179: invokevirtual #379                // Method scala/Predef$.wrapRefArray:([Ljava/lang/Object;)Lscala/collection/mutable/WrappedArray;
       182: invokevirtual #383                // Method akka/http/scaladsl/server/Directives$.concat:(Lscala/collection/Seq;)Lscala/Function1;
       185: areturn
      LocalVariableTable:
        Start  Length  Slot  Name   Signature
            0     186     0 $this   Lio/findify/s3mock/S3Mock;
            0     186     1 mat$1   Lakka/stream/ActorMaterializer;
            0     186     2 bucket$1   Ljava/lang/String;
            0     186     3 params$1   Lscala/collection/immutable/Map;
            0     186     4   key   Lakka/http/scaladsl/model/Uri$Path;
      LineNumberTable:
        line 44: 0
        line 45: 13
        line 46: 37
        line 47: 60
        line 48: 84
        line 49: 107
        line 50: 130
        line 51: 155
    MethodParameters:
      Name                           Flags
      $this                          final synthetic
      mat$1                          final
      bucket$1                       final
      params$1                       final
      key                            final

  public static final scala.Function1 $anonfun$start$4(io.findify.s3mock.S3Mock, akka.stream.ActorMaterializer, java.lang.String, scala.collection.immutable.Map);
    descriptor: (Lio/findify/s3mock/S3Mock;Lakka/stream/ActorMaterializer;Ljava/lang/String;Lscala/collection/immutable/Map;)Lscala/Function1;
    flags: ACC_PUBLIC, ACC_STATIC, ACC_FINAL, ACC_SYNTHETIC
    Code:
      stack=5, locals=4, args_size=4
         0: getstatic     #150                // Field akka/http/scaladsl/server/Directive$.MODULE$:Lakka/http/scaladsl/server/Directive$;
         3: getstatic     #145                // Field akka/http/scaladsl/server/Directives$.MODULE$:Lakka/http/scaladsl/server/Directives$;
         6: getstatic     #145                // Field akka/http/scaladsl/server/Directives$.MODULE$:Lakka/http/scaladsl/server/Directives$;
         9: invokevirtual #437                // Method akka/http/scaladsl/server/Directives$.RemainingPath:()Lakka/http/scaladsl/server/PathMatchers$RemainingPath$;
        12: invokevirtual #440                // Method akka/http/scaladsl/server/Directives$.path:(Lakka/http/scaladsl/server/PathMatcher;)Lakka/http/scaladsl/server/Directive;
        15: getstatic     #163                // Field akka/http/scaladsl/server/util/ApplyConverter$.MODULE$:Lakka/http/scaladsl/server/util/ApplyConverter$;
        18: invokevirtual #167                // Method akka/http/scaladsl/server/util/ApplyConverter$.hac1:()Lakka/http/scaladsl/server/util/ApplyConverter;
        21: invokevirtual #171                // Method akka/http/scaladsl/server/Directive$.addDirectiveApply:(Lakka/http/scaladsl/server/Directive;Lakka/http/scaladsl/server/util/ApplyConverter;)Lscala/Function1;
        24: aload_0
        25: aload_1
        26: aload_2
        27: aload_3
        28: invokedynamic #447,  0            // InvokeDynamic #2:apply:(Lio/findify/s3mock/S3Mock;Lakka/stream/ActorMaterializer;Ljava/lang/String;Lscala/collection/immutable/Map;)Lscala/Function1;
        33: invokeinterface #198,  2          // InterfaceMethod scala/Function1.apply:(Ljava/lang/Object;)Ljava/lang/Object;
        38: checkcast     #196                // class scala/Function1
        41: areturn
      LocalVariableTable:
        Start  Length  Slot  Name   Signature
            0      42     0 $this   Lio/findify/s3mock/S3Mock;
            0      42     1 mat$1   Lakka/stream/ActorMaterializer;
            0      42     2 bucket$1   Ljava/lang/String;
            0      42     3 params   Lscala/collection/immutable/Map;
      LineNumberTable:
        line 43: 0
    MethodParameters:
      Name                           Flags
      $this                          final synthetic
      mat$1                          final
      bucket$1                       final
      params                         final

  public static final scala.Function1 $anonfun$start$1(io.findify.s3mock.S3Mock, akka.stream.ActorMaterializer, java.lang.String);
    descriptor: (Lio/findify/s3mock/S3Mock;Lakka/stream/ActorMaterializer;Ljava/lang/String;)Lscala/Function1;
    flags: ACC_PUBLIC, ACC_STATIC, ACC_FINAL, ACC_SYNTHETIC
    Code:
      stack=5, locals=3, args_size=3
         0: getstatic     #145                // Field akka/http/scaladsl/server/Directives$.MODULE$:Lakka/http/scaladsl/server/Directives$;
         3: getstatic     #145                // Field akka/http/scaladsl/server/Directives$.MODULE$:Lakka/http/scaladsl/server/Directives$;
         6: getstatic     #150                // Field akka/http/scaladsl/server/Directive$.MODULE$:Lakka/http/scaladsl/server/Directive$;
         9: getstatic     #145                // Field akka/http/scaladsl/server/Directives$.MODULE$:Lakka/http/scaladsl/server/Directives$;
        12: invokevirtual #451                // Method akka/http/scaladsl/server/Directives$.pathSingleSlash:()Lakka/http/scaladsl/server/Directive;
        15: invokevirtual #455                // Method akka/http/scaladsl/server/Directive$.addByNameNullaryApply:(Lakka/http/scaladsl/server/Directive;)Lscala/Function1;
        18: aload_0
        19: aload_2
        20: invokedynamic #464,  0            // InvokeDynamic #3:apply:(Lio/findify/s3mock/S3Mock;Ljava/lang/String;)Lscala/Function0;
        25: invokeinterface #198,  2          // InterfaceMethod scala/Function1.apply:(Ljava/lang/Object;)Ljava/lang/Object;
        30: checkcast     #196                // class scala/Function1
        33: invokevirtual #202                // Method akka/http/scaladsl/server/Directives$._enhanceRouteWithConcatenation:(Lscala/Function1;)Lakka/http/scaladsl/server/RouteConcatenation$RouteWithConcatenation;
        36: getstatic     #150                // Field akka/http/scaladsl/server/Directive$.MODULE$:Lakka/http/scaladsl/server/Directive$;
        39: getstatic     #145                // Field akka/http/scaladsl/server/Directives$.MODULE$:Lakka/http/scaladsl/server/Directives$;
        42: invokevirtual #467                // Method akka/http/scaladsl/server/Directives$.pathEnd:()Lakka/http/scaladsl/server/Directive;
        45: invokevirtual #455                // Method akka/http/scaladsl/server/Directive$.addByNameNullaryApply:(Lakka/http/scaladsl/server/Directive;)Lscala/Function1;
        48: aload_0
        49: aload_2
        50: invokedynamic #471,  0            // InvokeDynamic #4:apply:(Lio/findify/s3mock/S3Mock;Ljava/lang/String;)Lscala/Function0;
        55: invokeinterface #198,  2          // InterfaceMethod scala/Function1.apply:(Ljava/lang/Object;)Ljava/lang/Object;
        60: checkcast     #196                // class scala/Function1
        63: invokevirtual #218                // Method akka/http/scaladsl/server/RouteConcatenation$RouteWithConcatenation.$tilde:(Lscala/Function1;)Lscala/Function1;
        66: invokevirtual #202                // Method akka/http/scaladsl/server/Directives$._enhanceRouteWithConcatenation:(Lscala/Function1;)Lakka/http/scaladsl/server/RouteConcatenation$RouteWithConcatenation;
        69: getstatic     #150                // Field akka/http/scaladsl/server/Directive$.MODULE$:Lakka/http/scaladsl/server/Directive$;
        72: getstatic     #145                // Field akka/http/scaladsl/server/Directives$.MODULE$:Lakka/http/scaladsl/server/Directives$;
        75: invokevirtual #474                // Method akka/http/scaladsl/server/Directives$.parameterMap:()Lakka/http/scaladsl/server/Directive;
        78: getstatic     #163                // Field akka/http/scaladsl/server/util/ApplyConverter$.MODULE$:Lakka/http/scaladsl/server/util/ApplyConverter$;
        81: invokevirtual #167                // Method akka/http/scaladsl/server/util/ApplyConverter$.hac1:()Lakka/http/scaladsl/server/util/ApplyConverter;
        84: invokevirtual #171                // Method akka/http/scaladsl/server/Directive$.addDirectiveApply:(Lakka/http/scaladsl/server/Directive;Lakka/http/scaladsl/server/util/ApplyConverter;)Lscala/Function1;
        87: aload_0
        88: aload_1
        89: aload_2
        90: invokedynamic #481,  0            // InvokeDynamic #5:apply:(Lio/findify/s3mock/S3Mock;Lakka/stream/ActorMaterializer;Ljava/lang/String;)Lscala/Function1;
        95: invokeinterface #198,  2          // InterfaceMethod scala/Function1.apply:(Ljava/lang/Object;)Ljava/lang/Object;
       100: checkcast     #196                // class scala/Function1
       103: invokevirtual #218                // Method akka/http/scaladsl/server/RouteConcatenation$RouteWithConcatenation.$tilde:(Lscala/Function1;)Lscala/Function1;
       106: areturn
      LocalVariableTable:
        Start  Length  Slot  Name   Signature
            0     107     0 $this   Lio/findify/s3mock/S3Mock;
            0     107     1 mat$1   Lakka/stream/ActorMaterializer;
            0     107     2 bucket   Ljava/lang/String;
      LineNumberTable:
        line 36: 0
        line 29: 3
        line 30: 18
        line 36: 36
        line 37: 48
        line 42: 69
    MethodParameters:
      Name                           Flags
      $this                          final synthetic
      mat$1                          final
      bucket                         final

  public static final akka.http.scaladsl.marshalling.ToResponseMarshallable $anonfun$start$7(io.findify.s3mock.S3Mock, akka.http.scaladsl.model.HttpRequest);
    descriptor: (Lio/findify/s3mock/S3Mock;Lakka/http/scaladsl/model/HttpRequest;)Lakka/http/scaladsl/marshalling/ToResponseMarshallable;
    flags: ACC_PUBLIC, ACC_STATIC, ACC_FINAL, ACC_SYNTHETIC
    Code:
      stack=8, locals=2, args_size=2
         0: aload_0
         1: invokevirtual #486                // Method logger:()Lcom/typesafe/scalalogging/Logger;
         4: invokevirtual #490                // Method com/typesafe/scalalogging/Logger.underlying:()Lorg/slf4j/Logger;
         7: invokeinterface #496,  1          // InterfaceMethod org/slf4j/Logger.isErrorEnabled:()Z
        12: ifeq          104
        15: aload_0
        16: invokevirtual #486                // Method logger:()Lcom/typesafe/scalalogging/Logger;
        19: invokevirtual #490                // Method com/typesafe/scalalogging/Logger.underlying:()Lorg/slf4j/Logger;
        22: new           #498                // class scala/StringContext
        25: dup
        26: getstatic     #356                // Field scala/Predef$.MODULE$:Lscala/Predef$;
        29: iconst_3
        30: anewarray     #500                // class java/lang/String
        33: dup
        34: iconst_0
        35: ldc_w         #502                // String method not implemented:
        38: aastore
        39: dup
        40: iconst_1
        41: ldc_w         #504                // String
        44: aastore
        45: dup
        46: iconst_2
        47: ldc_w         #506                // String
        50: aastore
        51: checkcast     #375                // class "[Ljava/lang/Object;"
        54: invokevirtual #379                // Method scala/Predef$.wrapRefArray:([Ljava/lang/Object;)Lscala/collection/mutable/WrappedArray;
        57: invokespecial #509                // Method scala/StringContext."<init>":(Lscala/collection/Seq;)V
        60: getstatic     #356                // Field scala/Predef$.MODULE$:Lscala/Predef$;
        63: iconst_2
        64: anewarray     #4                  // class java/lang/Object
        67: dup
        68: iconst_0
        69: aload_1
        70: invokevirtual #515                // Method akka/http/scaladsl/model/HttpRequest.method:()Lakka/http/scaladsl/model/HttpMethod;
        73: invokevirtual #520                // Method akka/http/scaladsl/model/HttpMethod.value:()Ljava/lang/String;
        76: aastore
        77: dup
        78: iconst_1
        79: aload_1
        80: invokevirtual #524                // Method akka/http/scaladsl/model/HttpRequest.uri:()Lakka/http/scaladsl/model/Uri;
        83: invokevirtual #525                // Method akka/http/scaladsl/model/Uri.toString:()Ljava/lang/String;
        86: aastore
        87: invokevirtual #529                // Method scala/Predef$.genericWrapArray:(Ljava/lang/Object;)Lscala/collection/mutable/WrappedArray;
        90: invokevirtual #533                // Method scala/StringContext.s:(Lscala/collection/Seq;)Ljava/lang/String;
        93: invokeinterface #537,  2          // InterfaceMethod org/slf4j/Logger.error:(Ljava/lang/String;)V
        98: getstatic     #543                // Field scala/runtime/BoxedUnit.UNIT:Lscala/runtime/BoxedUnit;
       101: goto          107
       104: getstatic     #543                // Field scala/runtime/BoxedUnit.UNIT:Lscala/runtime/BoxedUnit;
       107: pop
       108: getstatic     #548                // Field akka/http/scaladsl/marshalling/ToResponseMarshallable$.MODULE$:Lakka/http/scaladsl/marshalling/ToResponseMarshallable$;
       111: getstatic     #553                // Field akka/http/scaladsl/model/HttpResponse$.MODULE$:Lakka/http/scaladsl/model/HttpResponse$;
       114: getstatic     #558                // Field akka/http/scaladsl/model/StatusCodes$.MODULE$:Lakka/http/scaladsl/model/StatusCodes$;
       117: invokevirtual #562                // Method akka/http/scaladsl/model/StatusCodes$.NotImplemented:()Lakka/http/scaladsl/model/StatusCodes$ServerError;
       120: getstatic     #553                // Field akka/http/scaladsl/model/HttpResponse$.MODULE$:Lakka/http/scaladsl/model/HttpResponse$;
       123: invokevirtual #565                // Method akka/http/scaladsl/model/HttpResponse$.apply$default$2:()Lscala/collection/immutable/Seq;
       126: getstatic     #553                // Field akka/http/scaladsl/model/HttpResponse$.MODULE$:Lakka/http/scaladsl/model/HttpResponse$;
       129: invokevirtual #569                // Method akka/http/scaladsl/model/HttpResponse$.apply$default$3:()Lakka/http/scaladsl/model/ResponseEntity;
       132: getstatic     #553                // Field akka/http/scaladsl/model/HttpResponse$.MODULE$:Lakka/http/scaladsl/model/HttpResponse$;
       135: invokevirtual #573                // Method akka/http/scaladsl/model/HttpResponse$.apply$default$4:()Lakka/http/scaladsl/model/HttpProtocol;
       138: invokevirtual #576                // Method akka/http/scaladsl/model/HttpResponse$.apply:(Lakka/http/scaladsl/model/StatusCode;Lscala/collection/immutable/Seq;Lakka/http/scaladsl/model/ResponseEntity;Lakka/http/scaladsl/model/HttpProtocol;)Lakka/http/scaladsl/model/HttpResponse;
       141: getstatic     #581                // Field akka/http/scaladsl/marshalling/Marshaller$.MODULE$:Lakka/http/scaladsl/marshalling/Marshaller$;
       144: invokevirtual #585                // Method akka/http/scaladsl/marshalling/Marshaller$.fromResponse:()Lakka/http/scaladsl/marshalling/Marshaller;
       147: invokevirtual #588                // Method akka/http/scaladsl/marshalling/ToResponseMarshallable$.apply:(Ljava/lang/Object;Lakka/http/scaladsl/marshalling/Marshaller;)Lakka/http/scaladsl/marshalling/ToResponseMarshallable;
       150: areturn
      LocalVariableTable:
        Start  Length  Slot  Name   Signature
            0     151     0 $this   Lio/findify/s3mock/S3Mock;
            0     151     1 request$1   Lakka/http/scaladsl/model/HttpRequest;
      LineNumberTable:
        line 57: 0
        line 58: 108
      StackMapTable: number_of_entries = 2
        frame_type = 251 /* same_frame_extended */
          offset_delta = 104
        frame_type = 66 /* same_locals_1_stack_item */
          stack = [ class scala/runtime/BoxedUnit ]
    MethodParameters:
      Name                           Flags
      $this                          final synthetic
      request$1                      final

  public static final akka.http.scaladsl.server.StandardRoute $anonfun$start$6(io.findify.s3mock.S3Mock, akka.http.scaladsl.model.HttpRequest);
    descriptor: (Lio/findify/s3mock/S3Mock;Lakka/http/scaladsl/model/HttpRequest;)Lakka/http/scaladsl/server/StandardRoute;
    flags: ACC_PUBLIC, ACC_STATIC, ACC_FINAL, ACC_SYNTHETIC
    Code:
      stack=3, locals=2, args_size=2
         0: getstatic     #145                // Field akka/http/scaladsl/server/Directives$.MODULE$:Lakka/http/scaladsl/server/Directives$;
         3: aload_0
         4: aload_1
         5: invokedynamic #598,  0            // InvokeDynamic #6:apply:(Lio/findify/s3mock/S3Mock;Lakka/http/scaladsl/model/HttpRequest;)Lscala/Function0;
        10: invokevirtual #602                // Method akka/http/scaladsl/server/Directives$.complete:(Lscala/Function0;)Lakka/http/scaladsl/server/StandardRoute;
        13: areturn
      LocalVariableTable:
        Start  Length  Slot  Name   Signature
            0      14     0 $this   Lio/findify/s3mock/S3Mock;
            0      14     1 request   Lakka/http/scaladsl/model/HttpRequest;
      LineNumberTable:
        line 56: 0
    MethodParameters:
      Name                           Flags
      $this                          final synthetic
      request                        final

  public io.findify.s3mock.S3Mock(int, io.findify.s3mock.provider.Provider, akka.actor.ActorSystem);
    descriptor: (ILio/findify/s3mock/provider/Provider;Lakka/actor/ActorSystem;)V
    flags: ACC_PUBLIC
    Code:
      stack=2, locals=4, args_size=4
         0: aload_0
         1: iload_1
         2: putfield      #290                // Field port:I
         5: aload_0
         6: aload_3
         7: putfield      #127                // Field system:Lakka/actor/ActorSystem;
        10: aload_0
        11: invokespecial #606                // Method java/lang/Object."<init>":()V
        14: aload_0
        15: invokestatic  #610                // InterfaceMethod com/typesafe/scalalogging/LazyLogging.$init$:(Lcom/typesafe/scalalogging/LazyLogging;)V
        18: aload_0
        19: aload_2
        20: putfield      #106                // Field p:Lio/findify/s3mock/provider/Provider;
        23: return
      LocalVariableTable:
        Start  Length  Slot  Name   Signature
            0      24     0  this   Lio/findify/s3mock/S3Mock;
            0      24     1  port   I
            0      24     2 provider   Lio/findify/s3mock/provider/Provider;
            0      24     3 system   Lakka/actor/ActorSystem;
      LineNumberTable:
        line 20: 0
        line 21: 18
        line 20: 23
    MethodParameters:
      Name                           Flags
      port                           final
      provider                       final
      system                         final

  private static java.lang.Object $deserializeLambda$(java.lang.invoke.SerializedLambda);
    descriptor: (Ljava/lang/invoke/SerializedLambda;)Ljava/lang/Object;
    flags: ACC_PRIVATE, ACC_STATIC, ACC_SYNTHETIC
    Code:
      stack=1, locals=1, args_size=1
         0: aload_0
         1: invokedynamic #622,  0            // InvokeDynamic #7:lambdaDeserialize:(Ljava/lang/invoke/SerializedLambda;)Ljava/lang/Object;
         6: areturn
}
BootstrapMethods:
  0: #178 invokestatic java/lang/invoke/LambdaMetafactory.altMetafactory:(Ljava/lang/invoke/MethodHandles$Lookup;Ljava/lang/String;Ljava/lang/invoke/MethodType;[Ljava/lang/Object;)Ljava/lang/invoke/CallSite;
    Method arguments:
      #180 (Ljava/lang/Object;)Ljava/lang/Object;
      #185 invokestatic io/findify/s3mock/S3Mock.$anonfun$start$1:(Lio/findify/s3mock/S3Mock;Lakka/stream/ActorMaterializer;Ljava/lang/String;)Lscala/Function1;
      #187 (Ljava/lang/String;)Lscala/Function1;
      #188 3
      #189 1
      #191 scala/Serializable
  1: #178 invokestatic java/lang/invoke/LambdaMetafactory.altMetafactory:(Ljava/lang/invoke/MethodHandles$Lookup;Ljava/lang/String;Ljava/lang/invoke/MethodType;[Ljava/lang/Object;)Ljava/lang/invoke/CallSite;
    Method arguments:
      #180 (Ljava/lang/Object;)Ljava/lang/Object;
      #227 invokestatic io/findify/s3mock/S3Mock.$anonfun$start$6:(Lio/findify/s3mock/S3Mock;Lakka/http/scaladsl/model/HttpRequest;)Lakka/http/scaladsl/server/StandardRoute;
      #229 (Lakka/http/scaladsl/model/HttpRequest;)Lakka/http/scaladsl/server/StandardRoute;
      #188 3
      #189 1
      #191 scala/Serializable
  2: #178 invokestatic java/lang/invoke/LambdaMetafactory.altMetafactory:(Ljava/lang/invoke/MethodHandles$Lookup;Ljava/lang/String;Ljava/lang/invoke/MethodType;[Ljava/lang/Object;)Ljava/lang/invoke/CallSite;
    Method arguments:
      #180 (Ljava/lang/Object;)Ljava/lang/Object;
      #443 invokestatic io/findify/s3mock/S3Mock.$anonfun$start$5:(Lio/findify/s3mock/S3Mock;Lakka/stream/ActorMaterializer;Ljava/lang/String;Lscala/collection/immutable/Map;Lakka/http/scaladsl/model/Uri$Path;)Lscala/Function1;
      #445 (Lakka/http/scaladsl/model/Uri$Path;)Lscala/Function1;
      #188 3
      #189 1
      #191 scala/Serializable
  3: #178 invokestatic java/lang/invoke/LambdaMetafactory.altMetafactory:(Ljava/lang/invoke/MethodHandles$Lookup;Ljava/lang/String;Ljava/lang/invoke/MethodType;[Ljava/lang/Object;)Ljava/lang/invoke/CallSite;
    Method arguments:
      #457 ()Ljava/lang/Object;
      #460 invokestatic io/findify/s3mock/S3Mock.$anonfun$start$2:(Lio/findify/s3mock/S3Mock;Ljava/lang/String;)Lscala/Function1;
      #461 ()Lscala/Function1;
      #188 3
      #189 1
      #191 scala/Serializable
  4: #178 invokestatic java/lang/invoke/LambdaMetafactory.altMetafactory:(Ljava/lang/invoke/MethodHandles$Lookup;Ljava/lang/String;Ljava/lang/invoke/MethodType;[Ljava/lang/Object;)Ljava/lang/invoke/CallSite;
    Method arguments:
      #457 ()Ljava/lang/Object;
      #470 invokestatic io/findify/s3mock/S3Mock.$anonfun$start$3:(Lio/findify/s3mock/S3Mock;Ljava/lang/String;)Lscala/Function1;
      #461 ()Lscala/Function1;
      #188 3
      #189 1
      #191 scala/Serializable
  5: #178 invokestatic java/lang/invoke/LambdaMetafactory.altMetafactory:(Ljava/lang/invoke/MethodHandles$Lookup;Ljava/lang/String;Ljava/lang/invoke/MethodType;[Ljava/lang/Object;)Ljava/lang/invoke/CallSite;
    Method arguments:
      #180 (Ljava/lang/Object;)Ljava/lang/Object;
      #477 invokestatic io/findify/s3mock/S3Mock.$anonfun$start$4:(Lio/findify/s3mock/S3Mock;Lakka/stream/ActorMaterializer;Ljava/lang/String;Lscala/collection/immutable/Map;)Lscala/Function1;
      #479 (Lscala/collection/immutable/Map;)Lscala/Function1;
      #188 3
      #189 1
      #191 scala/Serializable
  6: #178 invokestatic java/lang/invoke/LambdaMetafactory.altMetafactory:(Ljava/lang/invoke/MethodHandles$Lookup;Ljava/lang/String;Ljava/lang/invoke/MethodType;[Ljava/lang/Object;)Ljava/lang/invoke/CallSite;
    Method arguments:
      #457 ()Ljava/lang/Object;
      #593 invokestatic io/findify/s3mock/S3Mock.$anonfun$start$7:(Lio/findify/s3mock/S3Mock;Lakka/http/scaladsl/model/HttpRequest;)Lakka/http/scaladsl/marshalling/ToResponseMarshallable;
      #595 ()Lakka/http/scaladsl/marshalling/ToResponseMarshallable;
      #188 3
      #189 1
      #191 scala/Serializable
  7: #619 invokestatic scala/runtime/LambdaDeserialize.bootstrap:(Ljava/lang/invoke/MethodHandles$Lookup;Ljava/lang/String;Ljava/lang/invoke/MethodType;[Ljava/lang/invoke/MethodHandle;)Ljava/lang/invoke/CallSite;
    Method arguments:
      #185 invokestatic io/findify/s3mock/S3Mock.$anonfun$start$1:(Lio/findify/s3mock/S3Mock;Lakka/stream/ActorMaterializer;Ljava/lang/String;)Lscala/Function1;
      #227 invokestatic io/findify/s3mock/S3Mock.$anonfun$start$6:(Lio/findify/s3mock/S3Mock;Lakka/http/scaladsl/model/HttpRequest;)Lakka/http/scaladsl/server/StandardRoute;
      #443 invokestatic io/findify/s3mock/S3Mock.$anonfun$start$5:(Lio/findify/s3mock/S3Mock;Lakka/stream/ActorMaterializer;Ljava/lang/String;Lscala/collection/immutable/Map;Lakka/http/scaladsl/model/Uri$Path;)Lscala/Function1;
      #460 invokestatic io/findify/s3mock/S3Mock.$anonfun$start$2:(Lio/findify/s3mock/S3Mock;Ljava/lang/String;)Lscala/Function1;
      #470 invokestatic io/findify/s3mock/S3Mock.$anonfun$start$3:(Lio/findify/s3mock/S3Mock;Ljava/lang/String;)Lscala/Function1;
      #477 invokestatic io/findify/s3mock/S3Mock.$anonfun$start$4:(Lio/findify/s3mock/S3Mock;Lakka/stream/ActorMaterializer;Ljava/lang/String;Lscala/collection/immutable/Map;)Lscala/Function1;
      #593 invokestatic io/findify/s3mock/S3Mock.$anonfun$start$7:(Lio/findify/s3mock/S3Mock;Lakka/http/scaladsl/model/HttpRequest;)Lakka/http/scaladsl/marshalling/ToResponseMarshallable;
SourceFile: "S3Mock.scala"
InnerClasses:
     public static final #15= #12 of #14; //ServerBinding=class akka/http/scaladsl/Http$ServerBinding of class akka/http/scaladsl/Http
     public static final #20= #17 of #19; //ServerError=class akka/http/scaladsl/model/StatusCodes$ServerError of class akka/http/scaladsl/model/StatusCodes
     public static abstract #25= #22 of #24; //Path=class akka/http/scaladsl/model/Uri$Path of class akka/http/scaladsl/model/Uri
     public #30= #27 of #29; //RemainingPath$=class akka/http/scaladsl/server/PathMatchers$RemainingPath$ of class akka/http/scaladsl/server/PathMatchers
     public #33= #32 of #29; //Segment$=class akka/http/scaladsl/server/PathMatchers$Segment$ of class akka/http/scaladsl/server/PathMatchers
     public static #38= #35 of #37; //RouteWithConcatenation=class akka/http/scaladsl/server/RouteConcatenation$RouteWithConcatenation of class akka/http/scaladsl/server/RouteConcatenation
     public static #41= #40 of #2; //Builder=class io/findify/s3mock/S3Mock$Builder of class io/findify/s3mock/S3Mock
     public static final #46= #43 of #45; //Lookup=class java/lang/invoke/MethodHandles$Lookup of class java/lang/invoke/MethodHandles
     public static abstract #51= #48 of #50; //Infinite=class scala/concurrent/duration/Duration$Infinite of class scala/concurrent/duration/Duration
RuntimeVisibleAnnotations:
  0: #8(#9=s#10)
Error: unknown attribute
  ScalaInlineInfo: length = 0x4F
   01 00 00 0F 00 B5 00 B6 01 01 5C 01 5D 01 01 81
   01 5D 01 01 AF 01 B0 01 01 82 01 83 01 00 DF 00
   E0 01 01 E2 01 E3 01 00 CF 02 5B 00 00 3A 00 6B
   01 00 6E 00 6F 01 00 56 00 57 01 00 3C 00 57 00
   00 38 00 68 00 00 71 00 6B 00 01 56 01 57 00
Error: unknown attribute
  ScalaSig: length = 0x3
   05 00 00
```

## Hexdump

```
0000000 ca fe ba be 00 00 00 34 02 7a 01 00 18 69 6f 2f
0000010 66 69 6e 64 69 66 79 2f 73 33 6d 6f 63 6b 2f 53
0000020 33 4d 6f 63 6b 07 00 01 01 00 10 6a 61 76 61 2f
0000030 6c 61 6e 67 2f 4f 62 6a 65 63 74 07 00 03 01 00
0000040 25 63 6f 6d 2f 74 79 70 65 73 61 66 65 2f 73 63
0000050 61 6c 61 6c 6f 67 67 69 6e 67 2f 4c 61 7a 79 4c
0000060 6f 67 67 69 6e 67 07 00 05 01 00 0c 53 33 4d 6f
0000070 63 6b 2e 73 63 61 6c 61 01 00 1e 4c 73 63 61 6c
0000080 61 2f 72 65 66 6c 65 63 74 2f 53 63 61 6c 61 53
0000090 69 67 6e 61 74 75 72 65 3b 01 00 05 62 79 74 65
00000a0 73 01 05 a3 06 01 05 25 64 01 42 01 03 01 25 11
00000b0 61 61 55 1a 4e 5f 0e 5c 27 42 41 02 05 03 19 19
00000c0 38 27 5c 38 64 57 2a 11 51 41 42 01 08 4d 26 74
00000d0 47 2d 1b 34 7a 15 05 39 11 41 41 35 70 07 01 19
00000e0 32 01 01 06 11 21 09 59 61 22 44 01 0d 15 05 69
00000f0 11 21 42 3a 64 43 32 0c 17 42 41 08 0d 05 19 09
0000100 65 2e 1f 2a 66 4d 42 11 11 03 47 07 02 25 29 11
0000110 31 03 46 01 0d 67 0e 0c 47 2e 19 37 70 4f 1e 4c
0000120 67 6e 1a 06 03 2b 59 09 01 02 5e 3d 71 4b 4e 0c
0000130 67 2d 1a 06 02 2f 05 19 31 6d 5c 37 0a 05 65 11
0000140 22 61 03 27 62 75 66 64 75 6e 5a 34 6a 5d 1e 44
0000150 01 62 07 01 03 02 03 06 49 01 48 01 05 61 3e 14
0000160 48 0f 05 02 0c 3b 25 11 61 04 04 02 04 13 3a 24
0000170 08 02 03 11 01 05 03 05 0b 11 42 11 02 11 41 14
0000180 78 4e 5e 35 65 4b 4a 04 22 41 09 13 0e 03 0d 52
0000190 21 01 09 02 0a 05 15 1a 23 01 03 29 73 5f 5a 4c
00001a0 47 2d 1a 3a 09 11 1d 02 21 11 21 51 01 0c 21 0a
00001b0 61 61 5d 3d 74 69 16 6c 07 43 41 15 2f 1b 05 51
00001c0 23 42 41 16 2d 03 15 09 37 0d 5e 38 73 15 05 69
00001d0 13 01 42 31 6c 57 06 4c 21 61 0c 16 03 17 05 1b
00001e0 47 6f 1c 3a 54 73 4e 24 58 2d 1c 05 06 63 01 21
00001f0 09 41 4d 01 07 79 25 74 17 0e 1e 20 15 07 4d 3a
0000200 04 08 06 02 35 6d 41 11 51 07 41 07 02 05 21 39
0000210 71 05 0d 49 01 02 08 41 03 22 42 0e 31 01 04 61
0000220 02 22 02 11 31 01 04 09 03 62 02 1e 01 05 04 25
0000230 19 61 4f 01 02 61 56 09 11 05 03 04 3e 01 01 06
0000240 49 21 49 01 03 61 02 42 11 62 10 01 41 02 03 07
0000250 49 11 02 21 02 09 09 4c 67 0e 5a 0b 02 03 42 11
0000260 21 49 13 08 03 07 22 6b 11 01 12 06 03 0b 1a 0b
0000270 01 62 5d 32 62 59 06 24 37 0f 1c 06 03 0f 32 0a
0000280 41 01 1b 3b 75 61 26 11 11 0a 52 01 05 11 52 24
0000290 08 2f 03 02 4c 19 0a 69 31 2b 1a 3a 77 4b 4a 14
00002a0 15 4e 1c 33 6a 5d 1e 54 21 21 13 23 09 13 39 03
00002b0 01 19 21 61 01 0a 13 79 15 01 03 32 6a 5d 12 7c
00002c0 46 25 5a 39 15 05 41 1b 06 43 41 06 52 13 09 11
00002d0 46 42 01 03 56 5d 26 24 08 62 02 2b 4e 03 03 05
00002e0 0d 21 51 01 04 71 12 0a 04 42 02 2c 01 41 03 26
00002f0 11 29 41 03 63 53 3a 24 07 05 43 03 59 01 11 05
0000300 01 29 41 03 74 69 06 14 48 0f 43 03 5b 01 11 05
0000310 31 2c 01 03 74 69 3e 04 58 23 01 29 08 0b 75 13
0000320 01 12 01 30 02 0d 4d 1b 54 6a 5c 32 6c 21 09 29
0000330 74 4c 42 03 02 05 21 05 01 6d 05 02 60 15 21 29
0000340 11 67 18 43 01 45 52 09 61 0c 43 03 65 3f 12 05
0000350 51 2d 41 03 62 61 42 64 17 10 06 02 35 4d 22 29
0000360 31 64 19 61 01 39 21 29 41 6d 18 43 01 51 52 19
0000370 41 27 1b 36 09 0b 6d 39 07 19 01 0f 09 0b 2d 3c
0000380 07 19 01 37 02 07 11 4c 27 0f 05 02 6e 69 3a 11
0000390 61 4e 1d 09 03 5f 32 69 11 01 1d 06 03 63 22 09
00003a0 61 01 10 3a 70 5f 52 74 14 42 41 3a 0d 03 19 01
00003b0 26 2f 1a 33 66 4d 26 11 51 4f 1e 02 07 27 52 14
00003c0 18 4e 5c 34 0b 05 4d 64 01 22 02 3d 60 09 03 49
00003d0 18 41 42 32 73 4b 06 24 58 0d 06 02 35 75 22 29
00003e0 31 64 1e 61 01 39 21 29 01 70 18 43 01 79 52 19
00003f0 41 27 20 40 09 0b 6d 59 08 19 01 0f 09 0b 2d 5c
0000400 08 19 01 37 07 0d 05 05 71 0c 41 41 02 05 1d 11
0000410 55 2f 1b 37 65 4b 4a 1c 22 61 20 06 09 0d 45 7a
0000420 48 11 41 41 04 29 09 09 49 01 45 02 02 0c 7d 6c
0000430 11 61 18 05 0a 03 1f 79 08 19 21 43 05 03 23 09
0000440 31 02 5a 33 67 43 56 64 47 0f 55 38 73 69 56 09
0000450 41 04 43 05 02 16 7d 04 0d 11 22 03 02 18 05 79
0000460 41 2d 1a 34 62 6b 32 24 08 6b 1c 3a 75 3f 12 2a
0000470 17 0f 46 02 51 03 33 41 01 02 56 41 0a 03 03 05
0000480 0d 01 08 05 08 03 3b 79 08 15 29 03 1d 03 31 21
0000490 57 4d 5a 31 76 59 52 04 76 4e 1d 3b 21 11 21 09
00004a0 09 63 20 61 01 0a 13 59 14 61 04 33 66 4d 06 2c
00004b0 48 0e 1e 29 73 5f 5a 4c 47 2d 1a 3a 09 13 05 15
00004c0 72 10 31 41 05 0a 05 1d 12 61 05 33 66 4d 06 2c
00004d0 48 0e 1e 29 73 5f 5a 4c 47 2d 1a 3a 60 49 15 0c
00004e0 48 63 01 29 02 2a 21 41 41 2b 61 09 02 02 03 07
00004f0 11 05 43 04 02 2e 7d 04 0b 15 42 11 02 21 11 2c
0000500 67 2d 59 3b 6d 69 42 13 78 4e 5e 35 65 4b 4a 04
0000510 03 62 42 41 19 7f 12 05 11 31 47 01 09 6f 26 24
0000520 08 0e 55 38 73 69 52 21 11 11 42 41 1b 11 19 59
0000530 12 71 06 61 01 39 21 39 11 11 48 40 05 02 05 1d
0000540 11 61 45 3c 6a 69 22 4c 65 2e 54 33 6e 5f 4a 4c
0000550 28 29 59 32 6c 4b 3a 24 07 62 42 41 1f 7f 12 05
0000560 11 71 48 01 10 6f 26 24 08 4e 52 35 6d 4b 0a 0b
0000570 37 6d 5b 33 6f 49 52 21 11 11 42 41 21 11 1d 09
0000580 19 25 61 0f 41 02 31 0c 41 01 5d 31 75 51 22 39
0000590 11 71 49 40 05 02 05 25 13 21 02 32 76 53 32 24
00005a0 47 23 01 1b 09 13 05 35 73 2c 25 41 05 02 05 3d
00005b0 13 61 07 13 6d 4b 4e 1c 18 4e 5c 35 75 49 1d 14
00005c0 58 2d 19 3b 66 65 12 22 57 4d 5a 31 76 59 52 24
00005d0 33 07 06 04 02 52 05 15 14 71 0d 16 04 51 05 4d
00005e0 33 46 41 41 2b 21 11 09 39 26 21 19 0e 05 05 65
00005f0 23 02 42 41 2e 03 3b 0a 11 22 1e 38 64 51 16 1c
0000600 37 2e 1a 33 0b 07 05 7d 43 22 01 06 62 5d 3a 7c
0000610 47 2f 19 3b 6a 5f 3a 4c 41 21 61 19 02 5a 09 09
0000620 52 4f 5c 32 69 4b 0e 5c 57 0d 1a 2c 62 65 26 0c
0000630 67 6e 59 33 09 0d 6d 09 59 05 31 01 1d 11 19 01
0000640 13 31 0a 61 01 43 01 01 00 25 61 6b 6b 61 2f 68
0000650 74 74 70 2f 73 63 61 6c 61 64 73 6c 2f 48 74 74
0000660 70 24 53 65 72 76 65 72 42 69 6e 64 69 6e 67 07
0000670 00 0b 01 00 17 61 6b 6b 61 2f 68 74 74 70 2f 73
0000680 63 61 6c 61 64 73 6c 2f 48 74 74 70 07 00 0d 01
0000690 00 0d 53 65 72 76 65 72 42 69 6e 64 69 6e 67 01
00006a0 00 30 61 6b 6b 61 2f 68 74 74 70 2f 73 63 61 6c
00006b0 61 64 73 6c 2f 6d 6f 64 65 6c 2f 53 74 61 74 75
00006c0 73 43 6f 64 65 73 24 53 65 72 76 65 72 45 72 72
00006d0 6f 72 07 00 10 01 00 24 61 6b 6b 61 2f 68 74 74
00006e0 70 2f 73 63 61 6c 61 64 73 6c 2f 6d 6f 64 65 6c
00006f0 2f 53 74 61 74 75 73 43 6f 64 65 73 07 00 12 01
0000700 00 0b 53 65 72 76 65 72 45 72 72 6f 72 01 00 21
0000710 61 6b 6b 61 2f 68 74 74 70 2f 73 63 61 6c 61 64
0000720 73 6c 2f 6d 6f 64 65 6c 2f 55 72 69 24 50 61 74
0000730 68 07 00 15 01 00 1c 61 6b 6b 61 2f 68 74 74 70
0000740 2f 73 63 61 6c 61 64 73 6c 2f 6d 6f 64 65 6c 2f
0000750 55 72 69 07 00 17 01 00 04 50 61 74 68 01 00 35
0000760 61 6b 6b 61 2f 68 74 74 70 2f 73 63 61 6c 61 64
0000770 73 6c 2f 73 65 72 76 65 72 2f 50 61 74 68 4d 61
0000780 74 63 68 65 72 73 24 52 65 6d 61 69 6e 69 6e 67
0000790 50 61 74 68 24 07 00 1a 01 00 26 61 6b 6b 61 2f
00007a0 68 74 74 70 2f 73 63 61 6c 61 64 73 6c 2f 73 65
00007b0 72 76 65 72 2f 50 61 74 68 4d 61 74 63 68 65 72
00007c0 73 07 00 1c 01 00 0e 52 65 6d 61 69 6e 69 6e 67
00007d0 50 61 74 68 24 01 00 2f 61 6b 6b 61 2f 68 74 74
00007e0 70 2f 73 63 61 6c 61 64 73 6c 2f 73 65 72 76 65
00007f0 72 2f 50 61 74 68 4d 61 74 63 68 65 72 73 24 53
0000800 65 67 6d 65 6e 74 24 07 00 1f 01 00 08 53 65 67
0000810 6d 65 6e 74 24 01 00 43 61 6b 6b 61 2f 68 74 74
0000820 70 2f 73 63 61 6c 61 64 73 6c 2f 73 65 72 76 65
0000830 72 2f 52 6f 75 74 65 43 6f 6e 63 61 74 65 6e 61
0000840 74 69 6f 6e 24 52 6f 75 74 65 57 69 74 68 43 6f
0000850 6e 63 61 74 65 6e 61 74 69 6f 6e 07 00 22 01 00
0000860 2c 61 6b 6b 61 2f 68 74 74 70 2f 73 63 61 6c 61
0000870 64 73 6c 2f 73 65 72 76 65 72 2f 52 6f 75 74 65
0000880 43 6f 6e 63 61 74 65 6e 61 74 69 6f 6e 07 00 24
0000890 01 00 16 52 6f 75 74 65 57 69 74 68 43 6f 6e 63
00008a0 61 74 65 6e 61 74 69 6f 6e 01 00 20 69 6f 2f 66
00008b0 69 6e 64 69 66 79 2f 73 33 6d 6f 63 6b 2f 53 33
00008c0 4d 6f 63 6b 24 42 75 69 6c 64 65 72 07 00 27 01
00008d0 00 07 42 75 69 6c 64 65 72 01 00 25 6a 61 76 61
00008e0 2f 6c 61 6e 67 2f 69 6e 76 6f 6b 65 2f 4d 65 74
00008f0 68 6f 64 48 61 6e 64 6c 65 73 24 4c 6f 6f 6b 75
0000900 70 07 00 2a 01 00 1e 6a 61 76 61 2f 6c 61 6e 67
0000910 2f 69 6e 76 6f 6b 65 2f 4d 65 74 68 6f 64 48 61
0000920 6e 64 6c 65 73 07 00 2c 01 00 06 4c 6f 6f 6b 75
0000930 70 01 00 2b 73 63 61 6c 61 2f 63 6f 6e 63 75 72
0000940 72 65 6e 74 2f 64 75 72 61 74 69 6f 6e 2f 44 75
0000950 72 61 74 69 6f 6e 24 49 6e 66 69 6e 69 74 65 07
0000960 00 2f 01 00 22 73 63 61 6c 61 2f 63 6f 6e 63 75
0000970 72 72 65 6e 74 2f 64 75 72 61 74 69 6f 6e 2f 44
0000980 75 72 61 74 69 6f 6e 07 00 31 01 00 08 49 6e 66
0000990 69 6e 69 74 65 01 00 04 70 6f 72 74 01 00 01 49
00009a0 01 00 06 73 79 73 74 65 6d 01 00 18 4c 61 6b 6b
00009b0 61 2f 61 63 74 6f 72 2f 41 63 74 6f 72 53 79 73
00009c0 74 65 6d 3b 01 00 01 70 01 00 25 4c 69 6f 2f 66
00009d0 69 6e 64 69 66 79 2f 73 33 6d 6f 63 6b 2f 70 72
00009e0 6f 76 69 64 65 72 2f 50 72 6f 76 69 64 65 72 3b
00009f0 01 00 04 62 69 6e 64 01 00 27 4c 61 6b 6b 61 2f
0000a00 68 74 74 70 2f 73 63 61 6c 61 64 73 6c 2f 48 74
0000a10 74 70 24 53 65 72 76 65 72 42 69 6e 64 69 6e 67
0000a20 3b 01 00 06 6c 6f 67 67 65 72 01 00 22 4c 63 6f
0000a30 6d 2f 74 79 70 65 73 61 66 65 2f 73 63 61 6c 61
0000a40 6c 6f 67 67 69 6e 67 2f 4c 6f 67 67 65 72 3b 01
0000a50 00 08 62 69 74 6d 61 70 24 30 01 00 01 5a 01 00
0000a60 1b 24 6c 65 73 73 69 6e 69 74 24 67 72 65 61 74
0000a70 65 72 24 64 65 66 61 75 6c 74 24 33 01 00 40 28
0000a80 49 4c 69 6f 2f 66 69 6e 64 69 66 79 2f 73 33 6d
0000a90 6f 63 6b 2f 70 72 6f 76 69 64 65 72 2f 50 72 6f
0000aa0 76 69 64 65 72 3b 29 4c 61 6b 6b 61 2f 61 63 74
0000ab0 6f 72 2f 41 63 74 6f 72 53 79 73 74 65 6d 3b 01
0000ac0 00 19 69 6f 2f 66 69 6e 64 69 66 79 2f 73 33 6d
0000ad0 6f 63 6b 2f 53 33 4d 6f 63 6b 24 07 00 42 01 00
0000ae0 07 4d 4f 44 55 4c 45 24 01 00 1b 4c 69 6f 2f 66
0000af0 69 6e 64 69 66 79 2f 73 33 6d 6f 63 6b 2f 53 33
0000b00 4d 6f 63 6b 24 3b 0c 00 44 00 45 09 00 43 00 46
0000b10 0c 00 40 00 41 0a 00 43 00 48 01 00 06 63 72 65
0000b20 61 74 65 01 00 2f 28 49 4c 6a 61 76 61 2f 6c 61
0000b30 6e 67 2f 53 74 72 69 6e 67 3b 29 4c 69 6f 2f 66
0000b40 69 6e 64 69 66 79 2f 73 33 6d 6f 63 6b 2f 53 33
0000b50 4d 6f 63 6b 3b 0c 00 4a 00 4b 0a 00 43 00 4c 01
0000b60 00 1d 28 49 29 4c 69 6f 2f 66 69 6e 64 69 66 79
0000b70 2f 73 33 6d 6f 63 6b 2f 53 33 4d 6f 63 6b 3b 0c
0000b80 00 4a 00 4e 0a 00 43 00 4f 01 00 05 61 70 70 6c
0000b90 79 0c 00 51 00 4b 0a 00 43 00 52 0c 00 51 00 4e
0000ba0 0a 00 43 00 54 01 00 11 6c 6f 67 67 65 72 24 6c
0000bb0 7a 79 63 6f 6d 70 75 74 65 01 00 24 28 29 4c 63
0000bc0 6f 6d 2f 74 79 70 65 73 61 66 65 2f 73 63 61 6c
0000bd0 61 6c 6f 67 67 69 6e 67 2f 4c 6f 67 67 65 72 3b
0000be0 0c 00 3e 00 3f 09 00 02 00 58 01 00 07 6c 6f 67
0000bf0 67 65 72 24 01 00 4b 28 4c 63 6f 6d 2f 74 79 70
0000c00 65 73 61 66 65 2f 73 63 61 6c 61 6c 6f 67 67 69
0000c10 6e 67 2f 4c 61 7a 79 4c 6f 67 67 69 6e 67 3b 29
0000c20 4c 63 6f 6d 2f 74 79 70 65 73 61 66 65 2f 73 63
0000c30 61 6c 61 6c 6f 67 67 69 6e 67 2f 4c 6f 67 67 65
0000c40 72 3b 0c 00 5a 00 5b 0b 00 06 00 5c 0c 00 3c 00
0000c50 3d 09 00 02 00 5e 01 00 04 74 68 69 73 01 00 1a
0000c60 4c 69 6f 2f 66 69 6e 64 69 66 79 2f 73 33 6d 6f
0000c70 63 6b 2f 53 33 4d 6f 63 6b 3b 01 00 13 6a 61 76
0000c80 61 2f 6c 61 6e 67 2f 54 68 72 6f 77 61 62 6c 65
0000c90 07 00 62 0c 00 56 00 57 0a 00 02 00 64 01 00 20
0000ca0 63 6f 6d 2f 74 79 70 65 73 61 66 65 2f 73 63 61
0000cb0 6c 61 6c 6f 67 67 69 6e 67 2f 4c 6f 67 67 65 72
0000cc0 07 00 66 01 00 27 28 29 4c 69 6f 2f 66 69 6e 64
0000cd0 69 66 79 2f 73 33 6d 6f 63 6b 2f 70 72 6f 76 69
0000ce0 64 65 72 2f 50 72 6f 76 69 64 65 72 3b 0c 00 38
0000cf0 00 39 09 00 02 00 69 01 00 29 28 29 4c 61 6b 6b
0000d00 61 2f 68 74 74 70 2f 73 63 61 6c 61 64 73 6c 2f
0000d10 48 74 74 70 24 53 65 72 76 65 72 42 69 6e 64 69
0000d20 6e 67 3b 0c 00 3a 00 3b 09 00 02 00 6c 01 00 08
0000d30 62 69 6e 64 5f 24 65 71 01 00 2a 28 4c 61 6b 6b
0000d40 61 2f 68 74 74 70 2f 73 63 61 6c 61 64 73 6c 2f
0000d50 48 74 74 70 24 53 65 72 76 65 72 42 69 6e 64 69
0000d60 6e 67 3b 29 56 01 00 03 78 24 31 01 00 05 73 74
0000d70 61 72 74 01 00 1e 61 6b 6b 61 2f 73 74 72 65 61
0000d80 6d 2f 41 63 74 6f 72 4d 61 74 65 72 69 61 6c 69
0000d90 7a 65 72 24 07 00 72 01 00 20 4c 61 6b 6b 61 2f
0000da0 73 74 72 65 61 6d 2f 41 63 74 6f 72 4d 61 74 65
0000db0 72 69 61 6c 69 7a 65 72 24 3b 0c 00 44 00 74 09
0000dc0 00 73 00 75 01 00 0f 61 70 70 6c 79 24 64 65 66
0000dd0 61 75 6c 74 24 31 01 00 10 28 29 4c 73 63 61 6c
0000de0 61 2f 4f 70 74 69 6f 6e 3b 0c 00 77 00 78 0a 00
0000df0 73 00 79 01 00 0f 61 70 70 6c 79 24 64 65 66 61
0000e00 75 6c 74 24 32 0c 00 7b 00 78 0a 00 73 00 7c 0c
0000e10 00 36 00 37 09 00 02 00 7e 01 00 59 28 4c 73 63
0000e20 61 6c 61 2f 4f 70 74 69 6f 6e 3b 4c 73 63 61 6c
0000e30 61 2f 4f 70 74 69 6f 6e 3b 4c 61 6b 6b 61 2f 61
0000e40 63 74 6f 72 2f 41 63 74 6f 72 52 65 66 46 61 63
0000e50 74 6f 72 79 3b 29 4c 61 6b 6b 61 2f 73 74 72 65
0000e60 61 6d 2f 41 63 74 6f 72 4d 61 74 65 72 69 61 6c
0000e70 69 7a 65 72 3b 0c 00 51 00 80 0a 00 73 00 81 01
0000e80 00 18 61 6b 6b 61 2f 68 74 74 70 2f 73 63 61 6c
0000e90 61 64 73 6c 2f 48 74 74 70 24 07 00 83 01 00 1a
0000ea0 4c 61 6b 6b 61 2f 68 74 74 70 2f 73 63 61 6c 61
0000eb0 64 73 6c 2f 48 74 74 70 24 3b 0c 00 44 00 85 09
0000ec0 00 84 00 86 01 00 30 28 4c 61 6b 6b 61 2f 61 63
0000ed0 74 6f 72 2f 41 63 74 6f 72 53 79 73 74 65 6d 3b
0000ee0 29 4c 61 6b 6b 61 2f 61 63 74 6f 72 2f 45 78 74
0000ef0 65 6e 73 69 6f 6e 3b 0c 00 51 00 88 0a 00 84 00
0000f00 89 01 00 1a 61 6b 6b 61 2f 68 74 74 70 2f 73 63
0000f10 61 6c 61 64 73 6c 2f 48 74 74 70 45 78 74 07 00
0000f20 8b 01 00 25 61 6b 6b 61 2f 68 74 74 70 2f 73 63
0000f30 61 6c 61 64 73 6c 2f 73 65 72 76 65 72 2f 44 69
0000f40 72 65 63 74 69 76 65 73 24 07 00 8d 01 00 27 4c
0000f50 61 6b 6b 61 2f 68 74 74 70 2f 73 63 61 6c 61 64
0000f60 73 6c 2f 73 65 72 76 65 72 2f 44 69 72 65 63 74
0000f70 69 76 65 73 24 3b 0c 00 44 00 8f 09 00 8e 00 90
0000f80 01 00 24 61 6b 6b 61 2f 68 74 74 70 2f 73 63 61
0000f90 6c 61 64 73 6c 2f 73 65 72 76 65 72 2f 44 69 72
0000fa0 65 63 74 69 76 65 24 07 00 92 01 00 26 4c 61 6b
0000fb0 6b 61 2f 68 74 74 70 2f 73 63 61 6c 61 64 73 6c
0000fc0 2f 73 65 72 76 65 72 2f 44 69 72 65 63 74 69 76
0000fd0 65 24 3b 0c 00 44 00 94 09 00 93 00 95 01 00 07
0000fe0 53 65 67 6d 65 6e 74 01 00 33 28 29 4c 61 6b 6b
0000ff0 61 2f 68 74 74 70 2f 73 63 61 6c 61 64 73 6c 2f
0001000 73 65 72 76 65 72 2f 50 61 74 68 4d 61 74 63 68
0001010 65 72 73 24 53 65 67 6d 65 6e 74 24 3b 0c 00 97
0001020 00 98 0a 00 8e 00 99 01 00 0a 70 61 74 68 50 72
0001030 65 66 69 78 01 00 4e 28 4c 61 6b 6b 61 2f 68 74
0001040 74 70 2f 73 63 61 6c 61 64 73 6c 2f 73 65 72 76
0001050 65 72 2f 50 61 74 68 4d 61 74 63 68 65 72 3b 29
0001060 4c 61 6b 6b 61 2f 68 74 74 70 2f 73 63 61 6c 61
0001070 64 73 6c 2f 73 65 72 76 65 72 2f 44 69 72 65 63
0001080 74 69 76 65 3b 0c 00 9b 00 9c 0a 00 8e 00 9d 01
0001090 00 2e 61 6b 6b 61 2f 68 74 74 70 2f 73 63 61 6c
00010a0 61 64 73 6c 2f 73 65 72 76 65 72 2f 75 74 69 6c
00010b0 2f 41 70 70 6c 79 43 6f 6e 76 65 72 74 65 72 24
00010c0 07 00 9f 01 00 30 4c 61 6b 6b 61 2f 68 74 74 70
00010d0 2f 73 63 61 6c 61 64 73 6c 2f 73 65 72 76 65 72
00010e0 2f 75 74 69 6c 2f 41 70 70 6c 79 43 6f 6e 76 65
00010f0 72 74 65 72 24 3b 0c 00 44 00 a1 09 00 a0 00 a2
0001100 01 00 04 68 61 63 31 01 00 31 28 29 4c 61 6b 6b
0001110 61 2f 68 74 74 70 2f 73 63 61 6c 61 64 73 6c 2f
0001120 73 65 72 76 65 72 2f 75 74 69 6c 2f 41 70 70 6c
0001130 79 43 6f 6e 76 65 72 74 65 72 3b 0c 00 a4 00 a5
0001140 0a 00 a0 00 a6 01 00 11 61 64 64 44 69 72 65 63
0001150 74 69 76 65 41 70 70 6c 79 01 00 67 28 4c 61 6b
0001160 6b 61 2f 68 74 74 70 2f 73 63 61 6c 61 64 73 6c
0001170 2f 73 65 72 76 65 72 2f 44 69 72 65 63 74 69 76
0001180 65 3b 4c 61 6b 6b 61 2f 68 74 74 70 2f 73 63 61
0001190 6c 61 64 73 6c 2f 73 65 72 76 65 72 2f 75 74 69
00011a0 6c 2f 41 70 70 6c 79 43 6f 6e 76 65 72 74 65 72
00011b0 3b 29 4c 73 63 61 6c 61 2f 46 75 6e 63 74 69 6f
00011c0 6e 31 3b 0c 00 a8 00 a9 0a 00 93 00 aa 01 00 22
00011d0 6a 61 76 61 2f 6c 61 6e 67 2f 69 6e 76 6f 6b 65
00011e0 2f 4c 61 6d 62 64 61 4d 65 74 61 66 61 63 74 6f
00011f0 72 79 07 00 ac 01 00 0e 61 6c 74 4d 65 74 61 66
0001200 61 63 74 6f 72 79 01 00 86 28 4c 6a 61 76 61 2f
0001210 6c 61 6e 67 2f 69 6e 76 6f 6b 65 2f 4d 65 74 68
0001220 6f 64 48 61 6e 64 6c 65 73 24 4c 6f 6f 6b 75 70
0001230 3b 4c 6a 61 76 61 2f 6c 61 6e 67 2f 53 74 72 69
0001240 6e 67 3b 4c 6a 61 76 61 2f 6c 61 6e 67 2f 69 6e
0001250 76 6f 6b 65 2f 4d 65 74 68 6f 64 54 79 70 65 3b
0001260 5b 4c 6a 61 76 61 2f 6c 61 6e 67 2f 4f 62 6a 65
0001270 63 74 3b 29 4c 6a 61 76 61 2f 6c 61 6e 67 2f 69
0001280 6e 76 6f 6b 65 2f 43 61 6c 6c 53 69 74 65 3b 0c
0001290 00 ae 00 af 0a 00 ad 00 b0 0f 06 00 b1 01 00 26
00012a0 28 4c 6a 61 76 61 2f 6c 61 6e 67 2f 4f 62 6a 65
00012b0 63 74 3b 29 4c 6a 61 76 61 2f 6c 61 6e 67 2f 4f
00012c0 62 6a 65 63 74 3b 10 00 b3 01 00 10 24 61 6e 6f
00012d0 6e 66 75 6e 24 73 74 61 72 74 24 31 01 00 5e 28
00012e0 4c 69 6f 2f 66 69 6e 64 69 66 79 2f 73 33 6d 6f
00012f0 63 6b 2f 53 33 4d 6f 63 6b 3b 4c 61 6b 6b 61 2f
0001300 73 74 72 65 61 6d 2f 41 63 74 6f 72 4d 61 74 65
0001310 72 69 61 6c 69 7a 65 72 3b 4c 6a 61 76 61 2f 6c
0001320 61 6e 67 2f 53 74 72 69 6e 67 3b 29 4c 73 63 61
0001330 6c 61 2f 46 75 6e 63 74 69 6f 6e 31 3b 0c 00 b5
0001340 00 b6 0a 00 02 00 b7 0f 06 00 b8 01 00 25 28 4c
0001350 6a 61 76 61 2f 6c 61 6e 67 2f 53 74 72 69 6e 67
0001360 3b 29 4c 73 63 61 6c 61 2f 46 75 6e 63 74 69 6f
0001370 6e 31 3b 10 00 ba 03 00 00 00 03 03 00 00 00 01
0001380 01 00 12 73 63 61 6c 61 2f 53 65 72 69 61 6c 69
0001390 7a 61 62 6c 65 07 00 be 01 00 4c 28 4c 69 6f 2f
00013a0 66 69 6e 64 69 66 79 2f 73 33 6d 6f 63 6b 2f 53
00013b0 33 4d 6f 63 6b 3b 4c 61 6b 6b 61 2f 73 74 72 65
00013c0 61 6d 2f 41 63 74 6f 72 4d 61 74 65 72 69 61 6c
00013d0 69 7a 65 72 3b 29 4c 73 63 61 6c 61 2f 46 75 6e
00013e0 63 74 69 6f 6e 31 3b 0c 00 51 00 c0 12 00 00 00
00013f0 c1 01 00 0f 73 63 61 6c 61 2f 46 75 6e 63 74 69
0001400 6f 6e 31 07 00 c3 0c 00 51 00 b3 0b 00 c4 00 c5
0001410 01 00 1e 5f 65 6e 68 61 6e 63 65 52 6f 75 74 65
0001420 57 69 74 68 43 6f 6e 63 61 74 65 6e 61 74 69 6f
0001430 6e 01 00 58 28 4c 73 63 61 6c 61 2f 46 75 6e 63
0001440 74 69 6f 6e 31 3b 29 4c 61 6b 6b 61 2f 68 74 74
0001450 70 2f 73 63 61 6c 61 64 73 6c 2f 73 65 72 76 65
0001460 72 2f 52 6f 75 74 65 43 6f 6e 63 61 74 65 6e 61
0001470 74 69 6f 6e 24 52 6f 75 74 65 57 69 74 68 43 6f
0001480 6e 63 61 74 65 6e 61 74 69 6f 6e 3b 0c 00 c7 00
0001490 c8 0a 00 8e 00 c9 01 00 23 69 6f 2f 66 69 6e 64
00014a0 69 66 79 2f 73 33 6d 6f 63 6b 2f 72 6f 75 74 65
00014b0 2f 4c 69 73 74 42 75 63 6b 65 74 73 07 00 cb 0c
00014c0 00 38 00 68 0a 00 02 00 cd 01 00 06 3c 69 6e 69
00014d0 74 3e 01 00 28 28 4c 69 6f 2f 66 69 6e 64 69 66
00014e0 79 2f 73 33 6d 6f 63 6b 2f 70 72 6f 76 69 64 65
00014f0 72 2f 50 72 6f 76 69 64 65 72 3b 29 56 0c 00 cf
0001500 00 d0 0a 00 cc 00 d1 01 00 05 72 6f 75 74 65 01
0001510 00 13 28 29 4c 73 63 61 6c 61 2f 46 75 6e 63 74
0001520 69 6f 6e 31 3b 0c 00 d3 00 d4 0a 00 cc 00 d5 01
0001530 00 06 24 74 69 6c 64 65 01 00 24 28 4c 73 63 61
0001540 6c 61 2f 46 75 6e 63 74 69 6f 6e 31 3b 29 4c 73
0001550 63 61 6c 61 2f 46 75 6e 63 74 69 6f 6e 31 3b 0c
0001560 00 d7 00 d8 0a 00 23 00 d9 01 00 0e 65 78 74 72
0001570 61 63 74 52 65 71 75 65 73 74 01 00 27 28 29 4c
0001580 61 6b 6b 61 2f 68 74 74 70 2f 73 63 61 6c 61 64
0001590 73 6c 2f 73 65 72 76 65 72 2f 44 69 72 65 63 74
00015a0 69 76 65 3b 0c 00 db 00 dc 0a 00 8e 00 dd 01 00
00015b0 10 24 61 6e 6f 6e 66 75 6e 24 73 74 61 72 74 24
00015c0 36 01 00 6b 28 4c 69 6f 2f 66 69 6e 64 69 66 79
00015d0 2f 73 33 6d 6f 63 6b 2f 53 33 4d 6f 63 6b 3b 4c
00015e0 61 6b 6b 61 2f 68 74 74 70 2f 73 63 61 6c 61 64
00015f0 73 6c 2f 6d 6f 64 65 6c 2f 48 74 74 70 52 65 71
0001600 75 65 73 74 3b 29 4c 61 6b 6b 61 2f 68 74 74 70
0001610 2f 73 63 61 6c 61 64 73 6c 2f 73 65 72 76 65 72
0001620 2f 53 74 61 6e 64 61 72 64 52 6f 75 74 65 3b 0c
0001630 00 df 00 e0 0a 00 02 00 e1 0f 06 00 e2 01 00 51
0001640 28 4c 61 6b 6b 61 2f 68 74 74 70 2f 73 63 61 6c
0001650 61 64 73 6c 2f 6d 6f 64 65 6c 2f 48 74 74 70 52
0001660 65 71 75 65 73 74 3b 29 4c 61 6b 6b 61 2f 68 74
0001670 74 70 2f 73 63 61 6c 61 64 73 6c 2f 73 65 72 76
0001680 65 72 2f 53 74 61 6e 64 61 72 64 52 6f 75 74 65
0001690 3b 10 00 e4 01 00 2d 28 4c 69 6f 2f 66 69 6e 64
00016a0 69 66 79 2f 73 33 6d 6f 63 6b 2f 53 33 4d 6f 63
00016b0 6b 3b 29 4c 73 63 61 6c 61 2f 46 75 6e 63 74 69
00016c0 6f 6e 31 3b 0c 00 51 00 e6 12 00 01 00 e7 01 00
00016d0 17 73 63 61 6c 61 2f 63 6f 6e 63 75 72 72 65 6e
00016e0 74 2f 41 77 61 69 74 24 07 00 e9 01 00 19 4c 73
00016f0 63 61 6c 61 2f 63 6f 6e 63 75 72 72 65 6e 74 2f
0001700 41 77 61 69 74 24 3b 0c 00 44 00 eb 09 00 ea 00
0001710 ec 01 00 2c 61 6b 6b 61 2f 68 74 74 70 2f 73 63
0001720 61 6c 61 64 73 6c 2f 73 65 74 74 69 6e 67 73 2f
0001730 52 6f 75 74 69 6e 67 53 65 74 74 69 6e 67 73 24
0001740 07 00 ee 01 00 2e 4c 61 6b 6b 61 2f 68 74 74 70
0001750 2f 73 63 61 6c 61 64 73 6c 2f 73 65 74 74 69 6e
0001760 67 73 2f 52 6f 75 74 69 6e 67 53 65 74 74 69 6e
0001770 67 73 24 3b 0c 00 44 00 f0 09 00 ef 00 f1 01 00
0001780 07 64 65 66 61 75 6c 74 01 00 30 28 4c 61 6b 6b
0001790 61 2f 61 63 74 6f 72 2f 41 63 74 6f 72 52 65 66
00017a0 46 61 63 74 6f 72 79 3b 29 4c 6a 61 76 61 2f 6c
00017b0 61 6e 67 2f 4f 62 6a 65 63 74 3b 0c 00 f3 00 f4
00017c0 0a 00 ef 00 f5 01 00 2b 61 6b 6b 61 2f 68 74 74
00017d0 70 2f 73 63 61 6c 61 64 73 6c 2f 73 65 74 74 69
00017e0 6e 67 73 2f 52 6f 75 74 69 6e 67 53 65 74 74 69
00017f0 6e 67 73 07 00 f7 01 00 2b 61 6b 6b 61 2f 68 74
0001800 74 70 2f 73 63 61 6c 61 64 73 6c 2f 73 65 74 74
0001810 69 6e 67 73 2f 50 61 72 73 65 72 53 65 74 74 69
0001820 6e 67 73 24 07 00 f9 01 00 2d 4c 61 6b 6b 61 2f
0001830 68 74 74 70 2f 73 63 61 6c 61 64 73 6c 2f 73 65
0001840 74 74 69 6e 67 73 2f 50 61 72 73 65 72 53 65 74
0001850 74 69 6e 67 73 24 3b 0c 00 44 00 fb 09 00 fa 00
0001860 fc 0a 00 fa 00 f5 01 00 2a 61 6b 6b 61 2f 68 74
0001870 74 70 2f 73 63 61 6c 61 64 73 6c 2f 73 65 74 74
0001880 69 6e 67 73 2f 50 61 72 73 65 72 53 65 74 74 69
0001890 6e 67 73 07 00 ff 01 00 25 61 6b 6b 61 2f 68 74
00018a0 74 70 2f 73 63 61 6c 61 64 73 6c 2f 73 65 72 76
00018b0 65 72 2f 52 6f 75 74 69 6e 67 4c 6f 67 24 07 01
00018c0 01 01 00 27 4c 61 6b 6b 61 2f 68 74 74 70 2f 73
00018d0 63 61 6c 61 64 73 6c 2f 73 65 72 76 65 72 2f 52
00018e0 6f 75 74 69 6e 67 4c 6f 67 24 3b 0c 00 44 01 03
00018f0 09 01 02 01 04 01 00 0f 66 72 6f 6d 41 63 74 6f
0001900 72 53 79 73 74 65 6d 01 00 40 28 4c 61 6b 6b 61
0001910 2f 61 63 74 6f 72 2f 41 63 74 6f 72 53 79 73 74
0001920 65 6d 3b 29 4c 61 6b 6b 61 2f 68 74 74 70 2f 73
0001930 63 61 6c 61 64 73 6c 2f 73 65 72 76 65 72 2f 52
0001940 6f 75 74 69 6e 67 4c 6f 67 3b 0c 01 06 01 07 0a
0001950 01 02 01 08 01 00 26 61 6b 6b 61 2f 68 74 74 70
0001960 2f 73 63 61 6c 61 64 73 6c 2f 73 65 72 76 65 72
0001970 2f 52 6f 75 74 65 52 65 73 75 6c 74 24 07 01 0a
0001980 01 00 28 4c 61 6b 6b 61 2f 68 74 74 70 2f 73 63
0001990 61 6c 61 64 73 6c 2f 73 65 72 76 65 72 2f 52 6f
00019a0 75 74 65 52 65 73 75 6c 74 24 3b 0c 00 44 01 0c
00019b0 09 01 0b 01 0d 01 00 1b 72 6f 75 74 65 32 48 61
00019c0 6e 64 6c 65 72 46 6c 6f 77 24 64 65 66 61 75 6c
00019d0 74 24 36 01 00 36 28 4c 73 63 61 6c 61 2f 46 75
00019e0 6e 63 74 69 6f 6e 31 3b 29 4c 73 63 61 6c 61 2f
00019f0 63 6f 6e 63 75 72 72 65 6e 74 2f 45 78 65 63 75
0001a00 74 69 6f 6e 43 6f 6e 74 65 78 74 3b 0c 01 0f 01
0001a10 10 0a 01 0b 01 11 01 00 1b 72 6f 75 74 65 32 48
0001a20 61 6e 64 6c 65 72 46 6c 6f 77 24 64 65 66 61 75
0001a30 6c 74 24 37 01 00 3f 28 4c 73 63 61 6c 61 2f 46
0001a40 75 6e 63 74 69 6f 6e 31 3b 29 4c 61 6b 6b 61 2f
0001a50 68 74 74 70 2f 73 63 61 6c 61 64 73 6c 2f 73 65
0001a60 72 76 65 72 2f 52 65 6a 65 63 74 69 6f 6e 48 61
0001a70 6e 64 6c 65 72 3b 0c 01 13 01 14 0a 01 0b 01 15
0001a80 01 00 1b 72 6f 75 74 65 32 48 61 6e 64 6c 65 72
0001a90 46 6c 6f 77 24 64 65 66 61 75 6c 74 24 38 01 00
0001aa0 3f 28 4c 73 63 61 6c 61 2f 46 75 6e 63 74 69 6f
0001ab0 6e 31 3b 29 4c 61 6b 6b 61 2f 68 74 74 70 2f 73
0001ac0 63 61 6c 61 64 73 6c 2f 73 65 72 76 65 72 2f 45
0001ad0 78 63 65 70 74 69 6f 6e 48 61 6e 64 6c 65 72 3b
0001ae0 0c 01 17 01 18 0a 01 0b 01 19 01 00 11 72 6f 75
0001af0 74 65 32 48 61 6e 64 6c 65 72 46 6c 6f 77 01 01
0001b00 42 28 4c 73 63 61 6c 61 2f 46 75 6e 63 74 69 6f
0001b10 6e 31 3b 4c 61 6b 6b 61 2f 68 74 74 70 2f 73 63
0001b20 61 6c 61 64 73 6c 2f 73 65 74 74 69 6e 67 73 2f
0001b30 52 6f 75 74 69 6e 67 53 65 74 74 69 6e 67 73 3b
0001b40 4c 61 6b 6b 61 2f 68 74 74 70 2f 73 63 61 6c 61
0001b50 64 73 6c 2f 73 65 74 74 69 6e 67 73 2f 50 61 72
0001b60 73 65 72 53 65 74 74 69 6e 67 73 3b 4c 61 6b 6b
0001b70 61 2f 73 74 72 65 61 6d 2f 4d 61 74 65 72 69 61
0001b80 6c 69 7a 65 72 3b 4c 61 6b 6b 61 2f 68 74 74 70
0001b90 2f 73 63 61 6c 61 64 73 6c 2f 73 65 72 76 65 72
0001ba0 2f 52 6f 75 74 69 6e 67 4c 6f 67 3b 4c 73 63 61
0001bb0 6c 61 2f 63 6f 6e 63 75 72 72 65 6e 74 2f 45 78
0001bc0 65 63 75 74 69 6f 6e 43 6f 6e 74 65 78 74 3b 4c
0001bd0 61 6b 6b 61 2f 68 74 74 70 2f 73 63 61 6c 61 64
0001be0 73 6c 2f 73 65 72 76 65 72 2f 52 65 6a 65 63 74
0001bf0 69 6f 6e 48 61 6e 64 6c 65 72 3b 4c 61 6b 6b 61
0001c00 2f 68 74 74 70 2f 73 63 61 6c 61 64 73 6c 2f 73
0001c10 65 72 76 65 72 2f 45 78 63 65 70 74 69 6f 6e 48
0001c20 61 6e 64 6c 65 72 3b 29 4c 61 6b 6b 61 2f 73 74
0001c30 72 65 61 6d 2f 73 63 61 6c 61 64 73 6c 2f 46 6c
0001c40 6f 77 3b 0c 01 1b 01 1c 0a 01 0b 01 1d 01 00 09
0001c50 6c 6f 63 61 6c 68 6f 73 74 08 01 1f 0c 00 34 00
0001c60 35 09 00 02 01 21 01 00 17 62 69 6e 64 41 6e 64
0001c70 48 61 6e 64 6c 65 24 64 65 66 61 75 6c 74 24 34
0001c80 01 00 28 28 29 4c 61 6b 6b 61 2f 68 74 74 70 2f
0001c90 73 63 61 6c 61 64 73 6c 2f 43 6f 6e 6e 65 63 74
0001ca0 69 6f 6e 43 6f 6e 74 65 78 74 3b 0c 01 23 01 24
0001cb0 0a 00 8c 01 25 01 00 17 62 69 6e 64 41 6e 64 48
0001cc0 61 6e 64 6c 65 24 64 65 66 61 75 6c 74 24 35 01
0001cd0 00 2e 28 29 4c 61 6b 6b 61 2f 68 74 74 70 2f 73
0001ce0 63 61 6c 61 64 73 6c 2f 73 65 74 74 69 6e 67 73
0001cf0 2f 53 65 72 76 65 72 53 65 74 74 69 6e 67 73 3b
0001d00 0c 01 27 01 28 0a 00 8c 01 29 01 00 17 62 69 6e
0001d10 64 41 6e 64 48 61 6e 64 6c 65 24 64 65 66 61 75
0001d20 6c 74 24 36 01 00 1d 28 29 4c 61 6b 6b 61 2f 65
0001d30 76 65 6e 74 2f 4c 6f 67 67 69 6e 67 41 64 61 70
0001d40 74 65 72 3b 0c 01 2b 01 2c 0a 00 8c 01 2d 01 00
0001d50 0d 62 69 6e 64 41 6e 64 48 61 6e 64 6c 65 01 00
0001d60 d0 28 4c 61 6b 6b 61 2f 73 74 72 65 61 6d 2f 73
0001d70 63 61 6c 61 64 73 6c 2f 46 6c 6f 77 3b 4c 6a 61
0001d80 76 61 2f 6c 61 6e 67 2f 53 74 72 69 6e 67 3b 49
0001d90 4c 61 6b 6b 61 2f 68 74 74 70 2f 73 63 61 6c 61
0001da0 64 73 6c 2f 43 6f 6e 6e 65 63 74 69 6f 6e 43 6f
0001db0 6e 74 65 78 74 3b 4c 61 6b 6b 61 2f 68 74 74 70
0001dc0 2f 73 63 61 6c 61 64 73 6c 2f 73 65 74 74 69 6e
0001dd0 67 73 2f 53 65 72 76 65 72 53 65 74 74 69 6e 67
0001de0 73 3b 4c 61 6b 6b 61 2f 65 76 65 6e 74 2f 4c 6f
0001df0 67 67 69 6e 67 41 64 61 70 74 65 72 3b 4c 61 6b
0001e00 6b 61 2f 73 74 72 65 61 6d 2f 4d 61 74 65 72 69
0001e10 61 6c 69 7a 65 72 3b 29 4c 73 63 61 6c 61 2f 63
0001e20 6f 6e 63 75 72 72 65 6e 74 2f 46 75 74 75 72 65
0001e30 3b 0c 01 2f 01 30 0a 00 8c 01 31 01 00 23 73 63
0001e40 61 6c 61 2f 63 6f 6e 63 75 72 72 65 6e 74 2f 64
0001e50 75 72 61 74 69 6f 6e 2f 44 75 72 61 74 69 6f 6e
0001e60 24 07 01 33 01 00 25 4c 73 63 61 6c 61 2f 63 6f
0001e70 6e 63 75 72 72 65 6e 74 2f 64 75 72 61 74 69 6f
0001e80 6e 2f 44 75 72 61 74 69 6f 6e 24 3b 0c 00 44 01
0001e90 35 09 01 34 01 36 01 00 03 49 6e 66 01 00 2f 28
0001ea0 29 4c 73 63 61 6c 61 2f 63 6f 6e 63 75 72 72 65
0001eb0 6e 74 2f 64 75 72 61 74 69 6f 6e 2f 44 75 72 61
0001ec0 74 69 6f 6e 24 49 6e 66 69 6e 69 74 65 3b 0c 01
0001ed0 38 01 39 0a 01 34 01 3a 01 00 06 72 65 73 75 6c
0001ee0 74 01 00 54 28 4c 73 63 61 6c 61 2f 63 6f 6e 63
0001ef0 75 72 72 65 6e 74 2f 41 77 61 69 74 61 62 6c 65
0001f00 3b 4c 73 63 61 6c 61 2f 63 6f 6e 63 75 72 72 65
0001f10 6e 74 2f 64 75 72 61 74 69 6f 6e 2f 44 75 72 61
0001f20 74 69 6f 6e 3b 29 4c 6a 61 76 61 2f 6c 61 6e 67
0001f30 2f 4f 62 6a 65 63 74 3b 0c 01 3c 01 3d 0a 00 ea
0001f40 01 3e 0c 00 6e 00 6f 0a 00 02 01 40 0c 00 3a 00
0001f50 6b 0a 00 02 01 42 01 00 11 4c 73 63 61 6c 61 2f
0001f60 46 75 6e 63 74 69 6f 6e 31 3b 01 00 03 78 24 32
0001f70 01 00 2d 4c 61 6b 6b 61 2f 68 74 74 70 2f 73 63
0001f80 61 6c 61 64 73 6c 2f 73 65 74 74 69 6e 67 73 2f
0001f90 52 6f 75 74 69 6e 67 53 65 74 74 69 6e 67 73 3b
0001fa0 01 00 03 78 24 33 01 00 2c 4c 61 6b 6b 61 2f 68
0001fb0 74 74 70 2f 73 63 61 6c 61 64 73 6c 2f 73 65 74
0001fc0 74 69 6e 67 73 2f 50 61 72 73 65 72 53 65 74 74
0001fd0 69 6e 67 73 3b 01 00 03 78 24 34 01 00 1f 4c 61
0001fe0 6b 6b 61 2f 73 74 72 65 61 6d 2f 41 63 74 6f 72
0001ff0 4d 61 74 65 72 69 61 6c 69 7a 65 72 3b 01 00 03
0002000 78 24 35 01 00 26 4c 61 6b 6b 61 2f 68 74 74 70
0002010 2f 73 63 61 6c 61 64 73 6c 2f 73 65 72 76 65 72
0002020 2f 52 6f 75 74 69 6e 67 4c 6f 67 3b 01 00 03 78
0002030 24 36 01 00 23 4c 73 63 61 6c 61 2f 63 6f 6e 63
0002040 75 72 72 65 6e 74 2f 45 78 65 63 75 74 69 6f 6e
0002050 43 6f 6e 74 65 78 74 3b 01 00 03 78 24 37 01 00
0002060 2c 4c 61 6b 6b 61 2f 68 74 74 70 2f 73 63 61 6c
0002070 61 64 73 6c 2f 73 65 72 76 65 72 2f 52 65 6a 65
0002080 63 74 69 6f 6e 48 61 6e 64 6c 65 72 3b 01 00 03
0002090 78 24 38 01 00 2c 4c 61 6b 6b 61 2f 68 74 74 70
00020a0 2f 73 63 61 6c 61 64 73 6c 2f 73 65 72 76 65 72
00020b0 2f 45 78 63 65 70 74 69 6f 6e 48 61 6e 64 6c 65
00020c0 72 3b 01 00 03 6d 61 74 01 00 04 68 74 74 70 01
00020d0 00 1c 4c 61 6b 6b 61 2f 68 74 74 70 2f 73 63 61
00020e0 6c 61 64 73 6c 2f 48 74 74 70 45 78 74 3b 01 00
00020f0 04 73 74 6f 70 01 00 03 28 29 56 01 00 06 75 6e
0002100 62 69 6e 64 01 00 1b 28 29 4c 73 63 61 6c 61 2f
0002110 63 6f 6e 63 75 72 72 65 6e 74 2f 46 75 74 75 72
0002120 65 3b 0c 01 58 01 59 0a 00 0c 01 5a 01 00 10 24
0002130 61 6e 6f 6e 66 75 6e 24 73 74 61 72 74 24 32 01
0002140 00 3f 28 4c 69 6f 2f 66 69 6e 64 69 66 79 2f 73
0002150 33 6d 6f 63 6b 2f 53 33 4d 6f 63 6b 3b 4c 6a 61
0002160 76 61 2f 6c 61 6e 67 2f 53 74 72 69 6e 67 3b 29
0002170 4c 73 63 61 6c 61 2f 46 75 6e 63 74 69 6f 6e 31
0002180 3b 01 00 05 24 74 68 69 73 01 00 08 62 75 63 6b
0002190 65 74 24 31 01 00 0d 73 63 61 6c 61 2f 50 72 65
00021a0 64 65 66 24 07 01 60 01 00 0f 4c 73 63 61 6c 61
00021b0 2f 50 72 65 64 65 66 24 3b 0c 00 44 01 62 09 01
00021c0 61 01 63 01 00 22 69 6f 2f 66 69 6e 64 69 66 79
00021d0 2f 73 33 6d 6f 63 6b 2f 72 6f 75 74 65 2f 4c 69
00021e0 73 74 42 75 63 6b 65 74 07 01 65 0a 01 66 00 d1
00021f0 0c 00 d3 00 ba 0a 01 66 01 68 01 00 24 69 6f 2f
0002200 66 69 6e 64 69 66 79 2f 73 33 6d 6f 63 6b 2f 72
0002210 6f 75 74 65 2f 43 72 65 61 74 65 42 75 63 6b 65
0002220 74 07 01 6a 0a 01 6b 00 d1 0a 01 6b 01 68 01 00
0002230 24 69 6f 2f 66 69 6e 64 69 66 79 2f 73 33 6d 6f
0002240 63 6b 2f 72 6f 75 74 65 2f 44 65 6c 65 74 65 42
0002250 75 63 6b 65 74 07 01 6e 0a 01 6f 00 d1 0a 01 6f
0002260 01 68 01 00 25 69 6f 2f 66 69 6e 64 69 66 79 2f
0002270 73 33 6d 6f 63 6b 2f 72 6f 75 74 65 2f 44 65 6c
0002280 65 74 65 4f 62 6a 65 63 74 73 07 01 72 0a 01 73
0002290 00 d1 0a 01 73 01 68 01 00 13 5b 4c 6a 61 76 61
00022a0 2f 6c 61 6e 67 2f 4f 62 6a 65 63 74 3b 07 01 76
00022b0 01 00 0c 77 72 61 70 52 65 66 41 72 72 61 79 01
00022c0 00 3c 28 5b 4c 6a 61 76 61 2f 6c 61 6e 67 2f 4f
00022d0 62 6a 65 63 74 3b 29 4c 73 63 61 6c 61 2f 63 6f
00022e0 6c 6c 65 63 74 69 6f 6e 2f 6d 75 74 61 62 6c 65
00022f0 2f 57 72 61 70 70 65 64 41 72 72 61 79 3b 0c 01
0002300 78 01 79 0a 01 61 01 7a 01 00 06 63 6f 6e 63 61
0002310 74 01 00 29 28 4c 73 63 61 6c 61 2f 63 6f 6c 6c
0002320 65 63 74 69 6f 6e 2f 53 65 71 3b 29 4c 73 63 61
0002330 6c 61 2f 46 75 6e 63 74 69 6f 6e 31 3b 0c 01 7c
0002340 01 7d 0a 00 8e 01 7e 01 00 12 4c 6a 61 76 61 2f
0002350 6c 61 6e 67 2f 53 74 72 69 6e 67 3b 01 00 10 24
0002360 61 6e 6f 6e 66 75 6e 24 73 74 61 72 74 24 33 01
0002370 00 10 24 61 6e 6f 6e 66 75 6e 24 73 74 61 72 74
0002380 24 35 01 00 a1 28 4c 69 6f 2f 66 69 6e 64 69 66
0002390 79 2f 73 33 6d 6f 63 6b 2f 53 33 4d 6f 63 6b 3b
00023a0 4c 61 6b 6b 61 2f 73 74 72 65 61 6d 2f 41 63 74
00023b0 6f 72 4d 61 74 65 72 69 61 6c 69 7a 65 72 3b 4c
00023c0 6a 61 76 61 2f 6c 61 6e 67 2f 53 74 72 69 6e 67
00023d0 3b 4c 73 63 61 6c 61 2f 63 6f 6c 6c 65 63 74 69
00023e0 6f 6e 2f 69 6d 6d 75 74 61 62 6c 65 2f 4d 61 70
00023f0 3b 4c 61 6b 6b 61 2f 68 74 74 70 2f 73 63 61 6c
0002400 61 64 73 6c 2f 6d 6f 64 65 6c 2f 55 72 69 24 50
0002410 61 74 68 3b 29 4c 73 63 61 6c 61 2f 46 75 6e 63
0002420 74 69 6f 6e 31 3b 01 00 05 6d 61 74 24 31 01 00
0002430 08 70 61 72 61 6d 73 24 31 01 00 03 6b 65 79 01
0002440 00 21 69 6f 2f 66 69 6e 64 69 66 79 2f 73 33 6d
0002450 6f 63 6b 2f 72 6f 75 74 65 2f 47 65 74 4f 62 6a
0002460 65 63 74 07 01 87 0a 01 88 00 d1 01 00 08 74 6f
0002470 53 74 72 69 6e 67 01 00 14 28 29 4c 6a 61 76 61
0002480 2f 6c 61 6e 67 2f 53 74 72 69 6e 67 3b 0c 01 8a
0002490 01 8b 0a 00 16 01 8c 01 00 57 28 4c 6a 61 76 61
00024a0 2f 6c 61 6e 67 2f 53 74 72 69 6e 67 3b 4c 6a 61
00024b0 76 61 2f 6c 61 6e 67 2f 53 74 72 69 6e 67 3b 4c
00024c0 73 63 61 6c 61 2f 63 6f 6c 6c 65 63 74 69 6f 6e
00024d0 2f 69 6d 6d 75 74 61 62 6c 65 2f 4d 61 70 3b 29
00024e0 4c 73 63 61 6c 61 2f 46 75 6e 63 74 69 6f 6e 31
00024f0 3b 0c 00 d3 01 8e 0a 01 88 01 8f 01 00 22 69 6f
0002500 2f 66 69 6e 64 69 66 79 2f 73 33 6d 6f 63 6b 2f
0002510 72 6f 75 74 65 2f 43 6f 70 79 4f 62 6a 65 63 74
0002520 07 01 91 0a 01 92 00 d1 01 00 37 28 4c 6a 61 76
0002530 61 2f 6c 61 6e 67 2f 53 74 72 69 6e 67 3b 4c 6a
0002540 61 76 61 2f 6c 61 6e 67 2f 53 74 72 69 6e 67 3b
0002550 29 4c 73 63 61 6c 61 2f 46 75 6e 63 74 69 6f 6e
0002560 31 3b 0c 00 d3 01 94 0a 01 92 01 95 01 00 2a 69
0002570 6f 2f 66 69 6e 64 69 66 79 2f 73 33 6d 6f 63 6b
0002580 2f 72 6f 75 74 65 2f 50 75 74 4f 62 6a 65 63 74
0002590 4d 75 6c 74 69 70 61 72 74 07 01 97 01 00 42 28
00025a0 4c 69 6f 2f 66 69 6e 64 69 66 79 2f 73 33 6d 6f
00025b0 63 6b 2f 70 72 6f 76 69 64 65 72 2f 50 72 6f 76
00025c0 69 64 65 72 3b 4c 61 6b 6b 61 2f 73 74 72 65 61
00025d0 6d 2f 4d 61 74 65 72 69 61 6c 69 7a 65 72 3b 29
00025e0 56 0c 00 cf 01 99 0a 01 98 01 9a 0a 01 98 01 95
00025f0 01 00 2f 69 6f 2f 66 69 6e 64 69 66 79 2f 73 33
0002600 6d 6f 63 6b 2f 72 6f 75 74 65 2f 50 75 74 4f 62
0002610 6a 65 63 74 4d 75 6c 74 69 70 61 72 74 53 74 61
0002620 72 74 07 01 9d 0a 01 9e 00 d1 0a 01 9e 01 95 01
0002630 00 32 69 6f 2f 66 69 6e 64 69 66 79 2f 73 33 6d
0002640 6f 63 6b 2f 72 6f 75 74 65 2f 50 75 74 4f 62 6a
0002650 65 63 74 4d 75 6c 74 69 70 61 72 74 43 6f 6d 70
0002660 6c 65 74 65 07 01 a1 0a 01 a2 00 d1 0a 01 a2 01
0002670 95 01 00 21 69 6f 2f 66 69 6e 64 69 66 79 2f 73
0002680 33 6d 6f 63 6b 2f 72 6f 75 74 65 2f 50 75 74 4f
0002690 62 6a 65 63 74 07 01 a5 0a 01 a6 01 9a 0a 01 a6
00026a0 01 95 01 00 24 69 6f 2f 66 69 6e 64 69 66 79 2f
00026b0 73 33 6d 6f 63 6b 2f 72 6f 75 74 65 2f 44 65 6c
00026c0 65 74 65 4f 62 6a 65 63 74 07 01 a9 0a 01 aa 00
00026d0 d1 0a 01 aa 01 95 01 00 20 4c 73 63 61 6c 61 2f
00026e0 63 6f 6c 6c 65 63 74 69 6f 6e 2f 69 6d 6d 75 74
00026f0 61 62 6c 65 2f 4d 61 70 3b 01 00 23 4c 61 6b 6b
0002700 61 2f 68 74 74 70 2f 73 63 61 6c 61 64 73 6c 2f
0002710 6d 6f 64 65 6c 2f 55 72 69 24 50 61 74 68 3b 01
0002720 00 10 24 61 6e 6f 6e 66 75 6e 24 73 74 61 72 74
0002730 24 34 01 00 7e 28 4c 69 6f 2f 66 69 6e 64 69 66
0002740 79 2f 73 33 6d 6f 63 6b 2f 53 33 4d 6f 63 6b 3b
0002750 4c 61 6b 6b 61 2f 73 74 72 65 61 6d 2f 41 63 74
0002760 6f 72 4d 61 74 65 72 69 61 6c 69 7a 65 72 3b 4c
0002770 6a 61 76 61 2f 6c 61 6e 67 2f 53 74 72 69 6e 67
0002780 3b 4c 73 63 61 6c 61 2f 63 6f 6c 6c 65 63 74 69
0002790 6f 6e 2f 69 6d 6d 75 74 61 62 6c 65 2f 4d 61 70
00027a0 3b 29 4c 73 63 61 6c 61 2f 46 75 6e 63 74 69 6f
00027b0 6e 31 3b 01 00 06 70 61 72 61 6d 73 01 00 0d 52
00027c0 65 6d 61 69 6e 69 6e 67 50 61 74 68 01 00 39 28
00027d0 29 4c 61 6b 6b 61 2f 68 74 74 70 2f 73 63 61 6c
00027e0 61 64 73 6c 2f 73 65 72 76 65 72 2f 50 61 74 68
00027f0 4d 61 74 63 68 65 72 73 24 52 65 6d 61 69 6e 69
0002800 6e 67 50 61 74 68 24 3b 0c 01 b2 01 b3 0a 00 8e
0002810 01 b4 01 00 04 70 61 74 68 0c 01 b6 00 9c 0a 00
0002820 8e 01 b7 0c 01 82 01 83 0a 00 02 01 b9 0f 06 01
0002830 ba 01 00 36 28 4c 61 6b 6b 61 2f 68 74 74 70 2f
0002840 73 63 61 6c 61 64 73 6c 2f 6d 6f 64 65 6c 2f 55
0002850 72 69 24 50 61 74 68 3b 29 4c 73 63 61 6c 61 2f
0002860 46 75 6e 63 74 69 6f 6e 31 3b 10 01 bc 0c 00 51
0002870 01 b0 12 00 02 01 be 01 00 06 62 75 63 6b 65 74
0002880 01 00 0f 70 61 74 68 53 69 6e 67 6c 65 53 6c 61
0002890 73 68 0c 01 c1 00 dc 0a 00 8e 01 c2 01 00 15 61
00028a0 64 64 42 79 4e 61 6d 65 4e 75 6c 6c 61 72 79 41
00028b0 70 70 6c 79 01 00 38 28 4c 61 6b 6b 61 2f 68 74
00028c0 74 70 2f 73 63 61 6c 61 64 73 6c 2f 73 65 72 76
00028d0 65 72 2f 44 69 72 65 63 74 69 76 65 3b 29 4c 73
00028e0 63 61 6c 61 2f 46 75 6e 63 74 69 6f 6e 31 3b 0c
00028f0 01 c4 01 c5 0a 00 93 01 c6 01 00 14 28 29 4c 6a
0002900 61 76 61 2f 6c 61 6e 67 2f 4f 62 6a 65 63 74 3b
0002910 10 01 c8 0c 01 5c 01 5d 0a 00 02 01 ca 0f 06 01
0002920 cb 10 00 d4 01 00 3f 28 4c 69 6f 2f 66 69 6e 64
0002930 69 66 79 2f 73 33 6d 6f 63 6b 2f 53 33 4d 6f 63
0002940 6b 3b 4c 6a 61 76 61 2f 6c 61 6e 67 2f 53 74 72
0002950 69 6e 67 3b 29 4c 73 63 61 6c 61 2f 46 75 6e 63
0002960 74 69 6f 6e 30 3b 0c 00 51 01 ce 12 00 03 01 cf
0002970 01 00 07 70 61 74 68 45 6e 64 0c 01 d1 00 dc 0a
0002980 00 8e 01 d2 0c 01 81 01 5d 0a 00 02 01 d4 0f 06
0002990 01 d5 12 00 04 01 cf 01 00 0c 70 61 72 61 6d 65
00029a0 74 65 72 4d 61 70 0c 01 d8 00 dc 0a 00 8e 01 d9
00029b0 0c 01 af 01 b0 0a 00 02 01 db 0f 06 01 dc 01 00
00029c0 33 28 4c 73 63 61 6c 61 2f 63 6f 6c 6c 65 63 74
00029d0 69 6f 6e 2f 69 6d 6d 75 74 61 62 6c 65 2f 4d 61
00029e0 70 3b 29 4c 73 63 61 6c 61 2f 46 75 6e 63 74 69
00029f0 6f 6e 31 3b 10 01 de 0c 00 51 00 b6 12 00 05 01
0002a00 e0 01 00 10 24 61 6e 6f 6e 66 75 6e 24 73 74 61
0002a10 72 74 24 37 01 00 79 28 4c 69 6f 2f 66 69 6e 64
0002a20 69 66 79 2f 73 33 6d 6f 63 6b 2f 53 33 4d 6f 63
0002a30 6b 3b 4c 61 6b 6b 61 2f 68 74 74 70 2f 73 63 61
0002a40 6c 61 64 73 6c 2f 6d 6f 64 65 6c 2f 48 74 74 70
0002a50 52 65 71 75 65 73 74 3b 29 4c 61 6b 6b 61 2f 68
0002a60 74 74 70 2f 73 63 61 6c 61 64 73 6c 2f 6d 61 72
0002a70 73 68 61 6c 6c 69 6e 67 2f 54 6f 52 65 73 70 6f
0002a80 6e 73 65 4d 61 72 73 68 61 6c 6c 61 62 6c 65 3b
0002a90 01 00 09 72 65 71 75 65 73 74 24 31 0c 00 3c 00
0002aa0 57 0a 00 02 01 e5 01 00 0a 75 6e 64 65 72 6c 79
0002ab0 69 6e 67 01 00 14 28 29 4c 6f 72 67 2f 73 6c 66
0002ac0 34 6a 2f 4c 6f 67 67 65 72 3b 0c 01 e7 01 e8 0a
0002ad0 00 67 01 e9 01 00 10 6f 72 67 2f 73 6c 66 34 6a
0002ae0 2f 4c 6f 67 67 65 72 07 01 eb 01 00 0e 69 73 45
0002af0 72 72 6f 72 45 6e 61 62 6c 65 64 01 00 03 28 29
0002b00 5a 0c 01 ed 01 ee 0b 01 ec 01 ef 01 00 13 73 63
0002b10 61 6c 61 2f 53 74 72 69 6e 67 43 6f 6e 74 65 78
0002b20 74 07 01 f1 01 00 10 6a 61 76 61 2f 6c 61 6e 67
0002b30 2f 53 74 72 69 6e 67 07 01 f3 01 00 18 6d 65 74
0002b40 68 6f 64 20 6e 6f 74 20 69 6d 70 6c 65 6d 65 6e
0002b50 74 65 64 3a 20 08 01 f5 01 00 01 20 08 01 f7 01
0002b60 00 00 08 01 f9 01 00 19 28 4c 73 63 61 6c 61 2f
0002b70 63 6f 6c 6c 65 63 74 69 6f 6e 2f 53 65 71 3b 29
0002b80 56 0c 00 cf 01 fb 0a 01 f2 01 fc 01 00 24 61 6b
0002b90 6b 61 2f 68 74 74 70 2f 73 63 61 6c 61 64 73 6c
0002ba0 2f 6d 6f 64 65 6c 2f 48 74 74 70 52 65 71 75 65
0002bb0 73 74 07 01 fe 01 00 06 6d 65 74 68 6f 64 01 00
0002bc0 27 28 29 4c 61 6b 6b 61 2f 68 74 74 70 2f 73 63
0002bd0 61 6c 61 64 73 6c 2f 6d 6f 64 65 6c 2f 48 74 74
0002be0 70 4d 65 74 68 6f 64 3b 0c 02 00 02 01 0a 01 ff
0002bf0 02 02 01 00 23 61 6b 6b 61 2f 68 74 74 70 2f 73
0002c00 63 61 6c 61 64 73 6c 2f 6d 6f 64 65 6c 2f 48 74
0002c10 74 70 4d 65 74 68 6f 64 07 02 04 01 00 05 76 61
0002c20 6c 75 65 0c 02 06 01 8b 0a 02 05 02 07 01 00 03
0002c30 75 72 69 01 00 20 28 29 4c 61 6b 6b 61 2f 68 74
0002c40 74 70 2f 73 63 61 6c 61 64 73 6c 2f 6d 6f 64 65
0002c50 6c 2f 55 72 69 3b 0c 02 09 02 0a 0a 01 ff 02 0b
0002c60 0a 00 18 01 8c 01 00 10 67 65 6e 65 72 69 63 57
0002c70 72 61 70 41 72 72 61 79 01 00 3b 28 4c 6a 61 76
0002c80 61 2f 6c 61 6e 67 2f 4f 62 6a 65 63 74 3b 29 4c
0002c90 73 63 61 6c 61 2f 63 6f 6c 6c 65 63 74 69 6f 6e
0002ca0 2f 6d 75 74 61 62 6c 65 2f 57 72 61 70 70 65 64
0002cb0 41 72 72 61 79 3b 0c 02 0e 02 0f 0a 01 61 02 10
0002cc0 01 00 01 73 01 00 2a 28 4c 73 63 61 6c 61 2f 63
0002cd0 6f 6c 6c 65 63 74 69 6f 6e 2f 53 65 71 3b 29 4c
0002ce0 6a 61 76 61 2f 6c 61 6e 67 2f 53 74 72 69 6e 67
0002cf0 3b 0c 02 12 02 13 0a 01 f2 02 14 01 00 05 65 72
0002d00 72 6f 72 01 00 15 28 4c 6a 61 76 61 2f 6c 61 6e
0002d10 67 2f 53 74 72 69 6e 67 3b 29 56 0c 02 16 02 17
0002d20 0b 01 ec 02 18 01 00 17 73 63 61 6c 61 2f 72 75
0002d30 6e 74 69 6d 65 2f 42 6f 78 65 64 55 6e 69 74 07
0002d40 02 1a 01 00 04 55 4e 49 54 01 00 19 4c 73 63 61
0002d50 6c 61 2f 72 75 6e 74 69 6d 65 2f 42 6f 78 65 64
0002d60 55 6e 69 74 3b 0c 02 1c 02 1d 09 02 1b 02 1e 01
0002d70 00 36 61 6b 6b 61 2f 68 74 74 70 2f 73 63 61 6c
0002d80 61 64 73 6c 2f 6d 61 72 73 68 61 6c 6c 69 6e 67
0002d90 2f 54 6f 52 65 73 70 6f 6e 73 65 4d 61 72 73 68
0002da0 61 6c 6c 61 62 6c 65 24 07 02 20 01 00 38 4c 61
0002db0 6b 6b 61 2f 68 74 74 70 2f 73 63 61 6c 61 64 73
0002dc0 6c 2f 6d 61 72 73 68 61 6c 6c 69 6e 67 2f 54 6f
0002dd0 52 65 73 70 6f 6e 73 65 4d 61 72 73 68 61 6c 6c
0002de0 61 62 6c 65 24 3b 0c 00 44 02 22 09 02 21 02 23
0002df0 01 00 26 61 6b 6b 61 2f 68 74 74 70 2f 73 63 61
0002e00 6c 61 64 73 6c 2f 6d 6f 64 65 6c 2f 48 74 74 70
0002e10 52 65 73 70 6f 6e 73 65 24 07 02 25 01 00 28 4c
0002e20 61 6b 6b 61 2f 68 74 74 70 2f 73 63 61 6c 61 64
0002e30 73 6c 2f 6d 6f 64 65 6c 2f 48 74 74 70 52 65 73
0002e40 70 6f 6e 73 65 24 3b 0c 00 44 02 27 09 02 26 02
0002e50 28 01 00 25 61 6b 6b 61 2f 68 74 74 70 2f 73 63
0002e60 61 6c 61 64 73 6c 2f 6d 6f 64 65 6c 2f 53 74 61
0002e70 74 75 73 43 6f 64 65 73 24 07 02 2a 01 00 27 4c
0002e80 61 6b 6b 61 2f 68 74 74 70 2f 73 63 61 6c 61 64
0002e90 73 6c 2f 6d 6f 64 65 6c 2f 53 74 61 74 75 73 43
0002ea0 6f 64 65 73 24 3b 0c 00 44 02 2c 09 02 2b 02 2d
0002eb0 01 00 0e 4e 6f 74 49 6d 70 6c 65 6d 65 6e 74 65
0002ec0 64 01 00 34 28 29 4c 61 6b 6b 61 2f 68 74 74 70
0002ed0 2f 73 63 61 6c 61 64 73 6c 2f 6d 6f 64 65 6c 2f
0002ee0 53 74 61 74 75 73 43 6f 64 65 73 24 53 65 72 76
0002ef0 65 72 45 72 72 6f 72 3b 0c 02 2f 02 30 0a 02 2b
0002f00 02 31 01 00 22 28 29 4c 73 63 61 6c 61 2f 63 6f
0002f10 6c 6c 65 63 74 69 6f 6e 2f 69 6d 6d 75 74 61 62
0002f20 6c 65 2f 53 65 71 3b 0c 00 7b 02 33 0a 02 26 02
0002f30 34 01 00 0f 61 70 70 6c 79 24 64 65 66 61 75 6c
0002f40 74 24 33 01 00 2b 28 29 4c 61 6b 6b 61 2f 68 74
0002f50 74 70 2f 73 63 61 6c 61 64 73 6c 2f 6d 6f 64 65
0002f60 6c 2f 52 65 73 70 6f 6e 73 65 45 6e 74 69 74 79
0002f70 3b 0c 02 36 02 37 0a 02 26 02 38 01 00 0f 61 70
0002f80 70 6c 79 24 64 65 66 61 75 6c 74 24 34 01 00 29
0002f90 28 29 4c 61 6b 6b 61 2f 68 74 74 70 2f 73 63 61
0002fa0 6c 61 64 73 6c 2f 6d 6f 64 65 6c 2f 48 74 74 70
0002fb0 50 72 6f 74 6f 63 6f 6c 3b 0c 02 3a 02 3b 0a 02
0002fc0 26 02 3c 01 00 be 28 4c 61 6b 6b 61 2f 68 74 74
0002fd0 70 2f 73 63 61 6c 61 64 73 6c 2f 6d 6f 64 65 6c
0002fe0 2f 53 74 61 74 75 73 43 6f 64 65 3b 4c 73 63 61
0002ff0 6c 61 2f 63 6f 6c 6c 65 63 74 69 6f 6e 2f 69 6d
0003000 6d 75 74 61 62 6c 65 2f 53 65 71 3b 4c 61 6b 6b
0003010 61 2f 68 74 74 70 2f 73 63 61 6c 61 64 73 6c 2f
0003020 6d 6f 64 65 6c 2f 52 65 73 70 6f 6e 73 65 45 6e
0003030 74 69 74 79 3b 4c 61 6b 6b 61 2f 68 74 74 70 2f
0003040 73 63 61 6c 61 64 73 6c 2f 6d 6f 64 65 6c 2f 48
0003050 74 74 70 50 72 6f 74 6f 63 6f 6c 3b 29 4c 61 6b
0003060 6b 61 2f 68 74 74 70 2f 73 63 61 6c 61 64 73 6c
0003070 2f 6d 6f 64 65 6c 2f 48 74 74 70 52 65 73 70 6f
0003080 6e 73 65 3b 0c 00 51 02 3e 0a 02 26 02 3f 01 00
0003090 2a 61 6b 6b 61 2f 68 74 74 70 2f 73 63 61 6c 61
00030a0 64 73 6c 2f 6d 61 72 73 68 61 6c 6c 69 6e 67 2f
00030b0 4d 61 72 73 68 61 6c 6c 65 72 24 07 02 41 01 00
00030c0 2c 4c 61 6b 6b 61 2f 68 74 74 70 2f 73 63 61 6c
00030d0 61 64 73 6c 2f 6d 61 72 73 68 61 6c 6c 69 6e 67
00030e0 2f 4d 61 72 73 68 61 6c 6c 65 72 24 3b 0c 00 44
00030f0 02 43 09 02 42 02 44 01 00 0c 66 72 6f 6d 52 65
0003100 73 70 6f 6e 73 65 01 00 2d 28 29 4c 61 6b 6b 61
0003110 2f 68 74 74 70 2f 73 63 61 6c 61 64 73 6c 2f 6d
0003120 61 72 73 68 61 6c 6c 69 6e 67 2f 4d 61 72 73 68
0003130 61 6c 6c 65 72 3b 0c 02 46 02 47 0a 02 42 02 48
0003140 01 00 76 28 4c 6a 61 76 61 2f 6c 61 6e 67 2f 4f
0003150 62 6a 65 63 74 3b 4c 61 6b 6b 61 2f 68 74 74 70
0003160 2f 73 63 61 6c 61 64 73 6c 2f 6d 61 72 73 68 61
0003170 6c 6c 69 6e 67 2f 4d 61 72 73 68 61 6c 6c 65 72
0003180 3b 29 4c 61 6b 6b 61 2f 68 74 74 70 2f 73 63 61
0003190 6c 61 64 73 6c 2f 6d 61 72 73 68 61 6c 6c 69 6e
00031a0 67 2f 54 6f 52 65 73 70 6f 6e 73 65 4d 61 72 73
00031b0 68 61 6c 6c 61 62 6c 65 3b 0c 00 51 02 4a 0a 02
00031c0 21 02 4b 01 00 26 4c 61 6b 6b 61 2f 68 74 74 70
00031d0 2f 73 63 61 6c 61 64 73 6c 2f 6d 6f 64 65 6c 2f
00031e0 48 74 74 70 52 65 71 75 65 73 74 3b 01 00 07 72
00031f0 65 71 75 65 73 74 0c 01 e2 01 e3 0a 00 02 02 4f
0003200 0f 06 02 50 01 00 39 28 29 4c 61 6b 6b 61 2f 68
0003210 74 74 70 2f 73 63 61 6c 61 64 73 6c 2f 6d 61 72
0003220 73 68 61 6c 6c 69 6e 67 2f 54 6f 52 65 73 70 6f
0003230 6e 73 65 4d 61 72 73 68 61 6c 6c 61 62 6c 65 3b
0003240 10 02 52 01 00 53 28 4c 69 6f 2f 66 69 6e 64 69
0003250 66 79 2f 73 33 6d 6f 63 6b 2f 53 33 4d 6f 63 6b
0003260 3b 4c 61 6b 6b 61 2f 68 74 74 70 2f 73 63 61 6c
0003270 61 64 73 6c 2f 6d 6f 64 65 6c 2f 48 74 74 70 52
0003280 65 71 75 65 73 74 3b 29 4c 73 63 61 6c 61 2f 46
0003290 75 6e 63 74 69 6f 6e 30 3b 0c 00 51 02 54 12 00
00032a0 06 02 55 01 00 08 63 6f 6d 70 6c 65 74 65 01 00
00032b0 3c 28 4c 73 63 61 6c 61 2f 46 75 6e 63 74 69 6f
00032c0 6e 30 3b 29 4c 61 6b 6b 61 2f 68 74 74 70 2f 73
00032d0 63 61 6c 61 64 73 6c 2f 73 65 72 76 65 72 2f 53
00032e0 74 61 6e 64 61 72 64 52 6f 75 74 65 3b 0c 02 57
00032f0 02 58 0a 00 8e 02 59 01 00 41 28 49 4c 69 6f 2f
0003300 66 69 6e 64 69 66 79 2f 73 33 6d 6f 63 6b 2f 70
0003310 72 6f 76 69 64 65 72 2f 50 72 6f 76 69 64 65 72
0003320 3b 4c 61 6b 6b 61 2f 61 63 74 6f 72 2f 41 63 74
0003330 6f 72 53 79 73 74 65 6d 3b 29 56 01 00 08 70 72
0003340 6f 76 69 64 65 72 0c 00 cf 01 57 0a 00 04 02 5d
0003350 01 00 06 24 69 6e 69 74 24 01 00 2a 28 4c 63 6f
0003360 6d 2f 74 79 70 65 73 61 66 65 2f 73 63 61 6c 61
0003370 6c 6f 67 67 69 6e 67 2f 4c 61 7a 79 4c 6f 67 67
0003380 69 6e 67 3b 29 56 0c 02 5f 02 60 0b 00 06 02 61
0003390 01 00 13 24 64 65 73 65 72 69 61 6c 69 7a 65 4c
00033a0 61 6d 62 64 61 24 01 00 37 28 4c 6a 61 76 61 2f
00033b0 6c 61 6e 67 2f 69 6e 76 6f 6b 65 2f 53 65 72 69
00033c0 61 6c 69 7a 65 64 4c 61 6d 62 64 61 3b 29 4c 6a
00033d0 61 76 61 2f 6c 61 6e 67 2f 4f 62 6a 65 63 74 3b
00033e0 01 00 1f 73 63 61 6c 61 2f 72 75 6e 74 69 6d 65
00033f0 2f 4c 61 6d 62 64 61 44 65 73 65 72 69 61 6c 69
0003400 7a 65 07 02 65 01 00 09 62 6f 6f 74 73 74 72 61
0003410 70 01 00 93 28 4c 6a 61 76 61 2f 6c 61 6e 67 2f
0003420 69 6e 76 6f 6b 65 2f 4d 65 74 68 6f 64 48 61 6e
0003430 64 6c 65 73 24 4c 6f 6f 6b 75 70 3b 4c 6a 61 76
0003440 61 2f 6c 61 6e 67 2f 53 74 72 69 6e 67 3b 4c 6a
0003450 61 76 61 2f 6c 61 6e 67 2f 69 6e 76 6f 6b 65 2f
0003460 4d 65 74 68 6f 64 54 79 70 65 3b 5b 4c 6a 61 76
0003470 61 2f 6c 61 6e 67 2f 69 6e 76 6f 6b 65 2f 4d 65
0003480 74 68 6f 64 48 61 6e 64 6c 65 3b 29 4c 6a 61 76
0003490 61 2f 6c 61 6e 67 2f 69 6e 76 6f 6b 65 2f 43 61
00034a0 6c 6c 53 69 74 65 3b 0c 02 67 02 68 0a 02 66 02
00034b0 69 0f 06 02 6a 01 00 11 6c 61 6d 62 64 61 44 65
00034c0 73 65 72 69 61 6c 69 7a 65 0c 02 6c 02 64 12 00
00034d0 07 02 6d 01 00 04 43 6f 64 65 01 00 12 4c 6f 63
00034e0 61 6c 56 61 72 69 61 62 6c 65 54 61 62 6c 65 01
00034f0 00 0f 4c 69 6e 65 4e 75 6d 62 65 72 54 61 62 6c
0003500 65 01 00 0d 53 74 61 63 6b 4d 61 70 54 61 62 6c
0003510 65 01 00 10 4d 65 74 68 6f 64 50 61 72 61 6d 65
0003520 74 65 72 73 01 00 10 42 6f 6f 74 73 74 72 61 70
0003530 4d 65 74 68 6f 64 73 01 00 0a 53 6f 75 72 63 65
0003540 46 69 6c 65 01 00 0c 49 6e 6e 65 72 43 6c 61 73
0003550 73 65 73 01 00 19 52 75 6e 74 69 6d 65 56 69 73
0003560 69 62 6c 65 41 6e 6e 6f 74 61 74 69 6f 6e 73 01
0003570 00 0f 53 63 61 6c 61 49 6e 6c 69 6e 65 49 6e 66
0003580 6f 01 00 08 53 63 61 6c 61 53 69 67 00 21 00 02
0003590 00 04 00 01 00 06 00 06 00 12 00 34 00 35 00 00
00035a0 00 12 00 36 00 37 00 00 00 12 00 38 00 39 00 00
00035b0 00 02 00 3a 00 3b 00 00 00 42 00 3c 00 3d 00 00
00035c0 00 42 00 3e 00 3f 00 00 00 15 00 09 00 40 00 41
00035d0 00 01 02 6f 00 00 00 15 00 03 00 02 00 00 00 09
00035e0 b2 00 47 1a 2b b6 00 49 b0 00 00 00 00 00 09 00
00035f0 4a 00 4b 00 01 02 6f 00 00 00 15 00 03 00 02 00
0003600 00 00 09 b2 00 47 1a 2b b6 00 4d b0 00 00 00 00
0003610 00 09 00 4a 00 4e 00 01 02 6f 00 00 00 14 00 02
0003620 00 01 00 00 00 08 b2 00 47 1a b6 00 50 b0 00 00
0003630 00 00 00 09 00 51 00 4b 00 01 02 6f 00 00 00 15
0003640 00 03 00 02 00 00 00 09 b2 00 47 1a 2b b6 00 53
0003650 b0 00 00 00 00 00 09 00 51 00 4e 00 01 02 6f 00
0003660 00 00 14 00 02 00 01 00 00 00 08 b2 00 47 1a b6
0003670 00 55 b0 00 00 00 00 00 02 00 56 00 57 00 01 02
0003680 6f 00 00 00 6a 00 02 00 02 00 00 00 25 2a 59 4c
0003690 c2 2a b4 00 59 9a 00 10 2a 2a b8 00 5d b5 00 5f
00036a0 2a 04 b5 00 59 2b c3 a7 00 06 2b c3 bf 2a b4 00
00036b0 5f b0 00 01 00 04 00 18 00 1d 00 00 00 03 02 70
00036c0 00 00 00 0c 00 01 00 00 00 25 00 60 00 61 00 00
00036d0 02 71 00 00 00 06 00 01 00 00 00 14 02 72 00 00
00036e0 00 0d 00 03 fc 00 18 07 00 02 44 07 00 63 02 00
00036f0 01 00 3c 00 57 00 01 02 6f 00 00 00 4a 00 01 00
0003700 01 00 00 00 13 2a b4 00 59 9a 00 0a 2a b7 00 65
0003710 a7 00 07 2a b4 00 5f b0 00 00 00 03 02 70 00 00
0003720 00 0c 00 01 00 00 00 13 00 60 00 61 00 00 02 71
0003730 00 00 00 06 00 01 00 00 00 14 02 72 00 00 00 07
0003740 00 02 0e 43 07 00 67 00 01 00 38 00 68 00 01 02
0003750 6f 00 00 00 2f 00 01 00 01 00 00 00 05 2a b4 00
0003760 6a b0 00 00 00 02 02 70 00 00 00 0c 00 01 00 00
0003770 00 05 00 60 00 61 00 00 02 71 00 00 00 06 00 01
0003780 00 00 00 15 00 02 00 3a 00 6b 00 01 02 6f 00 00
0003790 00 2f 00 01 00 01 00 00 00 05 2a b4 00 6d b0 00
00037a0 00 00 02 02 70 00 00 00 0c 00 01 00 00 00 05 00
00037b0 60 00 61 00 00 02 71 00 00 00 06 00 01 00 00 00
00037c0 16 00 02 00 6e 00 6f 00 02 02 6f 00 00 00 3a 00
00037d0 02 00 02 00 00 00 06 2a 2b b5 00 6d b1 00 00 00
00037e0 02 02 70 00 00 00 16 00 02 00 00 00 06 00 60 00
00037f0 61 00 00 00 00 00 06 00 70 00 3b 00 01 02 71 00
0003800 00 00 06 00 01 00 00 00 16 02 73 00 00 00 05 01
0003810 00 70 00 10 00 01 00 71 00 6b 00 01 02 6f 00 00
0003820 01 d1 00 0c 00 0c 00 00 01 21 b2 00 76 b2 00 76
0003830 b6 00 7a b2 00 76 b6 00 7d 2a b4 00 7f b6 00 82
0003840 4c b2 00 87 2a b4 00 7f b6 00 8a c0 00 8c 4d b2
0003850 00 91 b2 00 91 b2 00 96 b2 00 91 b2 00 91 b6 00
0003860 9a b6 00 9e b2 00 a3 b6 00 a7 b6 00 ab 2a 2b ba
0003870 00 c2 00 00 b9 00 c6 02 00 c0 00 c4 b6 00 ca bb
0003880 00 cc 59 2a b6 00 ce b7 00 d2 b6 00 d6 b6 00 da
0003890 b6 00 ca b2 00 96 b2 00 91 b6 00 de b2 00 a3 b6
00038a0 00 a7 b6 00 ab 2a ba 00 e8 00 00 b9 00 c6 02 00
00038b0 c0 00 c4 b6 00 da 4e 2a b2 00 ed 2c 2d 3a 04 b2
00038c0 00 f2 2a b4 00 7f b6 00 f6 c0 00 f8 3a 05 b2 00
00038d0 fd 2a b4 00 7f b6 00 fe c0 01 00 3a 06 2b 3a 07
00038e0 b2 01 05 2a b4 00 7f b6 01 09 3a 08 b2 01 0e 19
00038f0 04 b6 01 12 3a 09 b2 01 0e 19 04 b6 01 16 3a 0a
0003900 b2 01 0e 19 04 b6 01 1a 3a 0b b2 01 0e 19 04 19
0003910 05 19 06 19 07 19 08 19 09 19 0a 19 0b b6 01 1e
0003920 13 01 20 2a b4 01 22 2c b6 01 26 2c b6 01 2a 2c
0003930 b6 01 2e 2b b6 01 32 b2 01 37 b6 01 3b b6 01 3f
0003940 c0 00 0c b7 01 41 2a b7 01 43 b0 00 00 00 02 02
0003950 70 00 00 00 7a 00 0c 00 93 00 63 00 70 01 44 00
0003960 04 00 a2 00 54 01 45 01 46 00 05 00 b1 00 45 01
0003970 47 01 48 00 06 00 b4 00 42 01 49 01 4a 00 07 00
0003980 c0 00 36 01 4b 01 4c 00 08 00 ca 00 2c 01 4d 01
0003990 4e 00 09 00 d4 00 22 01 4f 01 50 00 0a 00 de 00
00039a0 18 01 51 01 52 00 0b 00 16 01 0a 01 53 01 4a 00
00039b0 01 00 24 00 fc 01 54 01 55 00 02 00 8c 00 94 00
00039c0 d3 01 44 00 03 00 00 01 21 00 60 00 61 00 00 02
00039d0 71 00 00 00 1e 00 07 00 00 00 19 00 17 00 1a 00
00039e0 25 00 37 00 28 00 1c 00 55 00 37 00 8d 00 3e 01
00039f0 1c 00 3f 00 01 01 56 01 57 00 01 02 6f 00 00 00
0003a00 3f 00 03 00 01 00 00 00 15 b2 00 ed 2a b7 01 43
0003a10 b6 01 5b b2 01 37 b6 01 3b b6 01 3f 57 b1 00 00
0003a20 00 02 02 70 00 00 00 0c 00 01 00 00 00 15 00 60
0003a30 00 61 00 00 02 71 00 00 00 06 00 01 00 00 00 45
0003a40 10 19 01 5c 01 5d 00 02 02 6f 00 00 00 a0 00 08
0003a50 00 02 00 00 00 5c b2 00 91 b2 01 64 07 bd 00 c4
0003a60 59 03 bb 01 66 59 2a b6 00 ce b7 01 67 2b b6 01
0003a70 69 53 59 04 bb 01 6b 59 2a b6 00 ce b7 01 6c 2b
0003a80 b6 01 6d 53 59 05 bb 01 6f 59 2a b6 00 ce b7 01
0003a90 70 2b b6 01 71 53 59 06 bb 01 73 59 2a b6 00 ce
0003aa0 b7 01 74 2b b6 01 75 53 c0 01 77 b6 01 7b b6 01
0003ab0 7f b0 00 00 00 02 02 70 00 00 00 16 00 02 00 00
0003ac0 00 5c 01 5e 00 61 00 00 00 00 00 5c 01 5f 01 80
0003ad0 00 01 02 71 00 00 00 16 00 05 00 00 00 1e 00 0c
0003ae0 00 1f 00 1e 00 20 00 30 00 21 00 42 00 22 02 73
0003af0 00 00 00 09 02 01 5e 10 10 01 5f 00 10 10 19 01
0003b00 81 01 5d 00 02 02 6f 00 00 00 8a 00 08 00 02 00
0003b10 00 00 4a b2 00 91 b2 01 64 06 bd 00 c4 59 03 bb
0003b20 01 66 59 2a b6 00 ce b7 01 67 2b b6 01 69 53 59
0003b30 04 bb 01 6b 59 2a b6 00 ce b7 01 6c 2b b6 01 6d
0003b40 53 59 05 bb 01 6f 59 2a b6 00 ce b7 01 70 2b b6
0003b50 01 71 53 c0 01 77 b6 01 7b b6 01 7f b0 00 00 00
0003b60 02 02 70 00 00 00 16 00 02 00 00 00 4a 01 5e 00
0003b70 61 00 00 00 00 00 4a 01 5f 01 80 00 01 02 71 00
0003b80 00 00 12 00 04 00 00 00 25 00 0c 00 26 00 1e 00
0003b90 27 00 30 00 28 02 73 00 00 00 09 02 01 5e 10 10
0003ba0 01 5f 00 10 10 19 01 82 01 83 00 02 02 6f 00 00
0003bb0 01 28 00 09 00 05 00 00 00 ba b2 00 91 b2 01 64
0003bc0 10 07 bd 00 c4 59 03 bb 01 88 59 2a b6 00 ce b7
0003bd0 01 89 2c 19 04 b6 01 8d 2d b6 01 90 53 59 04 bb
0003be0 01 92 59 2a b6 00 ce b7 01 93 2c 19 04 b6 01 8d
0003bf0 b6 01 96 53 59 05 bb 01 98 59 2a b6 00 ce 2b b7
0003c00 01 9b 2c 19 04 b6 01 8d b6 01 9c 53 59 06 bb 01
0003c10 9e 59 2a b6 00 ce b7 01 9f 2c 19 04 b6 01 8d b6
0003c20 01 a0 53 59 07 bb 01 a2 59 2a b6 00 ce b7 01 a3
0003c30 2c 19 04 b6 01 8d b6 01 a4 53 59 08 bb 01 a6 59
0003c40 2a b6 00 ce 2b b7 01 a7 2c 19 04 b6 01 8d b6 01
0003c50 a8 53 59 10 06 bb 01 aa 59 2a b6 00 ce b7 01 ab
0003c60 2c 19 04 b6 01 8d b6 01 ac 53 c0 01 77 b6 01 7b
0003c70 b6 01 7f b0 00 00 00 02 02 70 00 00 00 34 00 05
0003c80 00 00 00 ba 01 5e 00 61 00 00 00 00 00 ba 01 84
0003c90 01 4a 00 01 00 00 00 ba 01 5f 01 80 00 02 00 00
0003ca0 00 ba 01 85 01 ad 00 03 00 00 00 ba 01 86 01 ae
0003cb0 00 04 02 71 00 00 00 22 00 08 00 00 00 2c 00 0d
0003cc0 00 2d 00 25 00 2e 00 3c 00 2f 00 54 00 30 00 6b
0003cd0 00 31 00 82 00 32 00 9b 00 33 02 73 00 00 00 15
0003ce0 05 01 5e 10 10 01 84 00 10 01 5f 00 10 01 85 00
0003cf0 10 01 86 00 10 10 19 01 af 01 b0 00 02 02 6f 00
0003d00 00 00 72 00 05 00 04 00 00 00 2a b2 00 96 b2 00
0003d10 91 b2 00 91 b6 01 b5 b6 01 b8 b2 00 a3 b6 00 a7
0003d20 b6 00 ab 2a 2b 2c 2d ba 01 bf 00 00 b9 00 c6 02
0003d30 00 c0 00 c4 b0 00 00 00 02 02 70 00 00 00 2a 00
0003d40 04 00 00 00 2a 01 5e 00 61 00 00 00 00 00 2a 01
0003d50 84 01 4a 00 01 00 00 00 2a 01 5f 01 80 00 02 00
0003d60 00 00 2a 01 b1 01 ad 00 03 02 71 00 00 00 06 00
0003d70 01 00 00 00 2b 02 73 00 00 00 11 04 01 5e 10 10
0003d80 01 84 00 10 01 5f 00 10 01 b1 00 10 10 19 00 b5
0003d90 00 b6 00 02 02 6f 00 00 00 bd 00 05 00 03 00 00
0003da0 00 6b b2 00 91 b2 00 91 b2 00 96 b2 00 91 b6 01
0003db0 c3 b6 01 c7 2a 2c ba 01 d0 00 00 b9 00 c6 02 00
0003dc0 c0 00 c4 b6 00 ca b2 00 96 b2 00 91 b6 01 d3 b6
0003dd0 01 c7 2a 2c ba 01 d7 00 00 b9 00 c6 02 00 c0 00
0003de0 c4 b6 00 da b6 00 ca b2 00 96 b2 00 91 b6 01 da
0003df0 b2 00 a3 b6 00 a7 b6 00 ab 2a 2b 2c ba 01 e1 00
0003e00 00 b9 00 c6 02 00 c0 00 c4 b6 00 da b0 00 00 00
0003e10 02 02 70 00 00 00 20 00 03 00 00 00 6b 01 5e 00
0003e20 61 00 00 00 00 00 6b 01 84 01 4a 00 01 00 00 00
0003e30 6b 01 c0 01 80 00 02 02 71 00 00 00 1a 00 06 00
0003e40 00 00 24 00 03 00 1d 00 12 00 1e 00 24 00 24 00
0003e50 30 00 25 00 45 00 2a 02 73 00 00 00 0d 03 01 5e
0003e60 10 10 01 84 00 10 01 c0 00 10 10 19 01 e2 01 e3
0003e70 00 02 02 6f 00 00 00 de 00 08 00 02 00 00 00 97
0003e80 2a b6 01 e6 b6 01 ea b9 01 f0 01 00 99 00 5c 2a
0003e90 b6 01 e6 b6 01 ea bb 01 f2 59 b2 01 64 06 bd 01
0003ea0 f4 59 03 13 01 f6 53 59 04 13 01 f8 53 59 05 13
0003eb0 01 fa 53 c0 01 77 b6 01 7b b7 01 fd b2 01 64 05
0003ec0 bd 00 04 59 03 2b b6 02 03 b6 02 08 53 59 04 2b
0003ed0 b6 02 0c b6 02 0d 53 b6 02 11 b6 02 15 b9 02 19
0003ee0 02 00 b2 02 1f a7 00 06 b2 02 1f 57 b2 02 24 b2
0003ef0 02 29 b2 02 2e b6 02 32 b2 02 29 b6 02 35 b2 02
0003f00 29 b6 02 39 b2 02 29 b6 02 3d b6 02 40 b2 02 45
0003f10 b6 02 49 b6 02 4c b0 00 00 00 03 02 70 00 00 00
0003f20 16 00 02 00 00 00 97 01 5e 00 61 00 00 00 00 00
0003f30 97 01 e4 02 4d 00 01 02 71 00 00 00 0a 00 02 00
0003f40 00 00 39 00 6c 00 3a 02 72 00 00 00 09 00 02 fb
0003f50 00 68 42 07 02 1b 02 73 00 00 00 09 02 01 5e 10
0003f60 10 01 e4 00 10 10 19 00 df 00 e0 00 02 02 6f 00
0003f70 00 00 42 00 03 00 02 00 00 00 0e b2 00 91 2a 2b
0003f80 ba 02 56 00 00 b6 02 5a b0 00 00 00 02 02 70 00
0003f90 00 00 16 00 02 00 00 00 0e 01 5e 00 61 00 00 00
0003fa0 00 00 0e 02 4e 02 4d 00 01 02 71 00 00 00 06 00
0003fb0 01 00 00 00 38 02 73 00 00 00 09 02 01 5e 10 10
0003fc0 02 4e 00 10 00 01 00 cf 02 5b 00 02 02 6f 00 00
0003fd0 00 68 00 02 00 04 00 00 00 18 2a 1b b5 01 22 2a
0003fe0 2d b5 00 7f 2a b7 02 5e 2a b8 02 62 2a 2c b5 00
0003ff0 6a b1 00 00 00 02 02 70 00 00 00 2a 00 04 00 00
0004000 00 18 00 60 00 61 00 00 00 00 00 18 00 34 00 35
0004010 00 01 00 00 00 18 02 5c 00 39 00 02 00 00 00 18
0004020 00 36 00 37 00 03 02 71 00 00 00 0e 00 03 00 00
0004030 00 14 00 12 00 15 00 17 00 14 02 73 00 00 00 0d
0004040 03 00 34 00 10 02 5c 00 10 00 36 00 10 10 0a 02
0004050 63 02 64 00 01 02 6f 00 00 00 13 00 01 00 01 00
0004060 00 00 07 2a ba 02 6e 00 00 b0 00 00 00 00 00 06
0004070 02 74 00 00 00 84 00 08 00 b2 00 06 00 b4 00 b9
0004080 00 bb 00 bc 00 bd 00 bf 00 b2 00 06 00 b4 00 e3
0004090 00 e5 00 bc 00 bd 00 bf 00 b2 00 06 00 b4 01 bb
00040a0 01 bd 00 bc 00 bd 00 bf 00 b2 00 06 01 c9 01 cc
00040b0 01 cd 00 bc 00 bd 00 bf 00 b2 00 06 01 c9 01 d6
00040c0 01 cd 00 bc 00 bd 00 bf 00 b2 00 06 00 b4 01 dd
00040d0 01 df 00 bc 00 bd 00 bf 00 b2 00 06 01 c9 02 51
00040e0 02 53 00 bc 00 bd 00 bf 02 6b 00 07 00 b9 00 e3
00040f0 01 bb 01 cc 01 d6 01 dd 02 51 02 75 00 00 00 02
0004100 00 07 02 76 00 00 00 4a 00 09 00 0c 00 0e 00 0f
0004110 00 19 00 11 00 13 00 14 00 19 00 16 00 18 00 19
0004120 04 09 00 1b 00 1d 00 1e 00 01 00 20 00 1d 00 21
0004130 00 01 00 23 00 25 00 26 00 09 00 28 00 02 00 29
0004140 00 09 00 2b 00 2d 00 2e 00 19 00 30 00 32 00 33
0004150 04 09 02 77 00 00 00 0b 00 01 00 08 00 01 00 09
0004160 73 00 0a 02 78 00 00 00 4f 01 00 00 0f 00 b5 00
0004170 b6 01 01 5c 01 5d 01 01 81 01 5d 01 01 af 01 b0
0004180 01 01 82 01 83 01 00 df 00 e0 01 01 e2 01 e3 01
0004190 00 cf 02 5b 00 00 3a 00 6b 01 00 6e 00 6f 01 00
00041a0 56 00 57 01 00 3c 00 57 00 00 38 00 68 00 00 71
00041b0 00 6b 00 01 56 01 57 00 02 79 00 00 00 03 05 00
00041c0 00
00041c1
```
